Workbook

Sheet Citas New New
C1: Region | D1: Owner Name | E1: Subject | F1: Account Legal Name | G1: Top Parent Account | H1: Date | I1: Comments | J1: Top Parent | K1: New New | L1: Last Date | M1: Diferencia de dias | N1: Last Owner | O1: Last Región | P1: Account status | Q1: Validación Owner | R1: Tiempo | S1: Owner de la cuenta | T1: Validación Owner-Cuenta-Cita | U1: Estado | V1: EXT_REF_ID | W1: Total exposure | X1: Industry
C2: =VLOOKUP(D2,Diccionario!A:B,2,0) -> Estructurados Core | D2: Fernanda Rangel | E2: Meeting | F2: Omnibus Unidos Regiomontanos | H2: 46078 | I2: Se platicó con la empresa, el nombre comercial es APOLO, tienen viajes nacionales, e incursionan tambien en paquetería, compraron camiones y se los entregaron este diciembre 2025, el cliente tiene créditos caros, por lo que se buscará un refinanciamiento, cada camiones vale enre 8 y 12 mdp, los de ellos, al comprarlos doble piso valen 12 mdp, compran anualmente entre 4 y 5 camiones. Se pidió el listado de activos y el cuadro de pasivos. 40 camiones. Marca Volvo: Doubledeckers. Se financia con SOFOMS: Unifin, y locales. Volvo financial. Tasa calcula all in. 60 meses. Pains: Financiamientos con costo alto. Se detectó que hay oportunidad de refinanciamiento. No se proporcionó información de saldos, ni plazos remanentes. Objeciones: Booth Collateral. | J2: =IF(G2="",F2,G2) -> Omnibus Unidos Regiomontanos | K2: =IFERROR(VLOOKUP(Table1[[#This Row],[Top Parent]],'1.- Citas sin this week'!G:G,1,0),"New New") -> New New | L2: =_xlfn.XLOOKUP(Table1[[#This Row],[Top Parent]],Table3[Top Parent],Table3[Date]) -> #N/A | M2: =Table1[[#This Row],[Date]]-Table1[[#This Row],[Last Date]] -> #N/A | N2: =_xlfn.XLOOKUP(Table1[[#This Row],[Top Parent]],Table3[Top Parent],Table3[Owner Name]) -> #N/A | Q2: =IF(Table1[[#This Row],[Last Owner]]=Table1[[#This Row],[Owner Name]],"No","Si") -> #N/A | R2: =IF(Table1[[#This Row],[Diferencia de dias]]>182,"Si","No") -> #N/A | S2: Fernanda Rangel | T2: =IF(Table1[[#This Row],[Owner de la cuenta]]=Table1[[#This Row],[Owner Name]],"Si","No") -> Si | U2: Nuevo León | V2: SFAC0006110894 | X2: Transportation
C3: =VLOOKUP(D3,Diccionario!A:B,2,0) -> Estructurados Core | D3: Fernanda Rangel | E3: Meeting | F3: Aislamientos Y Forros Industriales | H3: 46077 | I3: Se platicó con la empresa, se dedican principalmente para aislantes en proyectos para las empresas, si venden de forma recurrente pero no cumple con el mínimo, los que cumplen llegan a ser proyectos, no les agradó la idea de que se tiene que otorgar un token, lo que comentan es que son muy cerrados y que solo la administradora tiene acceso al token, por lo que factoraje no lo ven viable, de arrendamiento sería por vehículos, compran entre 4 o 5 carros al año para los vendedores | J3: =IF(G3="",F3,G3) -> Aislamientos Y Forros Industriales | K3: =IFERROR(VLOOKUP(Table1[[#This Row],[Top Parent]],'1.- Citas sin this week'!G:G,1,0),"New New") -> New New | L3: =_xlfn.XLOOKUP(Table1[[#This Row],[Top Parent]],Table3[Top Parent],Table3[Date]) -> #N/A | M3: =Table1[[#This Row],[Date]]-Table1[[#This Row],[Last Date]] -> #N/A | N3: =_xlfn.XLOOKUP(Table1[[#This Row],[Top Parent]],Table3[Top Parent],Table3[Owner Name]) -> #N/A | P3: Prospect | Q3: =IF(Table1[[#This Row],[Last Owner]]=Table1[[#This Row],[Owner Name]],"No","Si") -> #N/A | R3: =IF(Table1[[#This Row],[Diferencia de dias]]>182,"Si","No") -> #N/A | S3: Fernanda Rangel | T3: =IF(Table1[[#This Row],[Owner de la cuenta]]=Table1[[#This Row],[Owner Name]],"Si","No") -> Si | U3: Nuevo León | V3: SFAC0006027147 | X3: Industrial Products & Services
C4: =VLOOKUP(D4,Diccionario!A:B,2,0) -> México 1 | D4: Kenia Martinez | E4: Email | F4: Centro Médico De Toluca | H4: 46080 | I4: Eduardo, Ana, me gustaría proponerles una reunión para presentarme formalmente y dar continuidad a la operación del año pasado, en la que aprobamos una línea de arrendamiento por 60 MDP para equipo médico y en la cual actualmente cuentan con una disponibilidad aproximada de 37,162,100.31 MDP para nuevas operaciones. ¿Cómo están de agenda el próximo jueves para reunirnos? | J4: =IF(G4="",F4,G4) -> Centro Médico De Toluca | K4: =IFERROR(VLOOKUP(Table1[[#This Row],[Top Parent]],'1.- Citas sin this week'!G:G,1,0),"New New") -> Centro Médico De Toluca | L4: =_xlfn.XLOOKUP(Table1[[#This Row],[Top Parent]],Table3[Top Parent],Table3[Date]) -> 46072 | M4: =Table1[[#This Row],[Date]]-Table1[[#This Row],[Last Date]] -> 8 | N4: =_xlfn.XLOOKUP(Table1[[#This Row],[Top Parent]],Table3[Top Parent],Table3[Owner Name]) -> Kenia Martinez | P4: Active | Q4: =IF(Table1[[#This Row],[Last Owner]]=Table1[[#This Row],[Owner Name]],"No","Si") -> No | R4: =IF(Table1[[#This Row],[Diferencia de dias]]>182,"Si","No") -> No | S4: Kenia Martinez | T4: =IF(Table1[[#This Row],[Owner de la cuenta]]=Table1[[#This Row],[Owner Name]],"Si","No") -> Si | U4: Estado de México | V4: SFAC0005706024 | W4: 18920958 | X4: Healthcare
C5: =VLOOKUP(D5,Diccionario!A:B,2,0) -> México 1 | D5: Kenia Martinez | E5: Meeting | F5: Orbia Advance Corporation | H5: 46080 | I5: Video C. Equipo NORMET. Dia: Martes 24 7pm. Revisamos temas de facturación, CAL tiempos estimados de firmas y pagos. Ya emitieron pre factura. | J5: =IF(G5="",F5,G5) -> Orbia Advance Corporation | K5: =IFERROR(VLOOKUP(Table1[[#This Row],[Top Parent]],'1.- Citas sin this week'!G:G,1,0),"New New") -> New New | L5: =_xlfn.XLOOKUP(Table1[[#This Row],[Top Parent]],Table3[Top Parent],Table3[Date]) -> #N/A | M5: =Table1[[#This Row],[Date]]-Table1[[#This Row],[Last Date]] -> #N/A | N5: =_xlfn.XLOOKUP(Table1[[#This Row],[Top Parent]],Table3[Top Parent],Table3[Owner Name]) -> #N/A | P5: Prospect | Q5: =IF(Table1[[#This Row],[Last Owner]]=Table1[[#This Row],[Owner Name]],"No","Si") -> #N/A | R5: =IF(Table1[[#This Row],[Diferencia de dias]]>182,"Si","No") -> #N/A | S5: Areli Canche | T5: =IF(Table1[[#This Row],[Owner de la cuenta]]=Table1[[#This Row],[Owner Name]],"Si","No") -> No | U5: Ciudad de México | V5: SFAC0006110706 | X5: Metals, Mining & Metals Fabrication
C6: =VLOOKUP(D6,Diccionario!A:B,2,0) -> Guadalajara | D6: Miguel Ortiz | E6: Meeting | F6: Trabba Prefabricados Concretos | H6: 46080 | I6: Requerimiento: Se agendo cita con Gaby Moreno, Gerente de finanzas de la empresa Trabba Prefabricados Concretos, Buscan una linea de crédito de 1 mdp, Giro: Productos prefabricados de concreto, operan desde hace 20 años, en 2025 vendieron 160 mdp, buen buro de crédito, no trabaja con gobierno, la empresa esta en Zapopan Jalisco, pagina de internet: https:trabba.com.mx | J6: =IF(G6="",F6,G6) -> Trabba Prefabricados Concretos | K6: =IFERROR(VLOOKUP(Table1[[#This Row],[Top Parent]],'1.- Citas sin this week'!G:G,1,0),"New New") -> Trabba Prefabricados Concretos | L6: =_xlfn.XLOOKUP(Table1[[#This Row],[Top Parent]],Table3[Top Parent],Table3[Date]) -> 45923 | M6: =Table1[[#This Row],[Date]]-Table1[[#This Row],[Last Date]] -> 157 | N6: =_xlfn.XLOOKUP(Table1[[#This Row],[Top Parent]],Table3[Top Parent],Table3[Owner Name]) -> Miguel Ortiz | P6: Prospect | Q6: =IF(Table1[[#This Row],[Last Owner]]=Table1[[#This Row],[Owner Name]],"No","Si") -> No | R6: =IF(Table1[[#This Row],[Diferencia de dias]]>182,"Si","No") -> No | S6: Miguel Ortiz | T6: =IF(Table1[[#This Row],[Owner de la cuenta]]=Table1[[#This Row],[Owner Name]],"Si","No") -> Si | U6: Jalisco | V6: SFAC0006103382 | X6: Construction
C7: =VLOOKUP(D7,Diccionario!A:B,2,0) -> México 1 | D7: Patricia Jurado | E7: Reunión de Seguimiento | F7: Natura | H7: 46080 | I7: Presentación de Porpuesta Se presento propuesta, cliente me pide agregar algunos datos adicionales y se acuerda hablar una propuesta más por una línea más grande que cubra los proyectos que vienen en 2026, así como realizarles un ejercicio de eficiencia en los dos escenarios. Se acuerda presentar siguiente semana. Hola Carlos, Antes que nada, muchas gracias por la llamada y el espacio que nos diste el día de hoy. Considero que avanzamos de manera muy positiva y logramos aterrizar varios puntos clave que integraré en la propuesta final. Para poder completarla, ¿me podrías apoyar por favor con el monto total estimado de los proyectos 2026 que podrían entrar dentro del esquema de financiamiento? Esto me permitirá incorporar ese onto total en los ejercicios de eficiencia que estaré preparando. Si pudieras compartirme ese dato el día de hoy, me ayudaría mucho para tenerte toda la información lista el lunes por la tarde. Te agradezco de antemano el apoyo, Saludos | J7: =IF(G7="",F7,G7) -> Natura | K7: =IFERROR(VLOOKUP(Table1[[#This Row],[Top Parent]],'1.- Citas sin this week'!G:G,1,0),"New New") -> Natura | L7: =_xlfn.XLOOKUP(Table1[[#This Row],[Top Parent]],Table3[Top Parent],Table3[Date]) -> 46050 | M7: =Table1[[#This Row],[Date]]-Table1[[#This Row],[Last Date]] -> 30 | N7: =_xlfn.XLOOKUP(Table1[[#This Row],[Top Parent]],Table3[Top Parent],Table3[Owner Name]) -> Patricia Jurado | P7: Active | Q7: =IF(Table1[[#This Row],[Last Owner]]=Table1[[#This Row],[Owner Name]],"No","Si") -> No | R7: =IF(Table1[[#This Row],[Diferencia de dias]]>182,"Si","No") -> No | S7: Patricia Jurado | T7: =IF(Table1[[#This Row],[Owner de la cuenta]]=Table1[[#This Row],[Owner Name]],"Si","No") -> Si | U7: Ciudad de México | V7: 1-52PEUP | X7: Chemicals & Plastics
C8: =VLOOKUP(D8,Diccionario!A:B,2,0) -> LMM 5 | D8: Monserrat Villanueva | E8: Meeting | F8: Impocarnes | G8: Atelier Post CO | H8: 46080 | I8: Junta con dueños, opp inmediata de 20mdp para equipar planta en Ecatepec, posible loan para nueva planta. | J8: =IF(G8="",F8,G8) -> Atelier Post CO | K8: =IFERROR(VLOOKUP(Table1[[#This Row],[Top Parent]],'1.- Citas sin this week'!G:G,1,0),"New New") -> Atelier Post CO | L8: =_xlfn.XLOOKUP(Table1[[#This Row],[Top Parent]],Table3[Top Parent],Table3[Date]) -> 45912 | M8: =Table1[[#This Row],[Date]]-Table1[[#This Row],[Last Date]] -> 168 | N8: =_xlfn.XLOOKUP(Table1[[#This Row],[Top Parent]],Table3[Top Parent],Table3[Owner Name]) -> Monserrat Villanueva | P8: Prospect | Q8: =IF(Table1[[#This Row],[Last Owner]]=Table1[[#This Row],[Owner Name]],"No","Si") -> No | R8: =IF(Table1[[#This Row],[Diferencia de dias]]>182,"Si","No") -> No | S8: Monserrat Villanueva | T8: =IF(Table1[[#This Row],[Owner de la cuenta]]=Table1[[#This Row],[Owner Name]],"Si","No") -> Si | U8: Ciudad de México | V8: SFAC0006087378 | X8: Food Bev & Ag
C9: =VLOOKUP(D9,Diccionario!A:B,2,0) -> LMM 3 | D9: Braulio Martinez | E9: Meeting | F9: Soluciones Logísticas DH | G9: Logistica Interncional De Mercancias | H9: 46080 | I9: Desayuno con Intermerk para conocer a Octavio, platicar sobre proyectos futuros. | J9: =IF(G9="",F9,G9) -> Logistica Interncional De Mercancias | K9: =IFERROR(VLOOKUP(Table1[[#This Row],[Top Parent]],'1.- Citas sin this week'!G:G,1,0),"New New") -> Logistica Interncional De Mercancias | L9: =_xlfn.XLOOKUP(Table1[[#This Row],[Top Parent]],Table3[Top Parent],Table3[Date]) -> 46014 | M9: =Table1[[#This Row],[Date]]-Table1[[#This Row],[Last Date]] -> 66 | N9: =_xlfn.XLOOKUP(Table1[[#This Row],[Top Parent]],Table3[Top Parent],Table3[Owner Name]) -> Braulio Martinez | P9: Active | Q9: =IF(Table1[[#This Row],[Last Owner]]=Table1[[#This Row],[Owner Name]],"No","Si") -> No | R9: =IF(Table1[[#This Row],[Diferencia de dias]]>182,"Si","No") -> No | S9: Braulio Martinez | T9: =IF(Table1[[#This Row],[Owner de la cuenta]]=Table1[[#This Row],[Owner Name]],"Si","No") -> Si | U9: Estado de México | V9: SFAC0006110023 | W9: 6089998.8 | X9: Transportation
C10: =VLOOKUP(D10,Diccionario!A:B,2,0) -> México 2 | D10: David Shaw | E10: Meeting | F10: Vimar Construcciones | H10: 46080 | I10: Reunión con CFO, se platico sobre las oportunidades de plataformas y todo terrenos zoomlion, se buscara avanzar con las propuestas para estar en la línea con condiciones competitivas. | J10: =IF(G10="",F10,G10) -> Vimar Construcciones | K10: =IFERROR(VLOOKUP(Table1[[#This Row],[Top Parent]],'1.- Citas sin this week'!G:G,1,0),"New New") -> Vimar Construcciones | L10: =_xlfn.XLOOKUP(Table1[[#This Row],[Top Parent]],Table3[Top Parent],Table3[Date]) -> 46048 | M10: =Table1[[#This Row],[Date]]-Table1[[#This Row],[Last Date]] -> 32 | N10: =_xlfn.XLOOKUP(Table1[[#This Row],[Top Parent]],Table3[Top Parent],Table3[Owner Name]) -> David Shaw | P10: Prospect | Q10: =IF(Table1[[#This Row],[Last Owner]]=Table1[[#This Row],[Owner Name]],"No","Si") -> No | R10: =IF(Table1[[#This Row],[Diferencia de dias]]>182,"Si","No") -> No | S10: David Shaw | T10: =IF(Table1[[#This Row],[Owner de la cuenta]]=Table1[[#This Row],[Owner Name]],"Si","No") -> Si | U10: Ciudad de México | V10: SFAC0006096575 | X10: Construction
C11: =VLOOKUP(D11,Diccionario!A:B,2,0) -> Estructurados Core | D11: Josue Olvera | E11: Meeting | F11: AVICOLA ABE | H11: 46080 | I11: Reunión con cliente de seguimiento, indica que continúa en cotización de las granjas con distintos proveedores. Se contempla terminar expediente para el martes. | J11: =IF(G11="",F11,G11) -> AVICOLA ABE | K11: =IFERROR(VLOOKUP(Table1[[#This Row],[Top Parent]],'1.- Citas sin this week'!G:G,1,0),"New New") -> AVICOLA ABE | L11: =_xlfn.XLOOKUP(Table1[[#This Row],[Top Parent]],Table3[Top Parent],Table3[Date]) -> 46034 | M11: =Table1[[#This Row],[Date]]-Table1[[#This Row],[Last Date]] -> 46 | N11: =_xlfn.XLOOKUP(Table1[[#This Row],[Top Parent]],Table3[Top Parent],Table3[Owner Name]) -> Josue Olvera | P11: Prospect | Q11: =IF(Table1[[#This Row],[Last Owner]]=Table1[[#This Row],[Owner Name]],"No","Si") -> No | R11: =IF(Table1[[#This Row],[Diferencia de dias]]>182,"Si","No") -> No | S11: Josue Olvera | T11: =IF(Table1[[#This Row],[Owner de la cuenta]]=Table1[[#This Row],[Owner Name]],"Si","No") -> Si | U11: Sinaloa | V11: SFAC0006075787 | X11: Food Bev & Ag
C12: =VLOOKUP(D12,Diccionario!A:B,2,0) -> LMM 1 | D12: Roberto Anaya | E12: Meeting | F12: Representaciones Cyecsa | H12: 46080 | I12: Se reviso propuesta y comparación en base a un crédito simple, el prospecto quedo de revisar la información con su fiscalista y regresar con nosotros. | J12: =IF(G12="",F12,G12) -> Representaciones Cyecsa | K12: =IFERROR(VLOOKUP(Table1[[#This Row],[Top Parent]],'1.- Citas sin this week'!G:G,1,0),"New New") -> Representaciones Cyecsa | L12: =_xlfn.XLOOKUP(Table1[[#This Row],[Top Parent]],Table3[Top Parent],Table3[Date]) -> 46036 | M12: =Table1[[#This Row],[Date]]-Table1[[#This Row],[Last Date]] -> 44 | N12: =_xlfn.XLOOKUP(Table1[[#This Row],[Top Parent]],Table3[Top Parent],Table3[Owner Name]) -> Roberto Anaya | P12: Prospect | Q12: =IF(Table1[[#This Row],[Last Owner]]=Table1[[#This Row],[Owner Name]],"No","Si") -> No | R12: =IF(Table1[[#This Row],[Diferencia de dias]]>182,"Si","No") -> No | S12: Roberto Anaya | T12: =IF(Table1[[#This Row],[Owner de la cuenta]]=Table1[[#This Row],[Owner Name]],"Si","No") -> Si | U12: Jalisco | V12: 1-4WNQ-53 | X12: Forest Products
C13: =VLOOKUP(D13,Diccionario!A:B,2,0) -> Monterrey | D13: Edgar Rodriguez | E13: Meeting | F13: CORPORATIVO DE ACERO Y SERVICIOS ASOCIADOS | H13: 46080 | I13: Visita con el director general de la empresa, dentro del grupo empresarial son 3 razones sociales pero todas venden por debajo de los 30mdp, tienen necesidades de líneas de crédito para factoraje por un monto aproximado de 1mdp. Por las ventas de la empresa y montos de línea es un segmento que no podemos cubrir | J13: =IF(G13="",F13,G13) -> CORPORATIVO DE ACERO Y SERVICIOS ASOCIADOS | K13: =IFERROR(VLOOKUP(Table1[[#This Row],[Top Parent]],'1.- Citas sin this week'!G:G,1,0),"New New") -> New New | L13: =_xlfn.XLOOKUP(Table1[[#This Row],[Top Parent]],Table3[Top Parent],Table3[Date]) -> #N/A | M13: =Table1[[#This Row],[Date]]-Table1[[#This Row],[Last Date]] -> #N/A | N13: =_xlfn.XLOOKUP(Table1[[#This Row],[Top Parent]],Table3[Top Parent],Table3[Owner Name]) -> #N/A | P13: Prospect | Q13: =IF(Table1[[#This Row],[Last Owner]]=Table1[[#This Row],[Owner Name]],"No","Si") -> #N/A | R13: =IF(Table1[[#This Row],[Diferencia de dias]]>182,"Si","No") -> #N/A | S13: Areli Canche | T13: =IF(Table1[[#This Row],[Owner de la cuenta]]=Table1[[#This Row],[Owner Name]],"Si","No") -> No | U13: Chihuahua | V13: SFAC0006058916 | X13: Construction
C14: =VLOOKUP(D14,Diccionario!A:B,2,0) -> Estructurados Core | D14: Josue Olvera | E14: Meeting | F14: ARTEGO | H14: 46076 | I14: Se sostuvo reunión con Felipe Arteaga, empresario con trayectoria de 35 años operando en empresa familiar Frigorizados la Huerta. Se independizó del negocio y decidió operar nuevas línes de negocio. entre ellos, Lácteos Ticoy que fabricó paletas a nivel industrial y empresa que actualmente ya no opera, ARTEGO, que comercializa productos dle extranjero en México, y PAZO GLOBAL, empresa en EEUU que comercializa productos mexicanos en el extranjero. La operación original de paletas cerró debido a temas regulatorios relacionados con permisos de Cofepris, lo que llevó a Felipe a desarrollar un nuevo modelo enfocado en comercialización e importación. Actualmente opera principalmente a través de ARTEGO Logística, empresa con 7 años de facturación bajo un esquema de trading y distribución. El modelo consiste en comprar producto nacional e internacional, importar vía Manzanillo (actualmente con cuatro contenedores en puerto), almacenar y etiquetar mediante terceros, y distribuir a cadenas nacionales. Comercializan productos en las principales cadenas de autoservicio como Walmart (incluyendo Sam?s) y Soriana. Todo el componente operativo es tercerizado, incluyendo fletes, almacenaje y etiquetado, lo que reduce CAPEX pero incrementa la dependencia de flujo constante. El negocio es intensivo en capital de trabajo y funciona bajo un modelo de rotación. Facturaron aproximadamente 160 millones de pesos en el ejercicio anterior y proyectan cerrar el año en 280 millones de pesos, lo que representa un crecimiento cercano al 75%. La facturación se realiza en pesos y la mayoría de las compras son en USD. Sin embargo, cuando detectan volatilidad en el mercado, implementan coberturas cambiarias para proteger márgenes. En cuanto a financiamiento, utilizan factoraje con las cadenas, particularmente con Walmart y Sam?s, así como con Soriana, quien anticipa hasta el 80% del valor de la factura. Señalan que el costo financiero con Walmart es elevado. Los plazos de pago son de aproximadamente 45 días para productos refrigerados y 60 días para productos secos, lo que presiona el ciclo de conversión de efectivo. También mantienen línea de crédito con Fincargo para soporte operativo. El negocio depende estructuralmente del financiamiento para sostener crecimiento, especialmente considerando el volumen de importaciones y la necesidad de mantener inventario disponible. Adicionalmente, cuentan con Pazo Global como vehículo estratégico para representar marcas mexicanas en otros países y traer productos internacionales para su comercialización en México. La intención es escalar a una dimensión mayor mediante esta plataforma, lo que implicará mayor requerimiento de capital de trabajo y posiblemente financiamiento estructurado para expansión. Se identifica que la principal necesidad está en la optimización de capital de trabajo y en la reducción del costo financiero actual. Existe oportunidad de estructurar factoraje que mejoren su operatividad. El modelo no es intensivo en activos fijos, sino en flujo y financiamiento. Próximo paso será solicitar información financiera firmarse en Davincci, información preliminar, así como llamada con el área de factoraje para la oportunidad detectada. | J14: =IF(G14="",F14,G14) -> ARTEGO | K14: =IFERROR(VLOOKUP(Table1[[#This Row],[Top Parent]],'1.- Citas sin this week'!G:G,1,0),"New New") -> New New | L14: =_xlfn.XLOOKUP(Table1[[#This Row],[Top Parent]],Table3[Top Parent],Table3[Date]) -> #N/A | M14: =Table1[[#This Row],[Date]]-Table1[[#This Row],[Last Date]] -> #N/A | N14: =_xlfn.XLOOKUP(Table1[[#This Row],[Top Parent]],Table3[Top Parent],Table3[Owner Name]) -> #N/A | P14: Prospect | Q14: =IF(Table1[[#This Row],[Last Owner]]=Table1[[#This Row],[Owner Name]],"No","Si") -> #N/A | R14: =IF(Table1[[#This Row],[Diferencia de dias]]>182,"Si","No") -> #N/A | S14: Josue Olvera | T14: =IF(Table1[[#This Row],[Owner de la cuenta]]=Table1[[#This Row],[Owner Name]],"Si","No") -> Si | U14: Aguascalientes | V14: SFAC0006103702 | X14: Retail
C15: =VLOOKUP(D15,Diccionario!A:B,2,0) -> México 1 | D15: Armando Estrada | E15: Reunión de Seguimiento | F15: Ubictum | G15: Nadro | H15: 46080 | I15: Reunión para presentar ejercicio MXN 140m. | J15: =IF(G15="",F15,G15) -> Nadro | K15: =IFERROR(VLOOKUP(Table1[[#This Row],[Top Parent]],'1.- Citas sin this week'!G:G,1,0),"New New") -> Nadro | L15: =_xlfn.XLOOKUP(Table1[[#This Row],[Top Parent]],Table3[Top Parent],Table3[Date]) -> 46070 | M15: =Table1[[#This Row],[Date]]-Table1[[#This Row],[Last Date]] -> 10 | N15: =_xlfn.XLOOKUP(Table1[[#This Row],[Top Parent]],Table3[Top Parent],Table3[Owner Name]) -> Armando Estrada | P15: Lost | Q15: =IF(Table1[[#This Row],[Last Owner]]=Table1[[#This Row],[Owner Name]],"No","Si") -> No | R15: =IF(Table1[[#This Row],[Diferencia de dias]]>182,"Si","No") -> No | S15: Armando Estrada | T15: =IF(Table1[[#This Row],[Owner de la cuenta]]=Table1[[#This Row],[Owner Name]],"Si","No") -> Si | U15: Ciudad de México | V15: SFAC0006006404 | W15: 0 | X15: Transportation
C16: =VLOOKUP(D16,Diccionario!A:B,2,0) -> LMM 3 | D16: Braulio Martinez | E16: Meeting | F16: GRUPO ALIANZA-JT | G16: JC MOLDS | H16: 46080 | I16: Firma de contrato de arrendamiento | J16: =IF(G16="",F16,G16) -> JC MOLDS | K16: =IFERROR(VLOOKUP(Table1[[#This Row],[Top Parent]],'1.- Citas sin this week'!G:G,1,0),"New New") -> JC MOLDS | L16: =_xlfn.XLOOKUP(Table1[[#This Row],[Top Parent]],Table3[Top Parent],Table3[Date]) -> 46056 | M16: =Table1[[#This Row],[Date]]-Table1[[#This Row],[Last Date]] -> 24 | N16: =_xlfn.XLOOKUP(Table1[[#This Row],[Top Parent]],Table3[Top Parent],Table3[Owner Name]) -> Braulio Martinez | P16: Dormant | Q16: =IF(Table1[[#This Row],[Last Owner]]=Table1[[#This Row],[Owner Name]],"No","Si") -> No | R16: =IF(Table1[[#This Row],[Diferencia de dias]]>182,"Si","No") -> No | S16: Braulio Martinez | T16: =IF(Table1[[#This Row],[Owner de la cuenta]]=Table1[[#This Row],[Owner Name]],"Si","No") -> Si | U16: Puebla | V16: SFAC0006083885 | W16: 3117751 | X16: Industrial Products & Services
C17: =VLOOKUP(D17,Diccionario!A:B,2,0) -> LMM 5 | D17: Monserrat Villanueva | E17: Meeting | F17: Impocarnes | G17: Atelier Post CO | H17: 46080 | I17: Agenda cita | J17: =IF(G17="",F17,G17) -> Atelier Post CO | K17: =IFERROR(VLOOKUP(Table1[[#This Row],[Top Parent]],'1.- Citas sin this week'!G:G,1,0),"New New") -> Atelier Post CO | L17: =_xlfn.XLOOKUP(Table1[[#This Row],[Top Parent]],Table3[Top Parent],Table3[Date]) -> 45912 | M17: =Table1[[#This Row],[Date]]-Table1[[#This Row],[Last Date]] -> 168 | N17: =_xlfn.XLOOKUP(Table1[[#This Row],[Top Parent]],Table3[Top Parent],Table3[Owner Name]) -> Monserrat Villanueva | P17: Prospect | Q17: =IF(Table1[[#This Row],[Last Owner]]=Table1[[#This Row],[Owner Name]],"No","Si") -> No | R17: =IF(Table1[[#This Row],[Diferencia de dias]]>182,"Si","No") -> No | S17: Monserrat Villanueva | T17: =IF(Table1[[#This Row],[Owner de la cuenta]]=Table1[[#This Row],[Owner Name]],"Si","No") -> Si | U17: Ciudad de México | V17: SFAC0006087378 | X17: Food Bev & Ag
C18: =VLOOKUP(D18,Diccionario!A:B,2,0) -> México 1 | D18: Kenia Martinez | E18: Meeting | F18: Mexichem | H18: 46080 | I18: Video C. 8 am Asistentes Abi Carreon y Kenia M. Revisamos cronograma de entregas, variacion en precios del equipo NORMET, y platicamos sobre el equipo de Voz y Datos de EPIROC, la confirguracion inicial cambio y hay afectaciones en tiempos de entrega, y costos. Tambien platicamos sobre el proceso del contrato, me pide que se envie hoy a mas tardar, para que logremos entrar al proceso de validacion interna. | J18: =IF(G18="",F18,G18) -> Mexichem | K18: =IFERROR(VLOOKUP(Table1[[#This Row],[Top Parent]],'1.- Citas sin this week'!G:G,1,0),"New New") -> Mexichem | L18: =_xlfn.XLOOKUP(Table1[[#This Row],[Top Parent]],Table3[Top Parent],Table3[Date]) -> 46070 | M18: =Table1[[#This Row],[Date]]-Table1[[#This Row],[Last Date]] -> 10 | N18: =_xlfn.XLOOKUP(Table1[[#This Row],[Top Parent]],Table3[Top Parent],Table3[Owner Name]) -> Kenia Martinez | P18: Lost | Q18: =IF(Table1[[#This Row],[Last Owner]]=Table1[[#This Row],[Owner Name]],"No","Si") -> No | R18: =IF(Table1[[#This Row],[Diferencia de dias]]>182,"Si","No") -> No | S18: Kenia Martinez | T18: =IF(Table1[[#This Row],[Owner de la cuenta]]=Table1[[#This Row],[Owner Name]],"Si","No") -> Si | U18: Ciudad de México | V18: 1-3HYG-425 | W18: 0 | X18: Chemicals & Plastics
C19: =VLOOKUP(D19,Diccionario!A:B,2,0) -> Estructurados Core | D19: Josue Olvera | E19: Meeting | F19: SALZILLO | H19: 46079 | I19: se tiene contacto con Antonio empresa dedicada al sector de transoprte contando con flotilla de camiones opera desde el 2007 facturacion mayor a 100 mdp, refiere buen buro no trabajar con gobierno requiere esquemas de arrendamiento | J19: =IF(G19="",F19,G19) -> SALZILLO | K19: =IFERROR(VLOOKUP(Table1[[#This Row],[Top Parent]],'1.- Citas sin this week'!G:G,1,0),"New New") -> SALZILLO | L19: =_xlfn.XLOOKUP(Table1[[#This Row],[Top Parent]],Table3[Top Parent],Table3[Date]) -> 45786 | M19: =Table1[[#This Row],[Date]]-Table1[[#This Row],[Last Date]] -> 293 | N19: =_xlfn.XLOOKUP(Table1[[#This Row],[Top Parent]],Table3[Top Parent],Table3[Owner Name]) -> Josue Olvera | P19: Prospect | Q19: =IF(Table1[[#This Row],[Last Owner]]=Table1[[#This Row],[Owner Name]],"No","Si") -> No | R19: =IF(Table1[[#This Row],[Diferencia de dias]]>182,"Si","No") -> Si | S19: Josue Olvera | T19: =IF(Table1[[#This Row],[Owner de la cuenta]]=Table1[[#This Row],[Owner Name]],"Si","No") -> Si | U19: Guanajuato | V19: SFAC0006075981 | X19: Transportation
C20: =VLOOKUP(D20,Diccionario!A:B,2,0) -> Estructurados Core | D20: Manuel Ibal | E20: Meeting | F20: Aguacates Terravo | H20: 46078 | I20: Cita con Ángel Navarro Director General y Gabriela CFO, tienen la necesidad de compra de equipo para el empaque, transporte, y en un mediano plazo liquidar socios. Ventas: $250MDP. Inversiones se han realizado con inversionistas. Clientes: Distribuidores. Mercados de abastos. Exportación directas. Pains: Poca liquidez y requerimientos de capital de trabajo. Los activos están en un fideicomiso de garantía diseñado para solicitar crédito. Bancos: Bajío. Revolventes. LEMs. Con pagos semestrales. Acitvos sujetos a fin: lineas de empaque. | J20: =IF(G20="",F20,G20) -> Aguacates Terravo | K20: =IFERROR(VLOOKUP(Table1[[#This Row],[Top Parent]],'1.- Citas sin this week'!G:G,1,0),"New New") -> New New | L20: =_xlfn.XLOOKUP(Table1[[#This Row],[Top Parent]],Table3[Top Parent],Table3[Date]) -> #N/A | M20: =Table1[[#This Row],[Date]]-Table1[[#This Row],[Last Date]] -> #N/A | N20: =_xlfn.XLOOKUP(Table1[[#This Row],[Top Parent]],Table3[Top Parent],Table3[Owner Name]) -> #N/A | Q20: =IF(Table1[[#This Row],[Last Owner]]=Table1[[#This Row],[Owner Name]],"No","Si") -> #N/A | R20: =IF(Table1[[#This Row],[Diferencia de dias]]>182,"Si","No") -> #N/A | S20: Manuel Ibal | T20: =IF(Table1[[#This Row],[Owner de la cuenta]]=Table1[[#This Row],[Owner Name]],"Si","No") -> Si | U20: Jalisco | V20: SFAC0006110888 | X20: Food Bev & Ag
C21: =VLOOKUP(D21,Diccionario!A:B,2,0) -> Estructurados Core | D21: Manuel Ibal | E21: Meeting | F21: BANANAS SAN JORGE | H21: 46078 | I21: Reunión con el CFO de la empresa Miguel Ángel, la empresa pertenece a un Grupo empresarial llamado Grupo San Jorge, se dedican a la producción de banana, limón, coco y papaya, tienen una empresa de plasticos que son los que fabrican las cajas para consumo propio y vender a terceros, tienen la necesidad de comprar equipos pero para la nave industrial que tienen en Mc Allen TX. San Jorge: Usa lineas revolvente, bajio, santander bbv. Con revolvencia para comprar de oportunidad. No se preguntaron montos. SI GARANTIA HIPOTECARIA. No se pudo recabar mayor información. Se agendó cita el miércoles para estar con el dueño. | J21: =IF(G21="",F21,G21) -> BANANAS SAN JORGE | K21: =IFERROR(VLOOKUP(Table1[[#This Row],[Top Parent]],'1.- Citas sin this week'!G:G,1,0),"New New") -> New New | L21: =_xlfn.XLOOKUP(Table1[[#This Row],[Top Parent]],Table3[Top Parent],Table3[Date]) -> #N/A | M21: =Table1[[#This Row],[Date]]-Table1[[#This Row],[Last Date]] -> #N/A | N21: =_xlfn.XLOOKUP(Table1[[#This Row],[Top Parent]],Table3[Top Parent],Table3[Owner Name]) -> #N/A | P21: Prospect | Q21: =IF(Table1[[#This Row],[Last Owner]]=Table1[[#This Row],[Owner Name]],"No","Si") -> #N/A | R21: =IF(Table1[[#This Row],[Diferencia de dias]]>182,"Si","No") -> #N/A | S21: Manuel Ibal | T21: =IF(Table1[[#This Row],[Owner de la cuenta]]=Table1[[#This Row],[Owner Name]],"Si","No") -> Si | U21: Jalisco | V21: SFAC0006072621 | X21: Food Bev & Ag
C22: =VLOOKUP(D22,Diccionario!A:B,2,0) -> LMM 3 | D22: Vadir Peña | E22: Meeting | F22: Dmtress | H22: 46079 | I22: Nos reunimos con la Lic. Esmeralda Pereyra, quien nos indicó que durante el presente ejercicio tienen planeado dar salida a un camión, mismo que debe de ser renovado, buscaremos reunión la siguiente semana con el Lic. Víctor Marquinez. | J22: =IF(G22="",F22,G22) -> Dmtress | K22: New New | L22: =_xlfn.XLOOKUP(Table1[[#This Row],[Top Parent]],Table3[Top Parent],Table3[Date]) -> 45826 | M22: =Table1[[#This Row],[Date]]-Table1[[#This Row],[Last Date]] -> 253 | N22: =_xlfn.XLOOKUP(Table1[[#This Row],[Top Parent]],Table3[Top Parent],Table3[Owner Name]) -> Diego Aviña | P22: Dormant | Q22: =IF(Table1[[#This Row],[Last Owner]]=Table1[[#This Row],[Owner Name]],"No","Si") -> Si | R22: =IF(Table1[[#This Row],[Diferencia de dias]]>182,"Si","No") -> Si | S22: Vadir Peña | T22: =IF(Table1[[#This Row],[Owner de la cuenta]]=Table1[[#This Row],[Owner Name]],"Si","No") -> Si | U22: Veracruz | V22: SFAC0006059948 | W22: 224302.1 | X22: Chemicals & Plastics
C23: =VLOOKUP(D23,Diccionario!A:B,2,0) -> Guadalajara | D23: Dulce Villegas | E23: Meeting | F23: Hospital San Javier | H23: 46079 | I23: Visita en las oficinas del cliente para dialogar respecto a la línea calificada para el equipo del robot quirúrgico y revisar la viabilidad de que cierren este proyecto con nosotros. Recientemente firmaron un Loan con BANSI por MXN 27 MM a un plazo de 60 meses más 1 año de gracias, TIIE + 4 puntos. Le haremos llegar un análisis de VPN entre este crédito y nuestra propuesta de arrendamiento. | J23: =IF(G23="",F23,G23) -> Hospital San Javier | K23: =IFERROR(VLOOKUP(Table1[[#This Row],[Top Parent]],'1.- Citas sin this week'!G:G,1,0),"New New") -> Hospital San Javier | L23: =_xlfn.XLOOKUP(Table1[[#This Row],[Top Parent]],Table3[Top Parent],Table3[Date]) -> 45994 | M23: =Table1[[#This Row],[Date]]-Table1[[#This Row],[Last Date]] -> 85 | N23: =_xlfn.XLOOKUP(Table1[[#This Row],[Top Parent]],Table3[Top Parent],Table3[Owner Name]) -> Dulce Villegas | P23: Active | Q23: =IF(Table1[[#This Row],[Last Owner]]=Table1[[#This Row],[Owner Name]],"No","Si") -> No | R23: =IF(Table1[[#This Row],[Diferencia de dias]]>182,"Si","No") -> No | S23: Dulce Villegas | T23: =IF(Table1[[#This Row],[Owner de la cuenta]]=Table1[[#This Row],[Owner Name]],"Si","No") -> Si | U23: Jalisco | V23: SFAC0006005196 | W23: 68316343 | X23: Healthcare
C24: =VLOOKUP(D24,Diccionario!A:B,2,0) -> Guadalajara | D24: Dulce Villegas | E24: Meeting | F24: ZAZ MUEBLES Y ALGO MAS | H24: 46079 | I24: Conferencia con el cliente para revisar oportunidades para este 2026. | J24: =IF(G24="",F24,G24) -> ZAZ MUEBLES Y ALGO MAS | K24: =IFERROR(VLOOKUP(Table1[[#This Row],[Top Parent]],'1.- Citas sin this week'!G:G,1,0),"New New") -> New New | L24: =_xlfn.XLOOKUP(Table1[[#This Row],[Top Parent]],Table3[Top Parent],Table3[Date]) -> #N/A | M24: =Table1[[#This Row],[Date]]-Table1[[#This Row],[Last Date]] -> #N/A | N24: =_xlfn.XLOOKUP(Table1[[#This Row],[Top Parent]],Table3[Top Parent],Table3[Owner Name]) -> #N/A | P24: Prospect | Q24: =IF(Table1[[#This Row],[Last Owner]]=Table1[[#This Row],[Owner Name]],"No","Si") -> #N/A | R24: =IF(Table1[[#This Row],[Diferencia de dias]]>182,"Si","No") -> #N/A | S24: Dulce Villegas | T24: =IF(Table1[[#This Row],[Owner de la cuenta]]=Table1[[#This Row],[Owner Name]],"Si","No") -> Si | U24: Jalisco | V24: SFAC0006021738 | X24: Consumer Products
C25: =VLOOKUP(D25,Diccionario!A:B,2,0) -> Guadalajara | D25: Fernando Carbajal | E25: Meeting | F25: MADOBOX | H25: 46079 | I25: EMPRESA / CIUDAD: New New Madobox / Uruapan, Mich VENTAS: $583 MM CITA CON: Alejandro Macias Doddoli - Dueño ACTIVIDAD: Fabricación de cajas agrícola de cartón corrugado. CLIENTES / PLAZO PAGO: Mission Produce, Calavo, WestPack, Aztecavo, Agrovisión plazo máximo de 30 días. ACTIVOS CORE: Flexo, Cortadora, Corrugadora, Troqueladora. (Financian con el proveedor). PROVEEDORES / PLAZO PAGO: Georgia Pacific, Arizlu, Licbox. BANCOS CORTO PLAZO / MONTOS / % US0: Bajío y BBVA AP y AF de 3 a 7 años con garantía de la maquinaría, no hay corto. Arrendamientos en USD. OPORTUNIDAD: Flexo de $960 M USD en AP de 60 a 84 meses para línea de papaya y plátano, proveedor chino. Cuando mande IF financiera se hará también propuesta para reestructura de pasivos. | J25: =IF(G25="",F25,G25) -> MADOBOX | K25: =IFERROR(VLOOKUP(Table1[[#This Row],[Top Parent]],'1.- Citas sin this week'!G:G,1,0),"New New") -> New New | L25: =_xlfn.XLOOKUP(Table1[[#This Row],[Top Parent]],Table3[Top Parent],Table3[Date]) -> #N/A | M25: =Table1[[#This Row],[Date]]-Table1[[#This Row],[Last Date]] -> #N/A | N25: =_xlfn.XLOOKUP(Table1[[#This Row],[Top Parent]],Table3[Top Parent],Table3[Owner Name]) -> #N/A | P25: Prospect | Q25: =IF(Table1[[#This Row],[Last Owner]]=Table1[[#This Row],[Owner Name]],"No","Si") -> #N/A | R25: =IF(Table1[[#This Row],[Diferencia de dias]]>182,"Si","No") -> #N/A | S25: Fernando Carbajal | T25: =IF(Table1[[#This Row],[Owner de la cuenta]]=Table1[[#This Row],[Owner Name]],"Si","No") -> Si | U25: Michoacán | V25: SFAC0006075570 | X25: Forest Products
C26: =VLOOKUP(D26,Diccionario!A:B,2,0) -> Guadalajara | D26: Marianna Peña | E26: Meeting | F26: Agroservicios Nacionales | H26: 46076 | I26: Por contingencia se movió la reunión de presencial a videollamada, solo pudo estar el tesorero. Tienen necesidad de financiamiento de 1K camionetas para distribución en distintos estados. Podría existir oportunidad de refinanciamiento de líneas de corto plazo, necesario indagar que exista maquinaria suficiente. La visita presencial se pospuso para la siguiente semana para platicar más a detalle con DG. | J26: =IF(G26="",F26,G26) -> Agroservicios Nacionales | K26: =IFERROR(VLOOKUP(Table1[[#This Row],[Top Parent]],'1.- Citas sin this week'!G:G,1,0),"New New") -> New New | L26: =_xlfn.XLOOKUP(Table1[[#This Row],[Top Parent]],Table3[Top Parent],Table3[Date]) -> #N/A | M26: =Table1[[#This Row],[Date]]-Table1[[#This Row],[Last Date]] -> #N/A | N26: =_xlfn.XLOOKUP(Table1[[#This Row],[Top Parent]],Table3[Top Parent],Table3[Owner Name]) -> #N/A | P26: Prospect | Q26: =IF(Table1[[#This Row],[Last Owner]]=Table1[[#This Row],[Owner Name]],"No","Si") -> #N/A | R26: =IF(Table1[[#This Row],[Diferencia de dias]]>182,"Si","No") -> #N/A | S26: Marianna Peña | T26: =IF(Table1[[#This Row],[Owner de la cuenta]]=Table1[[#This Row],[Owner Name]],"Si","No") -> Si | U26: Jalisco | V26: SFAC0005578380 | X26: Chemicals & Plastics
C27: =VLOOKUP(D27,Diccionario!A:B,2,0) -> Guadalajara | D27: Miguel Ortiz | E27: Meeting | F27: FASST | G27: Call Fasst | H27: 46078 | I27: Hora y fecha de cita: Miércoles 23 de febrero 10:00 am Originador: Miguel Ortiz Con quien se habló: Alfonso Vega Puesto: CFO Actividad de la empresa: Desarrollo de sistema de telecomunicación para servicios de cobranza, atención a clientes etc. Ventas de la empresa: $1340 millones Buró de crédito: Ok Sector privado 100% Años de operación: 23 años Ubicación: Querétaro. Busca servicio de Arrendamiento y crédito, prospecto acudió al evento Impulsando Empresas Querétaro. | J27: =IF(G27="",F27,G27) -> Call Fasst | K27: =IFERROR(VLOOKUP(Table1[[#This Row],[Top Parent]],'1.- Citas sin this week'!G:G,1,0),"New New") -> New New | L27: =_xlfn.XLOOKUP(Table1[[#This Row],[Top Parent]],Table3[Top Parent],Table3[Date]) -> #N/A | M27: =Table1[[#This Row],[Date]]-Table1[[#This Row],[Last Date]] -> #N/A | N27: =_xlfn.XLOOKUP(Table1[[#This Row],[Top Parent]],Table3[Top Parent],Table3[Owner Name]) -> #N/A | P27: Prospect | Q27: =IF(Table1[[#This Row],[Last Owner]]=Table1[[#This Row],[Owner Name]],"No","Si") -> #N/A | R27: =IF(Table1[[#This Row],[Diferencia de dias]]>182,"Si","No") -> #N/A | S27: Miguel Ortiz | T27: =IF(Table1[[#This Row],[Owner de la cuenta]]=Table1[[#This Row],[Owner Name]],"Si","No") -> Si | U27: Querétaro | V27: SFAC0006022225 | X27: Technology & Business Services
C28: =VLOOKUP(D28,Diccionario!A:B,2,0) -> LMM 3 | D28: Jose Nava | E28: Meeting | F28: CAJAS Y CORRUGADOS PARA EMPAQUE | H28: 46079 | I28: Firma de contrato | J28: =IF(G28="",F28,G28) -> CAJAS Y CORRUGADOS PARA EMPAQUE | K28: =IFERROR(VLOOKUP(Table1[[#This Row],[Top Parent]],'1.- Citas sin this week'!G:G,1,0),"New New") -> CAJAS Y CORRUGADOS PARA EMPAQUE | L28: =_xlfn.XLOOKUP(Table1[[#This Row],[Top Parent]],Table3[Top Parent],Table3[Date]) -> 46073 | M28: =Table1[[#This Row],[Date]]-Table1[[#This Row],[Last Date]] -> 6 | N28: =_xlfn.XLOOKUP(Table1[[#This Row],[Top Parent]],Table3[Top Parent],Table3[Owner Name]) -> Jose Nava | P28: Dormant | Q28: =IF(Table1[[#This Row],[Last Owner]]=Table1[[#This Row],[Owner Name]],"No","Si") -> No | R28: =IF(Table1[[#This Row],[Diferencia de dias]]>182,"Si","No") -> No | S28: Jose Nava | T28: =IF(Table1[[#This Row],[Owner de la cuenta]]=Table1[[#This Row],[Owner Name]],"Si","No") -> Si | U28: Puebla | V28: SFAC0006039064 | W28: 2752767.5 | X28: Forest Products
C29: =VLOOKUP(D29,Diccionario!A:B,2,0) -> Guadalajara | D29: Natalia Bernat | E29: Meeting | F29: Terminal de Almacenamiento y Distribución de Asfalto | H29: 46079 | I29: Cita con TADA, con HUgo Peña, tienen 30 autos utilitarios y 51 tracto camiones, empresa se dedica a elaboracion y distribución de asfalto. | J29: =IF(G29="",F29,G29) -> Terminal de Almacenamiento y Distribución de Asfalto | K29: =IFERROR(VLOOKUP(Table1[[#This Row],[Top Parent]],'1.- Citas sin this week'!G:G,1,0),"New New") -> New New | L29: =_xlfn.XLOOKUP(Table1[[#This Row],[Top Parent]],Table3[Top Parent],Table3[Date]) -> #N/A | M29: =Table1[[#This Row],[Date]]-Table1[[#This Row],[Last Date]] -> #N/A | N29: =_xlfn.XLOOKUP(Table1[[#This Row],[Top Parent]],Table3[Top Parent],Table3[Owner Name]) -> #N/A | P29: Prospect | Q29: =IF(Table1[[#This Row],[Last Owner]]=Table1[[#This Row],[Owner Name]],"No","Si") -> #N/A | R29: =IF(Table1[[#This Row],[Diferencia de dias]]>182,"Si","No") -> #N/A | S29: Natalia Bernat | T29: =IF(Table1[[#This Row],[Owner de la cuenta]]=Table1[[#This Row],[Owner Name]],"Si","No") -> Si | U29: Guanajuato | V29: SFAC0006024350 | X29: Construction
C30: =VLOOKUP(D30,Diccionario!A:B,2,0) -> México 1 | D30: Kenia Martinez | E30: Meeting | F30: Ecoshell | H30: 46079 | I30: Seguimiento con Oscar para Anexo de Cartera, y estatus de la operación. Me confirmo que ya envio el anexo a Nidi con los datos correctos, le propuse reunirnos la siguiente semana para dar celeridad a la oportunidad. Trabajare en conjunto con Nidi para coordinar esta sesión y avanzar. | J30: =IF(G30="",F30,G30) -> Ecoshell | K30: =IFERROR(VLOOKUP(Table1[[#This Row],[Top Parent]],'1.- Citas sin this week'!G:G,1,0),"New New") -> Ecoshell | L30: =_xlfn.XLOOKUP(Table1[[#This Row],[Top Parent]],Table3[Top Parent],Table3[Date]) -> 46028 | M30: =Table1[[#This Row],[Date]]-Table1[[#This Row],[Last Date]] -> 51 | N30: =_xlfn.XLOOKUP(Table1[[#This Row],[Top Parent]],Table3[Top Parent],Table3[Owner Name]) -> Kenia Martinez | P30: Prospect | Q30: =IF(Table1[[#This Row],[Last Owner]]=Table1[[#This Row],[Owner Name]],"No","Si") -> No | R30: =IF(Table1[[#This Row],[Diferencia de dias]]>182,"Si","No") -> No | S30: Kenia Martinez | T30: =IF(Table1[[#This Row],[Owner de la cuenta]]=Table1[[#This Row],[Owner Name]],"Si","No") -> Si | U30: Ciudad de México | V30: SFAC0006001594 | X30: Chemicals & Plastics
C31: =VLOOKUP(D31,Diccionario!A:B,2,0) -> LMM 4 | D31: Alexandra Ramírez | E31: Meeting | F31: Güntner de México | H31: 46079 | I31: reunion con jesus cruz para revisar requerimiento de cnc | J31: =IF(G31="",F31,G31) -> Güntner de México | K31: =IFERROR(VLOOKUP(Table1[[#This Row],[Top Parent]],'1.- Citas sin this week'!G:G,1,0),"New New") -> Güntner de México | L31: =_xlfn.XLOOKUP(Table1[[#This Row],[Top Parent]],Table3[Top Parent],Table3[Date]) -> 45988 | M31: =Table1[[#This Row],[Date]]-Table1[[#This Row],[Last Date]] -> 91 | N31: =_xlfn.XLOOKUP(Table1[[#This Row],[Top Parent]],Table3[Top Parent],Table3[Owner Name]) -> Alexandra Ramírez | P31: Prospect | Q31: =IF(Table1[[#This Row],[Last Owner]]=Table1[[#This Row],[Owner Name]],"No","Si") -> No | R31: =IF(Table1[[#This Row],[Diferencia de dias]]>182,"Si","No") -> No | S31: Alexandra Ramírez | T31: =IF(Table1[[#This Row],[Owner de la cuenta]]=Table1[[#This Row],[Owner Name]],"Si","No") -> Si | U31: Nuevo León | V31: SFAC0005506431 | X31: Industrial Products & Services
C32: =VLOOKUP(D32,Diccionario!A:B,2,0) -> Monterrey | D32: Sergio Mange | E32: Meeting | F32: Tenedora Agnico Eagle México | H32: 46079 | I32: Reunión con Marco Perea, Gerente General de la mina Pinos Altos (Chihuahua). Se llevó a cabo una videollamada en la que se presentaron los principales puntos de valor agregado que podemos aportar a su operación. Marco comentó que la propuesta es de su interés y planteó realizar una segunda videollamada, ahora incluyendo al Ing. Alberto Díaz, Director de Compras de la mina. En esta siguiente reunión, el Ing. Díaz nos podrá brindar una mayor perspectiva sobre los equipos que tienen previstos para la operación 2026, así como las estructuras de compra y esquemas que actualmente utilizan. | J32: =IF(G32="",F32,G32) -> Tenedora Agnico Eagle México | K32: =IFERROR(VLOOKUP(Table1[[#This Row],[Top Parent]],'1.- Citas sin this week'!G:G,1,0),"New New") -> Tenedora Agnico Eagle México | L32: =_xlfn.XLOOKUP(Table1[[#This Row],[Top Parent]],Table3[Top Parent],Table3[Date]) -> 46065 | M32: =Table1[[#This Row],[Date]]-Table1[[#This Row],[Last Date]] -> 14 | N32: =_xlfn.XLOOKUP(Table1[[#This Row],[Top Parent]],Table3[Top Parent],Table3[Owner Name]) -> Sergio Mange | P32: Prospect | Q32: =IF(Table1[[#This Row],[Last Owner]]=Table1[[#This Row],[Owner Name]],"No","Si") -> No | R32: =IF(Table1[[#This Row],[Diferencia de dias]]>182,"Si","No") -> No | S32: Sergio Mange | T32: =IF(Table1[[#This Row],[Owner de la cuenta]]=Table1[[#This Row],[Owner Name]],"Si","No") -> Si | U32: Chihuahua | V32: SFAC0005644825 | X32: Metals, Mining & Metals Fabrication
C33: =VLOOKUP(D33,Diccionario!A:B,2,0) -> Guadalajara | D33: Omar Rodríguez | E33: Meeting | F33: Empaques y diseños de polietileno | H33: 46079 | I33: Visita a la empresa con Eduardo Covarruvias Director de Finanzas y Lucy Barba de Tesorería. La empresa se dedica al ensamble de cartón corrugado, plástico corrugado, foam de polietileno para empresas como San Mina, Jabil, HP, Flextronic, Nefab, Veritiv, Continental, etc a plazos de 60 días. Este plazo está empatado con sus proveedores y comentaban que tenían buen flujo. Están por realizar una sustitución de activos por al menos 10 mdp (dobladoras, suajadoras, pegadoras, etc). Se comentó la posibilidad de un S&LB pero comentó que no estaban interesados. Trabajan hoy factoraje con RTS pero derivado a que están buscando mejorar condiciones con clientes no quisieran otro proveedor de factoraje. El 85% de sus ventas son en usd y facturan 12 mdd al año. Se da de alta oportunidad. | J33: =IF(G33="",F33,G33) -> Empaques y diseños de polietileno | K33: =IFERROR(VLOOKUP(Table1[[#This Row],[Top Parent]],'1.- Citas sin this week'!G:G,1,0),"New New") -> New New | L33: =_xlfn.XLOOKUP(Table1[[#This Row],[Top Parent]],Table3[Top Parent],Table3[Date]) -> #N/A | M33: =Table1[[#This Row],[Date]]-Table1[[#This Row],[Last Date]] -> #N/A | N33: =_xlfn.XLOOKUP(Table1[[#This Row],[Top Parent]],Table3[Top Parent],Table3[Owner Name]) -> #N/A | P33: Prospect | Q33: =IF(Table1[[#This Row],[Last Owner]]=Table1[[#This Row],[Owner Name]],"No","Si") -> #N/A | R33: =IF(Table1[[#This Row],[Diferencia de dias]]>182,"Si","No") -> #N/A | S33: Omar Rodríguez | T33: =IF(Table1[[#This Row],[Owner de la cuenta]]=Table1[[#This Row],[Owner Name]],"Si","No") -> Si | U33: Jalisco | V33: SFAC0006026438 | X33: Forest Products
C34: =VLOOKUP(D34,Diccionario!A:B,2,0) -> México 1 | D34: Fernando Martin | E34: Seguimiento | F34: Unifoods | H34: 46079 | I34: reunión con Contador de la empresa para aclaración de dudas financieras al cierre 2025. Se acordó el envío de información referente a sus pasivos financieros para poder ingresar a riesgos la operación. Se acordó el día 27 de febrero el tener la información para poder hacer HO el lunes (2) o martes (3) de marzo. | J34: =IF(G34="",F34,G34) -> Unifoods | K34: =IFERROR(VLOOKUP(Table1[[#This Row],[Top Parent]],'1.- Citas sin this week'!G:G,1,0),"New New") -> Unifoods | L34: =_xlfn.XLOOKUP(Table1[[#This Row],[Top Parent]],Table3[Top Parent],Table3[Date]) -> 46030 | M34: =Table1[[#This Row],[Date]]-Table1[[#This Row],[Last Date]] -> 49 | N34: =_xlfn.XLOOKUP(Table1[[#This Row],[Top Parent]],Table3[Top Parent],Table3[Owner Name]) -> Fernando Martin | P34: Prospect | Q34: =IF(Table1[[#This Row],[Last Owner]]=Table1[[#This Row],[Owner Name]],"No","Si") -> No | R34: =IF(Table1[[#This Row],[Diferencia de dias]]>182,"Si","No") -> No | S34: Fernando Martin | T34: =IF(Table1[[#This Row],[Owner de la cuenta]]=Table1[[#This Row],[Owner Name]],"Si","No") -> Si | U34: Ciudad de México | V34: 1-3HZC-775 | X34: Food Bev & Ag
C35: =VLOOKUP(D35,Diccionario!A:B,2,0) -> LMM 1 | D35: Alejandro Monteón | E35: Meeting | F35: Logística Express La Bufa | H35: 46079 | I35: Seguimiento a Factoraje, se le presentó resultados de Sintach | J35: =IF(G35="",F35,G35) -> Logística Express La Bufa | K35: =IFERROR(VLOOKUP(Table1[[#This Row],[Top Parent]],'1.- Citas sin this week'!G:G,1,0),"New New") -> Logística Express La Bufa | L35: =_xlfn.XLOOKUP(Table1[[#This Row],[Top Parent]],Table3[Top Parent],Table3[Date]) -> 46070 | M35: =Table1[[#This Row],[Date]]-Table1[[#This Row],[Last Date]] -> 9 | N35: =_xlfn.XLOOKUP(Table1[[#This Row],[Top Parent]],Table3[Top Parent],Table3[Owner Name]) -> Alejandro Monteón | P35: Dormant | Q35: =IF(Table1[[#This Row],[Last Owner]]=Table1[[#This Row],[Owner Name]],"No","Si") -> No | R35: =IF(Table1[[#This Row],[Diferencia de dias]]>182,"Si","No") -> No | S35: Alejandro Monteón | T35: =IF(Table1[[#This Row],[Owner de la cuenta]]=Table1[[#This Row],[Owner Name]],"Si","No") -> Si | U35: Zacatecas | V35: SFAC0006076081 | W35: 11764701 | X35: Transportation
C36: =VLOOKUP(D36,Diccionario!A:B,2,0) -> LMM 1 | D36: Alejandro Monteón | E36: Meeting | F36: Mova Printing Solutions | H36: 46079 | I36: Visita con director regional para ver nueva opp. | J36: =IF(G36="",F36,G36) -> Mova Printing Solutions | K36: =IFERROR(VLOOKUP(Table1[[#This Row],[Top Parent]],'1.- Citas sin this week'!G:G,1,0),"New New") -> Mova Printing Solutions | L36: =_xlfn.XLOOKUP(Table1[[#This Row],[Top Parent]],Table3[Top Parent],Table3[Date]) -> 45931 | M36: =Table1[[#This Row],[Date]]-Table1[[#This Row],[Last Date]] -> 148 | N36: =_xlfn.XLOOKUP(Table1[[#This Row],[Top Parent]],Table3[Top Parent],Table3[Owner Name]) -> Alejandro Monteón | P36: Active | Q36: =IF(Table1[[#This Row],[Last Owner]]=Table1[[#This Row],[Owner Name]],"No","Si") -> No | R36: =IF(Table1[[#This Row],[Diferencia de dias]]>182,"Si","No") -> No | S36: Alejandro Monteón | T36: =IF(Table1[[#This Row],[Owner de la cuenta]]=Table1[[#This Row],[Owner Name]],"Si","No") -> Si | U36: Jalisco | V36: SFAC0006008587 | W36: 33515745 | X36: Forest Products
C37: =VLOOKUP(D37,Diccionario!A:B,2,0) -> Guadalajara | D37: Samuel Cepeda | E37: Meeting | F37: Ticoy Foods | H37: 46077 | I37: Ticoy Foods - new new: Reunión con Felipe Arteaga, esta reunión quedó pendiente de la gira de Ags, hay oportunidad para equipo de transporte y refrigeración (este en S&LB) venden +250mdp, tienen una empresa hermana holistik dedicada a frutos congelados, nos van a pasar cotizaciones para propuesta. Están interesados en escuchar al equipo de factoraje ya que le venden a Soriana y Waltmart, se busca reunión siguiente semana con ellos y Toño. | J37: =IF(G37="",F37,G37) -> Ticoy Foods | K37: =IFERROR(VLOOKUP(Table1[[#This Row],[Top Parent]],'1.- Citas sin this week'!G:G,1,0),"New New") -> New New | L37: =_xlfn.XLOOKUP(Table1[[#This Row],[Top Parent]],Table3[Top Parent],Table3[Date]) -> #N/A | M37: =Table1[[#This Row],[Date]]-Table1[[#This Row],[Last Date]] -> #N/A | N37: =_xlfn.XLOOKUP(Table1[[#This Row],[Top Parent]],Table3[Top Parent],Table3[Owner Name]) -> #N/A | P37: Prospect | Q37: =IF(Table1[[#This Row],[Last Owner]]=Table1[[#This Row],[Owner Name]],"No","Si") -> #N/A | R37: =IF(Table1[[#This Row],[Diferencia de dias]]>182,"Si","No") -> #N/A | S37: Samuel Cepeda | T37: =IF(Table1[[#This Row],[Owner de la cuenta]]=Table1[[#This Row],[Owner Name]],"Si","No") -> Si | U37: Aguascalientes | V37: SFAC0006091715 | X37: Food Bev & Ag
C38: =VLOOKUP(D38,Diccionario!A:B,2,0) -> LMM 1 | D38: Alejandro Monteón | E38: Meeting | F38: Industria procesadora de empaques | H38: 46078 | I38: Presentación con la Adm para ver posibles proyectos de inversión. | J38: =IF(G38="",F38,G38) -> Industria procesadora de empaques | K38: =IFERROR(VLOOKUP(Table1[[#This Row],[Top Parent]],'1.- Citas sin this week'!G:G,1,0),"New New") -> New New | L38: =_xlfn.XLOOKUP(Table1[[#This Row],[Top Parent]],Table3[Top Parent],Table3[Date]) -> #N/A | M38: =Table1[[#This Row],[Date]]-Table1[[#This Row],[Last Date]] -> #N/A | N38: =_xlfn.XLOOKUP(Table1[[#This Row],[Top Parent]],Table3[Top Parent],Table3[Owner Name]) -> #N/A | P38: Dormant* | Q38: =IF(Table1[[#This Row],[Last Owner]]=Table1[[#This Row],[Owner Name]],"No","Si") -> #N/A | R38: =IF(Table1[[#This Row],[Diferencia de dias]]>182,"Si","No") -> #N/A | S38: Alejandro Monteón | T38: =IF(Table1[[#This Row],[Owner de la cuenta]]=Table1[[#This Row],[Owner Name]],"Si","No") -> Si | U38: Jalisco | V38: SFAC0006076069 | W38: 1 | X38: Industrial Products & Services
C39: =VLOOKUP(D39,Diccionario!A:B,2,0) -> LMM 1 | D39: Juan Villaseñor | E39: Meeting | F39: RANCHO LA MEMORIA | H39: 46079 | I39: Se tiene contacto con Cynthua empresa operando desde el 2015 en la producion agricola de diferentes vegetales la mayoría para exportación a EUA y la ventas en el pais es con empresas grandes como Walmart indica que tiene un nivel de factruracion entre los 50 mdp y 400 mdp refiere tener buen buro no trabaja con gobierno. requieren 3 Nissan Urvan 14 pasajeros con valor de $842,900.00 pesos piden cotizacion en 24 36 y 48 meses | J39: =IF(G39="",F39,G39) -> RANCHO LA MEMORIA | K39: =IFERROR(VLOOKUP(Table1[[#This Row],[Top Parent]],'1.- Citas sin this week'!G:G,1,0),"New New") -> New New | L39: =_xlfn.XLOOKUP(Table1[[#This Row],[Top Parent]],Table3[Top Parent],Table3[Date]) -> #N/A | M39: =Table1[[#This Row],[Date]]-Table1[[#This Row],[Last Date]] -> #N/A | N39: =_xlfn.XLOOKUP(Table1[[#This Row],[Top Parent]],Table3[Top Parent],Table3[Owner Name]) -> #N/A | Q39: =IF(Table1[[#This Row],[Last Owner]]=Table1[[#This Row],[Owner Name]],"No","Si") -> #N/A | R39: =IF(Table1[[#This Row],[Diferencia de dias]]>182,"Si","No") -> #N/A | S39: Juan Villaseñor | T39: =IF(Table1[[#This Row],[Owner de la cuenta]]=Table1[[#This Row],[Owner Name]],"Si","No") -> Si | U39: Sinaloa | V39: SFAC0006110892 | X39: Food Bev & Ag
C40: =VLOOKUP(D40,Diccionario!A:B,2,0) -> LMM 1 | D40: Juan Villaseñor | E40: Meeting | F40: Energio Servicios de Energía Sostenible | H40: 46078 | I40: -Hable con Neto Leal. -CEO de la empresa. -Dedicados a egregia sustentable a nivel industrial. -Interesado en adquirir vehículos para su operación: 3 camionetas pickup, 36 meses, seguro propio y placas en diferentes estados. Y capital de trabajo cuenta con 5 compresores industriales 1.1 MDP cada uno. -Ventas de 100 MDP. -Buen buro. -No trabaja con gobierno. -Mas de 20 años operando. -Ubicados en Sinaloa. | J40: =IF(G40="",F40,G40) -> Energio Servicios de Energía Sostenible | K40: =IFERROR(VLOOKUP(Table1[[#This Row],[Top Parent]],'1.- Citas sin this week'!G:G,1,0),"New New") -> New New | L40: =_xlfn.XLOOKUP(Table1[[#This Row],[Top Parent]],Table3[Top Parent],Table3[Date]) -> #N/A | M40: =Table1[[#This Row],[Date]]-Table1[[#This Row],[Last Date]] -> #N/A | N40: =_xlfn.XLOOKUP(Table1[[#This Row],[Top Parent]],Table3[Top Parent],Table3[Owner Name]) -> #N/A | P40: Prospect | Q40: =IF(Table1[[#This Row],[Last Owner]]=Table1[[#This Row],[Owner Name]],"No","Si") -> #N/A | R40: =IF(Table1[[#This Row],[Diferencia de dias]]>182,"Si","No") -> #N/A | S40: Juan Villaseñor | T40: =IF(Table1[[#This Row],[Owner de la cuenta]]=Table1[[#This Row],[Owner Name]],"Si","No") -> Si | U40: Sinaloa | V40: SFAC0006090100 | X40: Misc Service Industries
C41: =VLOOKUP(D41,Diccionario!A:B,2,0) -> LMM 1 | D41: Ricardo Moreno | E41: Meeting | F41: EMBAG PACK | H41: 46080 | I41: *Lic. Dulce Karen Alvarado Setina *Jefe de compras * Giro producción de empaques de Polietileno *Oportunidad S&LB de Flota vehícular *Ventas 200 mdp *Buen buro de crédito *Gobierno no aplica *Años de operación 12 *Ubicación: Michoacán | J41: =IF(G41="",F41,G41) -> EMBAG PACK | K41: =IFERROR(VLOOKUP(Table1[[#This Row],[Top Parent]],'1.- Citas sin this week'!G:G,1,0),"New New") -> New New | L41: =_xlfn.XLOOKUP(Table1[[#This Row],[Top Parent]],Table3[Top Parent],Table3[Date]) -> #N/A | M41: =Table1[[#This Row],[Date]]-Table1[[#This Row],[Last Date]] -> #N/A | N41: =_xlfn.XLOOKUP(Table1[[#This Row],[Top Parent]],Table3[Top Parent],Table3[Owner Name]) -> #N/A | P41: Prospect | Q41: =IF(Table1[[#This Row],[Last Owner]]=Table1[[#This Row],[Owner Name]],"No","Si") -> #N/A | R41: =IF(Table1[[#This Row],[Diferencia de dias]]>182,"Si","No") -> #N/A | S41: Ricardo Moreno | T41: =IF(Table1[[#This Row],[Owner de la cuenta]]=Table1[[#This Row],[Owner Name]],"Si","No") -> Si | U41: Michoacán | V41: SFAC0006073242 | X41: Chemicals & Plastics
C42: =VLOOKUP(D42,Diccionario!A:B,2,0) -> LMM 1 | D42: Ricardo Moreno | E42: Meeting | F42: Jesús Pulido | H42: 46078 | I42: Hora y fecha de cita: Lunes 23 de Febrero 5:00 pm Originador: Ricardo Moreno Con quien se hablo: Jesus Pulido Puesto: Dueño Actividad de la empresa: Distribución de Aguacate, fertilizantes y semillas para sie Ventas de la empresa: $60 millones Buró de crédito: Ok Sector privado 100% Años de operación: 6 años Ubicación: Michoacan de Ocampo Busca Arrendamiento de 10 Camiones de carga con valor de 1,800,000.00 | J42: =IF(G42="",F42,G42) -> Jesús Pulido | K42: New New | L42: =_xlfn.XLOOKUP(Table1[[#This Row],[Top Parent]],Table3[Top Parent],Table3[Date]) -> 45755 | M42: =Table1[[#This Row],[Date]]-Table1[[#This Row],[Last Date]] -> 323 | N42: =_xlfn.XLOOKUP(Table1[[#This Row],[Top Parent]],Table3[Top Parent],Table3[Owner Name]) -> Alejandro Monteón | P42: Prospect | Q42: =IF(Table1[[#This Row],[Last Owner]]=Table1[[#This Row],[Owner Name]],"No","Si") -> Si | R42: =IF(Table1[[#This Row],[Diferencia de dias]]>182,"Si","No") -> Si | S42: Ricardo Moreno | T42: =IF(Table1[[#This Row],[Owner de la cuenta]]=Table1[[#This Row],[Owner Name]],"Si","No") -> Si | U42: Michoacán | V42: SFAC0006087445 | X42: Food Bev & Ag
C43: =VLOOKUP(D43,Diccionario!A:B,2,0) -> LMM 3 | D43: Braulio Martinez | E43: Meeting | F43: Grucotox Construcciones | H43: 46077 | I43: Hora y fecha de cita: Martes 24 de febrero 2026, 16:00 hrs. Originador asignado: Braulio Martínez Con quien se hablo: Alejandro Zúñiga Alejo Puesto: Dueño de la empresa Actividad de la empresa: Empresa dedicada a la obra civil Oportunidad identificada: CE - Formulario - Facebook - 2023 - F03 Ventas de la empresa: $79,000,000.00 Buró de crédito: Ok Tipo de ventas: Sector privado Años de operación: 12 años Ubicación: "Cerrada Nicolás San Juan 03103 Ciudad de México, Ciudad de México México" Producto: Prospecto interesado en inyección de capital, interesado en conocer oportunidad tanto en crédito simple o s&lb, cuenta motoconformadora y un vehículo Cadillac, con costos aproximados 3,200 mdp y 2.4 mdp respectivamente. | J43: =IF(G43="",F43,G43) -> Grucotox Construcciones | K43: =IFERROR(VLOOKUP(Table1[[#This Row],[Top Parent]],'1.- Citas sin this week'!G:G,1,0),"New New") -> New New | L43: =_xlfn.XLOOKUP(Table1[[#This Row],[Top Parent]],Table3[Top Parent],Table3[Date]) -> #N/A | M43: =Table1[[#This Row],[Date]]-Table1[[#This Row],[Last Date]] -> #N/A | N43: =_xlfn.XLOOKUP(Table1[[#This Row],[Top Parent]],Table3[Top Parent],Table3[Owner Name]) -> #N/A | P43: Prospect | Q43: =IF(Table1[[#This Row],[Last Owner]]=Table1[[#This Row],[Owner Name]],"No","Si") -> #N/A | R43: =IF(Table1[[#This Row],[Diferencia de dias]]>182,"Si","No") -> #N/A | S43: Braulio Martinez | T43: =IF(Table1[[#This Row],[Owner de la cuenta]]=Table1[[#This Row],[Owner Name]],"Si","No") -> Si | U43: Ciudad de México | V43: SFAC0006099795 | X43: Construction
C44: =VLOOKUP(D44,Diccionario!A:B,2,0) -> México 1 | D44: Kenia Martinez | E44: Meeting | F44: Robert Bosch Gmbh | H44: 46079 | I44: Video C. Yolanda M. Montes Romero Malpica Cristopher David (Finanzas) Revision de propuesta final, solicitaron enviarles un cotizador para que ellos puedan modelar los ejercicios y poder presentar a sus clientes internos (plantas). | J44: =IF(G44="",F44,G44) -> Robert Bosch Gmbh | K44: =IFERROR(VLOOKUP(Table1[[#This Row],[Top Parent]],'1.- Citas sin this week'!G:G,1,0),"New New") -> Robert Bosch Gmbh | L44: =_xlfn.XLOOKUP(Table1[[#This Row],[Top Parent]],Table3[Top Parent],Table3[Date]) -> 45862 | M44: =Table1[[#This Row],[Date]]-Table1[[#This Row],[Last Date]] -> 217 | N44: =_xlfn.XLOOKUP(Table1[[#This Row],[Top Parent]],Table3[Top Parent],Table3[Owner Name]) -> Kenia Martinez | P44: Lost | Q44: =IF(Table1[[#This Row],[Last Owner]]=Table1[[#This Row],[Owner Name]],"No","Si") -> No | R44: =IF(Table1[[#This Row],[Diferencia de dias]]>182,"Si","No") -> Si | S44: Kenia Martinez | T44: =IF(Table1[[#This Row],[Owner de la cuenta]]=Table1[[#This Row],[Owner Name]],"Si","No") -> Si | U44: Ciudad de México | V44: 1-1X-559 | W44: 0 | X44: Automotive
C45: =VLOOKUP(D45,Diccionario!A:B,2,0) -> LMM 3 | D45: Braulio Martinez | E45: Meeting | F45: Lite Tek | H45: 46076 | I45: Se agenda cita con Yolanda García y Luis Fernando Alvarez *Contadores de la empresa *Giro: distribución de equipo de audio e iluminación *Oportunidad: linea de crédito para capital de trabajo o bien factoraje. *Ventas: 250 mdp *Buen buro de crédito *Sin operaciones con gobierno * Cuentan con flotas vehiculares autos de lujo y carga de mercancía. *mas de 10 años *Ubicación: Puebla | J45: =IF(G45="",F45,G45) -> Lite Tek | K45: =IFERROR(VLOOKUP(Table1[[#This Row],[Top Parent]],'1.- Citas sin this week'!G:G,1,0),"New New") -> New New | L45: =_xlfn.XLOOKUP(Table1[[#This Row],[Top Parent]],Table3[Top Parent],Table3[Date]) -> #N/A | M45: =Table1[[#This Row],[Date]]-Table1[[#This Row],[Last Date]] -> #N/A | N45: =_xlfn.XLOOKUP(Table1[[#This Row],[Top Parent]],Table3[Top Parent],Table3[Owner Name]) -> #N/A | P45: Prospect | Q45: =IF(Table1[[#This Row],[Last Owner]]=Table1[[#This Row],[Owner Name]],"No","Si") -> #N/A | R45: =IF(Table1[[#This Row],[Diferencia de dias]]>182,"Si","No") -> #N/A | S45: Braulio Martinez | T45: =IF(Table1[[#This Row],[Owner de la cuenta]]=Table1[[#This Row],[Owner Name]],"Si","No") -> Si | U45: Puebla | V45: SFAC0006095039 | X45: Industrial Products & Services
C46: =VLOOKUP(D46,Diccionario!A:B,2,0) -> México 2 | D46: Octavio Chimal | E46: Meeting | F46: QUARKSOFT | G46: Isa Corporativo | H46: 46079 | I46: videollamada factoraje | J46: =IF(G46="",F46,G46) -> Isa Corporativo | K46: =IFERROR(VLOOKUP(Table1[[#This Row],[Top Parent]],'1.- Citas sin this week'!G:G,1,0),"New New") -> Isa Corporativo | L46: =_xlfn.XLOOKUP(Table1[[#This Row],[Top Parent]],Table3[Top Parent],Table3[Date]) -> 46030 | M46: =Table1[[#This Row],[Date]]-Table1[[#This Row],[Last Date]] -> 49 | N46: =_xlfn.XLOOKUP(Table1[[#This Row],[Top Parent]],Table3[Top Parent],Table3[Owner Name]) -> Octavio Chimal | P46: Lost | Q46: =IF(Table1[[#This Row],[Last Owner]]=Table1[[#This Row],[Owner Name]],"No","Si") -> No | R46: =IF(Table1[[#This Row],[Diferencia de dias]]>182,"Si","No") -> No | S46: Jorge Estrada | T46: =IF(Table1[[#This Row],[Owner de la cuenta]]=Table1[[#This Row],[Owner Name]],"Si","No") -> No | U46: Ciudad de México | V46: SFAC0006018075 | W46: 0 | X46: Retail
C47: =VLOOKUP(D47,Diccionario!A:B,2,0) -> LMM 3 | D47: Jose Nava | E47: Meeting | F47: JCB | H47: 46079 | I47: Reunión con Ulises Vazquez,, requieren de financiar equipos para renta de corto plazo, nos compartio cotizaciones de su financiera para poder contra ofertar | J47: =IF(G47="",F47,G47) -> JCB | K47: New New | L47: =_xlfn.XLOOKUP(Table1[[#This Row],[Top Parent]],Table3[Top Parent],Table3[Date]) -> 45792 | M47: =Table1[[#This Row],[Date]]-Table1[[#This Row],[Last Date]] -> 287 | N47: =_xlfn.XLOOKUP(Table1[[#This Row],[Top Parent]],Table3[Top Parent],Table3[Owner Name]) -> Rene Lopez | P47: Prospect | Q47: =IF(Table1[[#This Row],[Last Owner]]=Table1[[#This Row],[Owner Name]],"No","Si") -> Si | R47: =IF(Table1[[#This Row],[Diferencia de dias]]>182,"Si","No") -> Si | S47: Jose Nava | T47: =IF(Table1[[#This Row],[Owner de la cuenta]]=Table1[[#This Row],[Owner Name]],"Si","No") -> Si | U47: Puebla | V47: SFAC0005611845 | X47: Industrial Products & Services
C48: =VLOOKUP(D48,Diccionario!A:B,2,0) -> LMM 3 | D48: Vadir Peña | E48: Meeting | F48: Intersyst Seguridad y Control | H48: 46079 | I48: Platicamos con el Ing. Aurelio Ceballos, se detectó oportunidad para financiar renovación de flotilla de vehículos utilitarios, enviaremos información de nuestro producto, y obtendremos información de flotilla a renovar. | J48: =IF(G48="",F48,G48) -> Intersyst Seguridad y Control | K48: =IFERROR(VLOOKUP(Table1[[#This Row],[Top Parent]],'1.- Citas sin this week'!G:G,1,0),"New New") -> New New | L48: =_xlfn.XLOOKUP(Table1[[#This Row],[Top Parent]],Table3[Top Parent],Table3[Date]) -> #N/A | M48: =Table1[[#This Row],[Date]]-Table1[[#This Row],[Last Date]] -> #N/A | N48: =_xlfn.XLOOKUP(Table1[[#This Row],[Top Parent]],Table3[Top Parent],Table3[Owner Name]) -> #N/A | P48: Dormant | Q48: =IF(Table1[[#This Row],[Last Owner]]=Table1[[#This Row],[Owner Name]],"No","Si") -> #N/A | R48: =IF(Table1[[#This Row],[Diferencia de dias]]>182,"Si","No") -> #N/A | S48: Vadir Peña | T48: =IF(Table1[[#This Row],[Owner de la cuenta]]=Table1[[#This Row],[Owner Name]],"Si","No") -> Si | U48: Veracruz | V48: SFAC0006056799 | W48: 640826.8 | X48: Industrial Products & Services
C49: =VLOOKUP(D49,Diccionario!A:B,2,0) -> LMM 3 | D49: Moises Villalon | E49: Meeting | F49: Aceites Sustentables de Palma | H49: 46079 | I49: Se tiene cita referenciada por medio de TIP | J49: =IF(G49="",F49,G49) -> Aceites Sustentables de Palma | K49: =IFERROR(VLOOKUP(Table1[[#This Row],[Top Parent]],'1.- Citas sin this week'!G:G,1,0),"New New") -> New New | L49: =_xlfn.XLOOKUP(Table1[[#This Row],[Top Parent]],Table3[Top Parent],Table3[Date]) -> #N/A | M49: =Table1[[#This Row],[Date]]-Table1[[#This Row],[Last Date]] -> #N/A | N49: =_xlfn.XLOOKUP(Table1[[#This Row],[Top Parent]],Table3[Top Parent],Table3[Owner Name]) -> #N/A | Q49: =IF(Table1[[#This Row],[Last Owner]]=Table1[[#This Row],[Owner Name]],"No","Si") -> #N/A | R49: =IF(Table1[[#This Row],[Diferencia de dias]]>182,"Si","No") -> #N/A | S49: Moises Villalon | T49: =IF(Table1[[#This Row],[Owner de la cuenta]]=Table1[[#This Row],[Owner Name]],"Si","No") -> Si | U49: Ciudad de México | V49: SFAC0006110884 | X49: Food Bev & Ag
C50: =VLOOKUP(D50,Diccionario!A:B,2,0) -> LMM 3 | D50: Teresa Cisneros | E50: Meeting | F50: Productos Helados Milky Mich | H50: 46077 | I50: *Productos Helados Milky Mich *José Islas *Contador *Venta de paletas y helados *Paneles solares ( 3mdp aprox) *80 mdp *Buen Buro *Sin ventas a Gobierno *Años 50 *Ubicación Hidalgo | J50: =IF(G50="",F50,G50) -> Productos Helados Milky Mich | K50: =IFERROR(VLOOKUP(Table1[[#This Row],[Top Parent]],'1.- Citas sin this week'!G:G,1,0),"New New") -> New New | L50: =_xlfn.XLOOKUP(Table1[[#This Row],[Top Parent]],Table3[Top Parent],Table3[Date]) -> #N/A | M50: =Table1[[#This Row],[Date]]-Table1[[#This Row],[Last Date]] -> #N/A | N50: =_xlfn.XLOOKUP(Table1[[#This Row],[Top Parent]],Table3[Top Parent],Table3[Owner Name]) -> #N/A | P50: Prospect | Q50: =IF(Table1[[#This Row],[Last Owner]]=Table1[[#This Row],[Owner Name]],"No","Si") -> #N/A | R50: =IF(Table1[[#This Row],[Diferencia de dias]]>182,"Si","No") -> #N/A | S50: Teresa Cisneros | T50: =IF(Table1[[#This Row],[Owner de la cuenta]]=Table1[[#This Row],[Owner Name]],"Si","No") -> Si | U50: Hidalgo | V50: SFAC0006018245 | X50: Food Bev & Ag
C51: =VLOOKUP(D51,Diccionario!A:B,2,0) -> LMM 3 | D51: Vadir Peña | E51: Meeting | F51: Geoperfora del Golfo | H51: 46079 | I51: Platicamos con la Ing. Maria Elena Guevara y la C.P. Diana Salas, obtendremos información de la última maquina adquirida en el último semestre del 2025, para evaluar S&LB. | J51: =IF(G51="",F51,G51) -> Geoperfora del Golfo | K51: =IFERROR(VLOOKUP(Table1[[#This Row],[Top Parent]],'1.- Citas sin this week'!G:G,1,0),"New New") -> New New | L51: =_xlfn.XLOOKUP(Table1[[#This Row],[Top Parent]],Table3[Top Parent],Table3[Date]) -> #N/A | M51: =Table1[[#This Row],[Date]]-Table1[[#This Row],[Last Date]] -> #N/A | N51: =_xlfn.XLOOKUP(Table1[[#This Row],[Top Parent]],Table3[Top Parent],Table3[Owner Name]) -> #N/A | P51: Lost | Q51: =IF(Table1[[#This Row],[Last Owner]]=Table1[[#This Row],[Owner Name]],"No","Si") -> #N/A | R51: =IF(Table1[[#This Row],[Diferencia de dias]]>182,"Si","No") -> #N/A | S51: Vadir Peña | T51: =IF(Table1[[#This Row],[Owner de la cuenta]]=Table1[[#This Row],[Owner Name]],"Si","No") -> Si | U51: Veracruz | V51: SFAC0006030636 | W51: 0 | X51: Construction
C52: =VLOOKUP(D52,Diccionario!A:B,2,0) -> LMM 3 | D52: Vadir Peña | E52: Meeting | F52: Manufacturera 3M | H52: 46079 | I52: Hora y fecha de cita: Jueves 26 de febrero 2026, 12:30 hrs. Originador asignado: Vadir Peña Con quien se hablo: Juan Miguel Bueno Ros Puesto: Presidente Actividad de la empresa: Empresa dedicada a la fabricación de maquinaria, equipos y partes industriales Oportunidad identificada: Base de datos Ventas de la empresa: $130,000,000.00 Buró de crédito: Ok Tipo de ventas: Privado Años de operación: Más de 30 años Ubicación: "Prol. De Av. 3 Jose B. Lizardi S/N Entre Calles 43 Y 45 Zona Industrial 94690 Córdoba, Veracruz México" Producto: Prospecto interesado en conocer las condiciones de arrendamiento para adquirir equipo de automatización para la plata con costo aproximado de 4muds. | J52: =IF(G52="",F52,G52) -> Manufacturera 3M | K52: =IFERROR(VLOOKUP(Table1[[#This Row],[Top Parent]],'1.- Citas sin this week'!G:G,1,0),"New New") -> New New | L52: =_xlfn.XLOOKUP(Table1[[#This Row],[Top Parent]],Table3[Top Parent],Table3[Date]) -> #N/A | M52: =Table1[[#This Row],[Date]]-Table1[[#This Row],[Last Date]] -> #N/A | N52: =_xlfn.XLOOKUP(Table1[[#This Row],[Top Parent]],Table3[Top Parent],Table3[Owner Name]) -> #N/A | P52: Prospect | Q52: =IF(Table1[[#This Row],[Last Owner]]=Table1[[#This Row],[Owner Name]],"No","Si") -> #N/A | R52: =IF(Table1[[#This Row],[Diferencia de dias]]>182,"Si","No") -> #N/A | S52: Vadir Peña | T52: =IF(Table1[[#This Row],[Owner de la cuenta]]=Table1[[#This Row],[Owner Name]],"Si","No") -> Si | U52: Veracruz | V52: 1-FKFMVS | X52: Industrial Products & Services
C53: =VLOOKUP(D53,Diccionario!A:B,2,0) -> LMM 3 | D53: Vadir Peña | E53: Meeting | F53: Manuel Jedidias Islas Bonilla | H53: 46077 | I53: Contacto: Manuel Islas Actividad: (Por confirmar en reunión ? relacionado con cámara de refrigeración y activos productivos) Oportunidad: S&LB sobre cámara de refrigeración y revisión de activos adicionales Ventas: 70 MDP (2025) Activo identificado: Cámara de refrigeración por 1 MDP Contexto: Refiere tener buen buró y no trabajar con Gob. Operación: 14 años Reunión: Mañana, 4:00 p.m. | J53: =IF(G53="",F53,G53) -> Manuel Jedidias Islas Bonilla | K53: =IFERROR(VLOOKUP(Table1[[#This Row],[Top Parent]],'1.- Citas sin this week'!G:G,1,0),"New New") -> New New | L53: =_xlfn.XLOOKUP(Table1[[#This Row],[Top Parent]],Table3[Top Parent],Table3[Date]) -> #N/A | M53: =Table1[[#This Row],[Date]]-Table1[[#This Row],[Last Date]] -> #N/A | N53: =_xlfn.XLOOKUP(Table1[[#This Row],[Top Parent]],Table3[Top Parent],Table3[Owner Name]) -> #N/A | P53: Prospect | Q53: =IF(Table1[[#This Row],[Last Owner]]=Table1[[#This Row],[Owner Name]],"No","Si") -> #N/A | R53: =IF(Table1[[#This Row],[Diferencia de dias]]>182,"Si","No") -> #N/A | S53: Vadir Peña | T53: =IF(Table1[[#This Row],[Owner de la cuenta]]=Table1[[#This Row],[Owner Name]],"Si","No") -> Si | U53: Tabasco | V53: SFAC0006071535 | X53: Food Bev & Ag
C54: =VLOOKUP(D54,Diccionario!A:B,2,0) -> Monterrey | D54: Sergio Mange | E54: Meeting | F54: Compañia Impresora Especializada | H54: 46078 | I54: Videoconferencia con Daniel Dalamu y Fabio López (proveedor de equipos). Daniel comentó que la próxima semana estará en Alemania revisando los posibles equipos a adquirir. Ya nos compartieron toda la documentación necesaria para realizar el hand-off interno y avanzar con el análisis. Dado que existe la posibilidad de que se trate de un equipo usado, se exploró la alternativa de estructurar la operación mediante una hipoteca, con el objetivo de poder otorgar el plazo que el cliente está buscando. En caso de ser necesario, estuvieron de acuerdo con esta opción. | J54: =IF(G54="",F54,G54) -> Compañia Impresora Especializada | K54: =IFERROR(VLOOKUP(Table1[[#This Row],[Top Parent]],'1.- Citas sin this week'!G:G,1,0),"New New") -> Compañia Impresora Especializada | L54: =_xlfn.XLOOKUP(Table1[[#This Row],[Top Parent]],Table3[Top Parent],Table3[Date]) -> 46049 | M54: =Table1[[#This Row],[Date]]-Table1[[#This Row],[Last Date]] -> 29 | N54: =_xlfn.XLOOKUP(Table1[[#This Row],[Top Parent]],Table3[Top Parent],Table3[Owner Name]) -> Sergio Mange | P54: Dormant | Q54: =IF(Table1[[#This Row],[Last Owner]]=Table1[[#This Row],[Owner Name]],"No","Si") -> No | R54: =IF(Table1[[#This Row],[Diferencia de dias]]>182,"Si","No") -> No | S54: Sergio Mange | T54: =IF(Table1[[#This Row],[Owner de la cuenta]]=Table1[[#This Row],[Owner Name]],"Si","No") -> Si | U54: Nuevo León | V54: SFAC0006087192 | W54: 11160322 | X54: Forest Products
C55: =VLOOKUP(D55,Diccionario!A:B,2,0) -> LMM 3 | D55: Vadir Peña | E55: Meeting | F55: Etesla | H55: 46077 | I55: Platicamos con Daniel Ortíz, director y dueño de ETESLA, de momento no planean hacer inversiones en posibles vehículos utilitarios, sin embargo, nos referenció un cliente que está por realizar una inversión en un proyecto de almacenamiento de energía. | J55: =IF(G55="",F55,G55) -> Etesla | K55: =IFERROR(VLOOKUP(Table1[[#This Row],[Top Parent]],'1.- Citas sin this week'!G:G,1,0),"New New") -> New New | L55: =_xlfn.XLOOKUP(Table1[[#This Row],[Top Parent]],Table3[Top Parent],Table3[Date]) -> #N/A | M55: =Table1[[#This Row],[Date]]-Table1[[#This Row],[Last Date]] -> #N/A | N55: =_xlfn.XLOOKUP(Table1[[#This Row],[Top Parent]],Table3[Top Parent],Table3[Owner Name]) -> #N/A | P55: Prospect | Q55: =IF(Table1[[#This Row],[Last Owner]]=Table1[[#This Row],[Owner Name]],"No","Si") -> #N/A | R55: =IF(Table1[[#This Row],[Diferencia de dias]]>182,"Si","No") -> #N/A | S55: Areli Canche | T55: Si | U55: Veracruz | V55: SFAC0006110835 | X55: Utilities & Energy
C56: =VLOOKUP(D56,Diccionario!A:B,2,0) -> LMM 3 | D56: Teresa Cisneros | E56: Meeting | F56: SYNELMEX | H56: 46078 | I56: Seguimiento para alianzas con sus clientes. | J56: =IF(G56="",F56,G56) -> SYNELMEX | K56: =IFERROR(VLOOKUP(Table1[[#This Row],[Top Parent]],'1.- Citas sin this week'!G:G,1,0),"New New") -> SYNELMEX | L56: =_xlfn.XLOOKUP(Table1[[#This Row],[Top Parent]],Table3[Top Parent],Table3[Date]) -> 46041 | M56: =Table1[[#This Row],[Date]]-Table1[[#This Row],[Last Date]] -> 37 | N56: =_xlfn.XLOOKUP(Table1[[#This Row],[Top Parent]],Table3[Top Parent],Table3[Owner Name]) -> Teresa Cisneros | P56: Prospect | Q56: =IF(Table1[[#This Row],[Last Owner]]=Table1[[#This Row],[Owner Name]],"No","Si") -> No | R56: =IF(Table1[[#This Row],[Diferencia de dias]]>182,"Si","No") -> No | S56: Teresa Cisneros | T56: =IF(Table1[[#This Row],[Owner de la cuenta]]=Table1[[#This Row],[Owner Name]],"Si","No") -> Si | U56: Ciudad de México | V56: SFAC0006104494 | X56: Utilities & Energy
C57: =VLOOKUP(D57,Diccionario!A:B,2,0) -> LMM 4 | D57: Alexandra Luna | E57: Meeting | F57: Pecom | H57: 46077 | I57: Hora y fecha de cita: Martes 24 de Febrero 1:00 pm Originador: Con quien se hablo: Jose Cinco, Ing. Luis y Carlos Puesto: Contador y dueños Actividad de la empresa: Proveedores de energia Ventas de la empresa: $64 millones Buró de crédito: Ok Sector privado 100% Años de operación: 20 años Ubicación: Sonora Buscan conocer los servicios de Engen Capital y que tasas se manejan en Crédito. | J57: =IF(G57="",F57,G57) -> Pecom | K57: =IFERROR(VLOOKUP(Table1[[#This Row],[Top Parent]],'1.- Citas sin this week'!G:G,1,0),"New New") -> New New | L57: =_xlfn.XLOOKUP(Table1[[#This Row],[Top Parent]],Table3[Top Parent],Table3[Date]) -> #N/A | M57: =Table1[[#This Row],[Date]]-Table1[[#This Row],[Last Date]] -> #N/A | N57: =_xlfn.XLOOKUP(Table1[[#This Row],[Top Parent]],Table3[Top Parent],Table3[Owner Name]) -> #N/A | P57: Prospect | Q57: =IF(Table1[[#This Row],[Last Owner]]=Table1[[#This Row],[Owner Name]],"No","Si") -> #N/A | R57: =IF(Table1[[#This Row],[Diferencia de dias]]>182,"Si","No") -> #N/A | S57: Alexandra Luna | T57: =IF(Table1[[#This Row],[Owner de la cuenta]]=Table1[[#This Row],[Owner Name]],"Si","No") -> Si | U57: Sonora | V57: SFAC0005599116 | X57: Technology & Business Services
C58: =VLOOKUP(D58,Diccionario!A:B,2,0) -> Guadalajara | D58: Dulce Villegas | E58: Meeting | F58: Cervecería de Colima | H58: 46078 | I58: Conferencia con el cliente para retomar contacto y revisar la situación actual de la empresa para buscar oportunidades en las que pudiéramos sumar en este 2026. Han sido años cosechar lo que se ha venido sembrando en los últimos años, han presentado un buen crecimiento y siguen alcanzado buena penetración en el mercado. Oportunidades: S&LB de la línea de envasado y CAPEX para el 2026 que está enfocado en eliminar cuellos de botella que se tienen aún en una parte de la producción. Adicional a barriles de fermentación, planta tratadora de agua. Factoraje: Se invitó al especialista de factoraje, se acordó buscarlos a finales de la primera semana de marzo, para llevar a cabo la actualización del registro en Da Vinci y con ello poder analizar si es factible este producto y con qué deudores. Acuerdos: Se mandará los EEFF actualizados para analizar la situación actual de la empresa y con ello revisar la viabilidad de los proyectos. | J58: =IF(G58="",F58,G58) -> Cervecería de Colima | K58: =IFERROR(VLOOKUP(Table1[[#This Row],[Top Parent]],'1.- Citas sin this week'!G:G,1,0),"New New") -> Cervecería de Colima | L58: =_xlfn.XLOOKUP(Table1[[#This Row],[Top Parent]],Table3[Top Parent],Table3[Date]) -> 45968 | M58: =Table1[[#This Row],[Date]]-Table1[[#This Row],[Last Date]] -> 110 | N58: =_xlfn.XLOOKUP(Table1[[#This Row],[Top Parent]],Table3[Top Parent],Table3[Owner Name]) -> Dulce Villegas | P58: Dormant | Q58: =IF(Table1[[#This Row],[Last Owner]]=Table1[[#This Row],[Owner Name]],"No","Si") -> No | R58: =IF(Table1[[#This Row],[Diferencia de dias]]>182,"Si","No") -> No | S58: Dulce Villegas | T58: =IF(Table1[[#This Row],[Owner de la cuenta]]=Table1[[#This Row],[Owner Name]],"Si","No") -> Si | U58: Colima | V58: SFAC0006020764 | W58: 1 | X58: Food Bev & Ag
C59: =VLOOKUP(D59,Diccionario!A:B,2,0) -> LMM 4 | D59: Alexandra Luna | E59: Meeting | F59: DYLU SERVICIOS | H59: 46076 | I59: Cita por necesidad de adquisición de activo | J59: =IF(G59="",F59,G59) -> DYLU SERVICIOS | K59: =IFERROR(VLOOKUP(Table1[[#This Row],[Top Parent]],'1.- Citas sin this week'!G:G,1,0),"New New") -> New New | L59: =_xlfn.XLOOKUP(Table1[[#This Row],[Top Parent]],Table3[Top Parent],Table3[Date]) -> #N/A | M59: =Table1[[#This Row],[Date]]-Table1[[#This Row],[Last Date]] -> #N/A | N59: =_xlfn.XLOOKUP(Table1[[#This Row],[Top Parent]],Table3[Top Parent],Table3[Owner Name]) -> #N/A | P59: Prospect | Q59: =IF(Table1[[#This Row],[Last Owner]]=Table1[[#This Row],[Owner Name]],"No","Si") -> #N/A | R59: =IF(Table1[[#This Row],[Diferencia de dias]]>182,"Si","No") -> #N/A | S59: Alexandra Luna | T59: =IF(Table1[[#This Row],[Owner de la cuenta]]=Table1[[#This Row],[Owner Name]],"Si","No") -> Si | U59: Sonora | V59: SFAC0006110879 | X59: Misc Service Industries
C60: =VLOOKUP(D60,Diccionario!A:B,2,0) -> LMM 4 | D60: Alexandra Ramírez | E60: Meeting | F60: M25 INTERNATIONAL TECH | H60: 46078 | I60: Hora y fecha de cita: Miércoles 25 de febrero 1:00 pm Originador: Alexandra Ramírez Con quien se habló: Marco Ivan Puesto: Director de Finanzas Actividad de la empresa: Producción de equipos de tecnologia Ventas de la empresa: $180 millones Buró de crédito: Ok Sector privado 100% Años de operación: 36 años Ubicación: Durango Buscan Crédito y Factoraje, cliente desconfiado menciona que tiene maquinaria y sus clientes para factoraje son XUEHUA HUANG, GRAN VISTA ZHOU, AVILDIA entre otros, desea conocer tasas de interés para cada servicio. | J60: =IF(G60="",F60,G60) -> M25 INTERNATIONAL TECH | K60: =IFERROR(VLOOKUP(Table1[[#This Row],[Top Parent]],'1.- Citas sin this week'!G:G,1,0),"New New") -> M25 INTERNATIONAL TECH | L60: =_xlfn.XLOOKUP(Table1[[#This Row],[Top Parent]],Table3[Top Parent],Table3[Date]) -> 45828 | M60: =Table1[[#This Row],[Date]]-Table1[[#This Row],[Last Date]] -> 250 | N60: =_xlfn.XLOOKUP(Table1[[#This Row],[Top Parent]],Table3[Top Parent],Table3[Owner Name]) -> Alexandra Ramírez | P60: Prospect | Q60: =IF(Table1[[#This Row],[Last Owner]]=Table1[[#This Row],[Owner Name]],"No","Si") -> No | R60: =IF(Table1[[#This Row],[Diferencia de dias]]>182,"Si","No") -> Si | S60: Alexandra Ramírez | T60: =IF(Table1[[#This Row],[Owner de la cuenta]]=Table1[[#This Row],[Owner Name]],"Si","No") -> Si | U60: Durango | V60: SFAC0006095934 | X60: Industrial Products & Services
C61: =VLOOKUP(D61,Diccionario!A:B,2,0) -> Monterrey | D61: Miguel Antunez | E61: Presentacion Factoraje HS | F61: Centrus Packaging | H61: 46078 | I61: HS hara la presentacion del producto al cliente. | J61: =IF(G61="",F61,G61) -> Centrus Packaging | K61: =IFERROR(VLOOKUP(Table1[[#This Row],[Top Parent]],'1.- Citas sin this week'!G:G,1,0),"New New") -> Centrus Packaging | L61: =_xlfn.XLOOKUP(Table1[[#This Row],[Top Parent]],Table3[Top Parent],Table3[Date]) -> 46064 | M61: =Table1[[#This Row],[Date]]-Table1[[#This Row],[Last Date]] -> 14 | N61: =_xlfn.XLOOKUP(Table1[[#This Row],[Top Parent]],Table3[Top Parent],Table3[Owner Name]) -> Miguel Antunez | P61: Prospect | Q61: =IF(Table1[[#This Row],[Last Owner]]=Table1[[#This Row],[Owner Name]],"No","Si") -> No | R61: =IF(Table1[[#This Row],[Diferencia de dias]]>182,"Si","No") -> No | S61: Miguel Antunez | T61: =IF(Table1[[#This Row],[Owner de la cuenta]]=Table1[[#This Row],[Owner Name]],"Si","No") -> Si | U61: Baja California | V61: SFAC0006028758 | X61: Forest Products
C62: =VLOOKUP(D62,Diccionario!A:B,2,0) -> LMM 4 | D62: Alexandra Ramírez | E62: Meeting | F62: Ciemmobil | H62: 46078 | I62: Contacto: Armando de Degolla Actividad: Venta y renta de maquinaria / activos productivos Oportunidad: S&lb para 2 plataformas (60? y 45?), modelos 2025 Monto estimado: 2 MDP Ventas: 128 MDP (2025) Contexto: Refiere tener buen buró y no trabajar con Gob. Operación: +10 años Reunión: ? 24 FEB , 4:30 | J62: =IF(G62="",F62,G62) -> Ciemmobil | K62: =IFERROR(VLOOKUP(Table1[[#This Row],[Top Parent]],'1.- Citas sin this week'!G:G,1,0),"New New") -> New New | L62: =_xlfn.XLOOKUP(Table1[[#This Row],[Top Parent]],Table3[Top Parent],Table3[Date]) -> #N/A | M62: =Table1[[#This Row],[Date]]-Table1[[#This Row],[Last Date]] -> #N/A | N62: =_xlfn.XLOOKUP(Table1[[#This Row],[Top Parent]],Table3[Top Parent],Table3[Owner Name]) -> #N/A | P62: Prospect | Q62: =IF(Table1[[#This Row],[Last Owner]]=Table1[[#This Row],[Owner Name]],"No","Si") -> #N/A | R62: =IF(Table1[[#This Row],[Diferencia de dias]]>182,"Si","No") -> #N/A | S62: Alexandra Ramírez | T62: =IF(Table1[[#This Row],[Owner de la cuenta]]=Table1[[#This Row],[Owner Name]],"Si","No") -> Si | U62: Coahuila | V62: SFAC0006053071 | X62: Industrial Products & Services
C63: =VLOOKUP(D63,Diccionario!A:B,2,0) -> LMM 4 | D63: Mayreth García | E63: Meeting | F63: Mercados populares de Cuauhtemoc | H63: 46077 | I63: Se busca reunion con Beto para conocer la operacion de la empresa, se podria dar una opcion de linea de factoraje por sus plazos de pago con sus clientes de comedores industriales, el requerimiento actual es de compra de unos T380, se buscaran opciones con otros proveedores de camiones para enviar propuesta al cliente. | J63: =IF(G63="",F63,G63) -> Mercados populares de Cuauhtemoc | K63: =IFERROR(VLOOKUP(Table1[[#This Row],[Top Parent]],'1.- Citas sin this week'!G:G,1,0),"New New") -> New New | L63: =_xlfn.XLOOKUP(Table1[[#This Row],[Top Parent]],Table3[Top Parent],Table3[Date]) -> #N/A | M63: =Table1[[#This Row],[Date]]-Table1[[#This Row],[Last Date]] -> #N/A | N63: =_xlfn.XLOOKUP(Table1[[#This Row],[Top Parent]],Table3[Top Parent],Table3[Owner Name]) -> #N/A | Q63: =IF(Table1[[#This Row],[Last Owner]]=Table1[[#This Row],[Owner Name]],"No","Si") -> #N/A | R63: =IF(Table1[[#This Row],[Diferencia de dias]]>182,"Si","No") -> #N/A | S63: Mayreth García | T63: =IF(Table1[[#This Row],[Owner de la cuenta]]=Table1[[#This Row],[Owner Name]],"Si","No") -> Si | U63: Chihuahua | V63: SFAC0006110891 | X63: Retail
C64: =VLOOKUP(D64,Diccionario!A:B,2,0) -> LMM 5 | D64: Christian Gamboa | E64: Meeting | F64: SKN IMAGEN Y BELLEZA | H64: 46078 | I64: Reunión Revisión proyectos 2026, se tuvo un primer acercamiento con la compañia, de manera virtual, estamos buscando poder visitar su planta en Atizapan, vemos oportuinidades de arrendamiento, y de factoraje sin embargo es necesario tocar base con un DM que en este caso serian los dueños, Victor es nel Cahmpion en la operación, se trata de una compañia mexicana fundada en 2009 dedicada a la fabricación y comercialización de productos de belleza y cuidado personal, con enfoque en ofrecer artículos accesibles y de calidad al mercado nacional. Su operación incluye el desarrollo y producción de productos capilares y de cuidado personal, tales como: Silica capilar (gotas de seda) Shampoos Aceites para cabello Cremas y productos de cuidado personal Fijadores y moldeadores capilares | J64: =IF(G64="",F64,G64) -> SKN IMAGEN Y BELLEZA | K64: =IFERROR(VLOOKUP(Table1[[#This Row],[Top Parent]],'1.- Citas sin this week'!G:G,1,0),"New New") -> New New | L64: =_xlfn.XLOOKUP(Table1[[#This Row],[Top Parent]],Table3[Top Parent],Table3[Date]) -> #N/A | M64: =Table1[[#This Row],[Date]]-Table1[[#This Row],[Last Date]] -> #N/A | N64: =_xlfn.XLOOKUP(Table1[[#This Row],[Top Parent]],Table3[Top Parent],Table3[Owner Name]) -> #N/A | P64: Prospect | Q64: =IF(Table1[[#This Row],[Last Owner]]=Table1[[#This Row],[Owner Name]],"No","Si") -> #N/A | R64: =IF(Table1[[#This Row],[Diferencia de dias]]>182,"Si","No") -> #N/A | S64: Christian Gamboa | T64: =IF(Table1[[#This Row],[Owner de la cuenta]]=Table1[[#This Row],[Owner Name]],"Si","No") -> Si | U64: Estado de México | V64: SFAC0006044167 | X64: Chemicals & Plastics
C65: =VLOOKUP(D65,Diccionario!A:B,2,0) -> LMM 5 | D65: Christian Gamboa | E65: Meeting | F65: Cromher De Mexico | H65: 46078 | I65: 2da reunión con la compañia, se trata de un fabricante de productos adesivos, para la industrua papelera principalmente, tiene como principales clientes a Office Depot y Lumen, es una empresa en crecimiento sin embargo en este momento solo vemos oportunidad para poder financiar autos utilitarios. | J65: =IF(G65="",F65,G65) -> Cromher De Mexico | K65: New New | L65: =_xlfn.XLOOKUP(Table1[[#This Row],[Top Parent]],Table3[Top Parent],Table3[Date]) -> 45890 | M65: =Table1[[#This Row],[Date]]-Table1[[#This Row],[Last Date]] -> 188 | N65: =_xlfn.XLOOKUP(Table1[[#This Row],[Top Parent]],Table3[Top Parent],Table3[Owner Name]) -> Karol Alfaro | P65: Prospect | Q65: =IF(Table1[[#This Row],[Last Owner]]=Table1[[#This Row],[Owner Name]],"No","Si") -> Si | R65: =IF(Table1[[#This Row],[Diferencia de dias]]>182,"Si","No") -> Si | S65: Christian Gamboa | T65: =IF(Table1[[#This Row],[Owner de la cuenta]]=Table1[[#This Row],[Owner Name]],"Si","No") -> Si | U65: Estado de México | V65: SFAC0006091465 | X65: Chemicals & Plastics
C66: =VLOOKUP(D66,Diccionario!A:B,2,0) -> LMM 5 | D66: Ilan Mizrahi | E66: Meeting | F66: LOUNN | H66: 46077 | I66: Se tuvo junta con el CEO jesus, encontramos oportunidad de hacer relación con ellos como broker ya que se dedican a ser intermediarios de empresas que buscan creditos | J66: =IF(G66="",F66,G66) -> LOUNN | K66: =IFERROR(VLOOKUP(Table1[[#This Row],[Top Parent]],'1.- Citas sin this week'!G:G,1,0),"New New") -> New New | L66: =_xlfn.XLOOKUP(Table1[[#This Row],[Top Parent]],Table3[Top Parent],Table3[Date]) -> #N/A | M66: =Table1[[#This Row],[Date]]-Table1[[#This Row],[Last Date]] -> #N/A | N66: =_xlfn.XLOOKUP(Table1[[#This Row],[Top Parent]],Table3[Top Parent],Table3[Owner Name]) -> #N/A | P66: Prospect | Q66: =IF(Table1[[#This Row],[Last Owner]]=Table1[[#This Row],[Owner Name]],"No","Si") -> #N/A | R66: =IF(Table1[[#This Row],[Diferencia de dias]]>182,"Si","No") -> #N/A | S66: Ilan Mizrahi | T66: =IF(Table1[[#This Row],[Owner de la cuenta]]=Table1[[#This Row],[Owner Name]],"Si","No") -> Si | U66: Ciudad de México | V66: SFAC0006110878 | X66: Financial services
C67: =VLOOKUP(D67,Diccionario!A:B,2,0) -> Monterrey | D67: Edgar Rodriguez | E67: Meeting | F67: INGENIERIA METALICA Y PLASTICA DE MEXICO | H67: 46078 | I67: Se realizó visita de seguimiento con el cliente, quien reporta cumplimiento puntual en sus obligaciones financieras y buen historial con la banca. Durante 2025 cerraron con ventas aproximadas de USD 44 millones, ligeramente por debajo del año previo debido a efectos de tipo de cambio y pérdida temporal de un cliente relevante (restructuración corporativa). Para 2026 proyectan recuperación en ventas en dólares apoyados en nuevos proyectos que arrancan en mayo y octubre. Actualmente operan con tres líneas revolventes con BBVA, Banco Sabadell y Banorte por un total aproximado de $45 MDP, utilizadas de forma permanente para capital de trabajo, con clean-ups periódicos. Oportunidades detectadas: ? Posible reestructura de pasivos de corto a largo plazo (aprox. 50% de líneas actuales) para disminuir presión de renovaciones y riesgo de cancelación. ? Potencial financiamiento de nueva maquinaria (USD 500 mil ? 1 millón) sujeto a confirmación de proyectos. ? Interés en analizar esquema a 60?72 meses sin comisión, con tasa competitiva. Se acordó enviar estados financieros 2025 y preparar ejercicio numérico para evaluar viabilidad de migrar parte del pasivo revolvente a estructura de largo plazo. | J67: =IF(G67="",F67,G67) -> INGENIERIA METALICA Y PLASTICA DE MEXICO | K67: New New | L67: =_xlfn.XLOOKUP(Table1[[#This Row],[Top Parent]],Table3[Top Parent],Table3[Date]) -> 45840 | M67: =Table1[[#This Row],[Date]]-Table1[[#This Row],[Last Date]] -> 238 | N67: =_xlfn.XLOOKUP(Table1[[#This Row],[Top Parent]],Table3[Top Parent],Table3[Owner Name]) -> Dario del Río | P67: Dormant | Q67: =IF(Table1[[#This Row],[Last Owner]]=Table1[[#This Row],[Owner Name]],"No","Si") -> Si | R67: =IF(Table1[[#This Row],[Diferencia de dias]]>182,"Si","No") -> Si | S67: Edgar Rodriguez | T67: =IF(Table1[[#This Row],[Owner de la cuenta]]=Table1[[#This Row],[Owner Name]],"Si","No") -> Si | U67: Chihuahua | V67: SFAC0006072725 | W67: 5413728.8 | X67: Chemicals & Plastics
C68: =VLOOKUP(D68,Diccionario!A:B,2,0) -> LMM 5 | D68: Ilan Mizrahi | E68: Meeting | F68: Laboratorios San Angel | H68: 46076 | I68: Se tuvo reunion con abel CFO, nos comenta que en este momento la empresa laboratorios san angel, se encuentra en concurso mercantil, ya que el 70% esta centrado en gobierno, no es prospecto para engen. | J68: =IF(G68="",F68,G68) -> Laboratorios San Angel | K68: =IFERROR(VLOOKUP(Table1[[#This Row],[Top Parent]],'1.- Citas sin this week'!G:G,1,0),"New New") -> New New | L68: =_xlfn.XLOOKUP(Table1[[#This Row],[Top Parent]],Table3[Top Parent],Table3[Date]) -> #N/A | M68: =Table1[[#This Row],[Date]]-Table1[[#This Row],[Last Date]] -> #N/A | N68: =_xlfn.XLOOKUP(Table1[[#This Row],[Top Parent]],Table3[Top Parent],Table3[Owner Name]) -> #N/A | P68: Prospect | Q68: =IF(Table1[[#This Row],[Last Owner]]=Table1[[#This Row],[Owner Name]],"No","Si") -> #N/A | R68: =IF(Table1[[#This Row],[Diferencia de dias]]>182,"Si","No") -> #N/A | S68: Ilan Mizrahi | T68: =IF(Table1[[#This Row],[Owner de la cuenta]]=Table1[[#This Row],[Owner Name]],"Si","No") -> Si | U68: Ciudad de México | V68: SFAC0006016841 | X68: Healthcare
C69: =VLOOKUP(D69,Diccionario!A:B,2,0) -> Guadalajara | D69: Dulce Villegas | E69: Meeting | F69: Anteus Constructora | H69: 46078 | I69: Visita en las oficinas del cliente para retomar contacto y revisar la situación actual de la empresa para buscar oportunidades en las que pudiéramos sumar en este 2026. Han sido años complejos para la industria en la que se desarrollan, han estado buscando incursionar en nuevas estrategias de negocio. Están buscando cerrar un crédito con Bansi por MXN 400 MM para uno de sus proyectos por medio de un Loan. Oportunidades: S&LB de equipo amarillo y otro equipo que el cliente utiliza para su operación habitual. Se acordó que el cliente nos mande la lista de sus activos para con base en este definir el monto posible, hablamos de alrededor de MXN 50 MM de acuerdo a las políticas que tenemos en Engen para equipo usado. Este recurso será utilizado para capital de trabajo. | J69: =IF(G69="",F69,G69) -> Anteus Constructora | K69: =IFERROR(VLOOKUP(Table1[[#This Row],[Top Parent]],'1.- Citas sin this week'!G:G,1,0),"New New") -> Anteus Constructora | L69: =_xlfn.XLOOKUP(Table1[[#This Row],[Top Parent]],Table3[Top Parent],Table3[Date]) -> 45940 | M69: =Table1[[#This Row],[Date]]-Table1[[#This Row],[Last Date]] -> 138 | N69: =_xlfn.XLOOKUP(Table1[[#This Row],[Top Parent]],Table3[Top Parent],Table3[Owner Name]) -> Dulce Villegas | P69: Dormant | Q69: =IF(Table1[[#This Row],[Last Owner]]=Table1[[#This Row],[Owner Name]],"No","Si") -> No | R69: =IF(Table1[[#This Row],[Diferencia de dias]]>182,"Si","No") -> No | S69: Dulce Villegas | T69: =IF(Table1[[#This Row],[Owner de la cuenta]]=Table1[[#This Row],[Owner Name]],"Si","No") -> Si | U69: Jalisco | V69: SFAC0002806265 | W69: 0 | X69: Construction
C70: =VLOOKUP(D70,Diccionario!A:B,2,0) -> LMM 5 | D70: Jorge Avendaño | E70: Meeting | F70: Softelligence | H70: 46079 | I70: proyecto nuevo con AT&T para el que requiere capital de trabajo | J70: =IF(G70="",F70,G70) -> Softelligence | K70: =IFERROR(VLOOKUP(Table1[[#This Row],[Top Parent]],'1.- Citas sin this week'!G:G,1,0),"New New") -> New New | L70: =_xlfn.XLOOKUP(Table1[[#This Row],[Top Parent]],Table3[Top Parent],Table3[Date]) -> #N/A | M70: =Table1[[#This Row],[Date]]-Table1[[#This Row],[Last Date]] -> #N/A | N70: =_xlfn.XLOOKUP(Table1[[#This Row],[Top Parent]],Table3[Top Parent],Table3[Owner Name]) -> #N/A | P70: Prospect | Q70: =IF(Table1[[#This Row],[Last Owner]]=Table1[[#This Row],[Owner Name]],"No","Si") -> #N/A | R70: =IF(Table1[[#This Row],[Diferencia de dias]]>182,"Si","No") -> #N/A | S70: Jorge Avendaño | T70: =IF(Table1[[#This Row],[Owner de la cuenta]]=Table1[[#This Row],[Owner Name]],"Si","No") -> Si | U70: Querétaro | V70: SFAC0006034161 | X70: Telecom
C71: =VLOOKUP(D71,Diccionario!A:B,2,0) -> LMM 5 | D71: Jorge Avendaño | E71: Meeting | F71: SIISA SOLUCIONES | H71: 46078 | I71: revisión de proyectos llave en mano para clientes finales | J71: =IF(G71="",F71,G71) -> SIISA SOLUCIONES | K71: =IFERROR(VLOOKUP(Table1[[#This Row],[Top Parent]],'1.- Citas sin this week'!G:G,1,0),"New New") -> New New | L71: =_xlfn.XLOOKUP(Table1[[#This Row],[Top Parent]],Table3[Top Parent],Table3[Date]) -> #N/A | M71: =Table1[[#This Row],[Date]]-Table1[[#This Row],[Last Date]] -> #N/A | N71: =_xlfn.XLOOKUP(Table1[[#This Row],[Top Parent]],Table3[Top Parent],Table3[Owner Name]) -> #N/A | P71: Prospect | Q71: =IF(Table1[[#This Row],[Last Owner]]=Table1[[#This Row],[Owner Name]],"No","Si") -> #N/A | R71: =IF(Table1[[#This Row],[Diferencia de dias]]>182,"Si","No") -> #N/A | S71: Jorge Avendaño | T71: =IF(Table1[[#This Row],[Owner de la cuenta]]=Table1[[#This Row],[Owner Name]],"Si","No") -> Si | U71: Querétaro | V71: SFAC0006107861 | X71: Construction
C72: =VLOOKUP(D72,Diccionario!A:B,2,0) -> LMM 5 | D72: Julieta Medrano | E72: Meeting | F72: Remake Advertising | H72: 46079 | I72: -Hable con Angie Flores. -Contadora de la empresa. -Dedicados a construcción y mantenimiento industrial. -Interesados en adquirir vehículos para su operación, Nissan Urvan y Chevrolet Tornado, palazo de 36 meses, seguro diferido. -Ventas de 45 MDP -Buen buró. No trabaja con gobierno. -Mas de 3 años operando. -Ubicados en CDMX | J72: =IF(G72="",F72,G72) -> Remake Advertising | K72: =IFERROR(VLOOKUP(Table1[[#This Row],[Top Parent]],'1.- Citas sin this week'!G:G,1,0),"New New") -> New New | L72: =_xlfn.XLOOKUP(Table1[[#This Row],[Top Parent]],Table3[Top Parent],Table3[Date]) -> #N/A | M72: =Table1[[#This Row],[Date]]-Table1[[#This Row],[Last Date]] -> #N/A | N72: =_xlfn.XLOOKUP(Table1[[#This Row],[Top Parent]],Table3[Top Parent],Table3[Owner Name]) -> #N/A | Q72: =IF(Table1[[#This Row],[Last Owner]]=Table1[[#This Row],[Owner Name]],"No","Si") -> #N/A | R72: =IF(Table1[[#This Row],[Diferencia de dias]]>182,"Si","No") -> #N/A | S72: Julieta Medrano | T72: =IF(Table1[[#This Row],[Owner de la cuenta]]=Table1[[#This Row],[Owner Name]],"Si","No") -> Si | U72: Ciudad de México | V72: SFAC0006110886 | X72: Construction
C73: =VLOOKUP(D73,Diccionario!A:B,2,0) -> LMM 1 | D73: Juan Villaseñor | E73: Meeting | F73: Nutriesence | H73: 46078 | I73: Hora y fecha de cita: Miércoles 25 de febrero 2026, 10:30 hrs. Originador asignado: Juan Villaseñor Con quien se habló: Gustavo Crespo Puesto: Tomador de decisión Actividad de la empresa: Comercialización de productos alimenticios para animales. Oportunidad identificada: Mailing febrero 2026 Ventas de la empresa: $ 116,000,000.00 Buró de crédito: Saludable Tipo de ventas: Sector privado. Años de operación: 8 años Ubicación: Chapultepec 15, Ladron de Guevara 44650 Guadalajara, Jalisco México Producto: Busca inyección de capital por 3 a 5 mdp | J73: =IF(G73="",F73,G73) -> Nutriesence | K73: =IFERROR(VLOOKUP(Table1[[#This Row],[Top Parent]],'1.- Citas sin this week'!G:G,1,0),"New New") -> Nutriesence | L73: =_xlfn.XLOOKUP(Table1[[#This Row],[Top Parent]],Table3[Top Parent],Table3[Date]) -> 45734 | M73: =Table1[[#This Row],[Date]]-Table1[[#This Row],[Last Date]] -> 344 | N73: =_xlfn.XLOOKUP(Table1[[#This Row],[Top Parent]],Table3[Top Parent],Table3[Owner Name]) -> Juan Villaseñor | P73: Prospect | Q73: =IF(Table1[[#This Row],[Last Owner]]=Table1[[#This Row],[Owner Name]],"No","Si") -> No | R73: =IF(Table1[[#This Row],[Diferencia de dias]]>182,"Si","No") -> Si | S73: Juan Villaseñor | T73: =IF(Table1[[#This Row],[Owner de la cuenta]]=Table1[[#This Row],[Owner Name]],"Si","No") -> Si | U73: Jalisco | V73: SFAC0006086217 | X73: Food Bev & Ag
C74: =VLOOKUP(D74,Diccionario!A:B,2,0) -> LMM 3 | D74: Vadir Peña | E74: Meeting | F74: Baco Transportes | H74: 46078 | I74: Tuvimos reunión con la C.P. Ingrid Gutiérrez y Manuel y el C.P. Marco Antonio Cruz, donde destacó la búsqueda de una línea de factoraje a proveedores y de un refinanciamiento, adicional, durante el año se está considerando adquirir 4 unidades más International. | J74: =IF(G74="",F74,G74) -> Baco Transportes | K74: New New | L74: =_xlfn.XLOOKUP(Table1[[#This Row],[Top Parent]],Table3[Top Parent],Table3[Date]) -> 45827 | M74: =Table1[[#This Row],[Date]]-Table1[[#This Row],[Last Date]] -> 251 | N74: =_xlfn.XLOOKUP(Table1[[#This Row],[Top Parent]],Table3[Top Parent],Table3[Owner Name]) -> Diego Aviña | P74: Dormant | Q74: =IF(Table1[[#This Row],[Last Owner]]=Table1[[#This Row],[Owner Name]],"No","Si") -> Si | R74: =IF(Table1[[#This Row],[Diferencia de dias]]>182,"Si","No") -> Si | S74: Vadir Peña | T74: =IF(Table1[[#This Row],[Owner de la cuenta]]=Table1[[#This Row],[Owner Name]],"Si","No") -> Si | U74: Veracruz | V74: SFAC0006054810 | W74: 19335242 | X74: Transportation
C75: =VLOOKUP(D75,Diccionario!A:B,2,0) -> LMM 5 | D75: Mauricio Ortiz | E75: Meeting | F75: FOOD PROTEINS CORPORATION | H75: 46078 | I75: Cita con Eduardo Pinzón Gerente de finanzas Leads que surgieron: 1.-Financiamiento con garantía hipotecaria de 80MDP 2.-Factoraje (actualmente con Nafinsa) 3.-Camión Scania Eléctrico 4.-Fleet | J75: =IF(G75="",F75,G75) -> FOOD PROTEINS CORPORATION | K75: =IFERROR(VLOOKUP(Table1[[#This Row],[Top Parent]],'1.- Citas sin this week'!G:G,1,0),"New New") -> New New | L75: =_xlfn.XLOOKUP(Table1[[#This Row],[Top Parent]],Table3[Top Parent],Table3[Date]) -> #N/A | M75: =Table1[[#This Row],[Date]]-Table1[[#This Row],[Last Date]] -> #N/A | N75: =_xlfn.XLOOKUP(Table1[[#This Row],[Top Parent]],Table3[Top Parent],Table3[Owner Name]) -> #N/A | P75: Dormant | Q75: =IF(Table1[[#This Row],[Last Owner]]=Table1[[#This Row],[Owner Name]],"No","Si") -> #N/A | R75: =IF(Table1[[#This Row],[Diferencia de dias]]>182,"Si","No") -> #N/A | S75: Mauricio Ortiz | T75: =IF(Table1[[#This Row],[Owner de la cuenta]]=Table1[[#This Row],[Owner Name]],"Si","No") -> Si | U75: Ciudad de México | V75: SFAC0003707356 | W75: 56824.1 | X75: Food Bev & Ag
C76: =VLOOKUP(D76,Diccionario!A:B,2,0) -> LMM 5 | D76: Julieta Medrano | E76: Meeting | F76: Miguel Angel Jímenez | H76: 46079 | I76: Se tiene contacto con Miguel es el asesor del Dr, quién comenta que requiere adquirir una cotización para un automóvil BMW (se adjunta cotización) DR RICARDO NUÑEZ VERDIN/ Novapel con años de experiencia en medicina estética e implantes capilares. Se cotiza con ONE FLEET | J76: =IF(G76="",F76,G76) -> Miguel Angel Jímenez | K76: =IFERROR(VLOOKUP(Table1[[#This Row],[Top Parent]],'1.- Citas sin this week'!G:G,1,0),"New New") -> New New | L76: =_xlfn.XLOOKUP(Table1[[#This Row],[Top Parent]],Table3[Top Parent],Table3[Date]) -> #N/A | M76: =Table1[[#This Row],[Date]]-Table1[[#This Row],[Last Date]] -> #N/A | N76: =_xlfn.XLOOKUP(Table1[[#This Row],[Top Parent]],Table3[Top Parent],Table3[Owner Name]) -> #N/A | Q76: =IF(Table1[[#This Row],[Last Owner]]=Table1[[#This Row],[Owner Name]],"No","Si") -> #N/A | R76: =IF(Table1[[#This Row],[Diferencia de dias]]>182,"Si","No") -> #N/A | S76: Julieta Medrano | T76: =IF(Table1[[#This Row],[Owner de la cuenta]]=Table1[[#This Row],[Owner Name]],"Si","No") -> Si | U76: Jalisco | V76: SFAC0006110889 | X76: Unknown
C77: =VLOOKUP(D77,Diccionario!A:B,2,0) -> LMM 5 | D77: Julieta Medrano | E77: Call | F77: Industrias Plásticas de San Luis | H77: 46078 | I77: Cliente interesado en equipo de plastico por crecimiento, se cotizará un PP 30% 70% con 4 meses de entrega. Fabrican bolsas, sogas, cuerdas y rafia | J77: =IF(G77="",F77,G77) -> Industrias Plásticas de San Luis | K77: =IFERROR(VLOOKUP(Table1[[#This Row],[Top Parent]],'1.- Citas sin this week'!G:G,1,0),"New New") -> New New | L77: =_xlfn.XLOOKUP(Table1[[#This Row],[Top Parent]],Table3[Top Parent],Table3[Date]) -> #N/A | M77: =Table1[[#This Row],[Date]]-Table1[[#This Row],[Last Date]] -> #N/A | N77: =_xlfn.XLOOKUP(Table1[[#This Row],[Top Parent]],Table3[Top Parent],Table3[Owner Name]) -> #N/A | Q77: =IF(Table1[[#This Row],[Last Owner]]=Table1[[#This Row],[Owner Name]],"No","Si") -> #N/A | R77: =IF(Table1[[#This Row],[Diferencia de dias]]>182,"Si","No") -> #N/A | S77: Julieta Medrano | T77: =IF(Table1[[#This Row],[Owner de la cuenta]]=Table1[[#This Row],[Owner Name]],"Si","No") -> Si | U77: San Luis Potosí | V77: SFAC0006110883 | X77: Chemicals & Plastics
C78: =VLOOKUP(D78,Diccionario!A:B,2,0) -> LMM 5 | D78: Julieta Medrano | E78: Meeting | F78: Servicios de Analisis Tecnicos | H78: 46077 | I78: Lic. Víctor Rello Director General Actividad de la empresa: Laboratorio de pruebas de la rama eléctrica- electrónica. Oportunidad identificada: general-website Ventas $35,000,000 margen 25% Buró de crédito: ok Años de operación: 31 años Producto: AP adquisición de Equipo de Alta tecnología para efectuar pruebas en el espectro radioeléctrico, tales como antenas, analizadores de espectro, generadores de señal y simuladores digitales | J78: =IF(G78="",F78,G78) -> Servicios de Analisis Tecnicos | K78: =IFERROR(VLOOKUP(Table1[[#This Row],[Top Parent]],'1.- Citas sin this week'!G:G,1,0),"New New") -> New New | L78: =_xlfn.XLOOKUP(Table1[[#This Row],[Top Parent]],Table3[Top Parent],Table3[Date]) -> #N/A | M78: =Table1[[#This Row],[Date]]-Table1[[#This Row],[Last Date]] -> #N/A | N78: =_xlfn.XLOOKUP(Table1[[#This Row],[Top Parent]],Table3[Top Parent],Table3[Owner Name]) -> #N/A | Q78: =IF(Table1[[#This Row],[Last Owner]]=Table1[[#This Row],[Owner Name]],"No","Si") -> #N/A | R78: =IF(Table1[[#This Row],[Diferencia de dias]]>182,"Si","No") -> #N/A | S78: Julieta Medrano | T78: =IF(Table1[[#This Row],[Owner de la cuenta]]=Table1[[#This Row],[Owner Name]],"Si","No") -> Si | U78: Ciudad de México | V78: SFAC0006110881 | X78: Misc Service Industries
C79: =VLOOKUP(D79,Diccionario!A:B,2,0) -> LMM 3 | D79: Braulio Martinez | E79: Meeting | F79: Hyrcosa | H79: 46078 | I79: Reunión para definición del activo y nuevo proyecto de paneles solares, se presentará nuevo proveedor | J79: =IF(G79="",F79,G79) -> Hyrcosa | K79: =IFERROR(VLOOKUP(Table1[[#This Row],[Top Parent]],'1.- Citas sin this week'!G:G,1,0),"New New") -> Hyrcosa | L79: =_xlfn.XLOOKUP(Table1[[#This Row],[Top Parent]],Table3[Top Parent],Table3[Date]) -> 45889 | M79: =Table1[[#This Row],[Date]]-Table1[[#This Row],[Last Date]] -> 189 | N79: =_xlfn.XLOOKUP(Table1[[#This Row],[Top Parent]],Table3[Top Parent],Table3[Owner Name]) -> Braulio Martinez | P79: Prospect | Q79: =IF(Table1[[#This Row],[Last Owner]]=Table1[[#This Row],[Owner Name]],"No","Si") -> No | R79: =IF(Table1[[#This Row],[Diferencia de dias]]>182,"Si","No") -> Si | S79: Braulio Martinez | T79: =IF(Table1[[#This Row],[Owner de la cuenta]]=Table1[[#This Row],[Owner Name]],"Si","No") -> Si | U79: Oaxaca | V79: SFAC0006105038 | X79: Food Bev & Ag
C80: =VLOOKUP(D80,Diccionario!A:B,2,0) -> LMM 5 | D80: Julieta Medrano | E80: Meeting | F80: Movilab SA de CV | H80: 46077 | I80: Con quien se hablo: Janet Rojas Dir Actividad de la empresa: Laboratorio de análisis, profesionales, científicos y técnicos del petróleo Ventas $33,000,000.00 Buró de crédito: Ok Tipo de ventas: Sector privado 98%, sector gobierno 2% Años de operación: 32 años Producto: Prospecto interesado en inyección de capital, interesado en conocer oportunidad tanto en crédito simple o s&lb, cuenta equipamiento especializado para el análisis de hidrocarburos se anexa inventario total. Busca 1.5mpd a 24 meses | J80: =IF(G80="",F80,G80) -> Movilab SA de CV | K80: =IFERROR(VLOOKUP(Table1[[#This Row],[Top Parent]],'1.- Citas sin this week'!G:G,1,0),"New New") -> New New | L80: =_xlfn.XLOOKUP(Table1[[#This Row],[Top Parent]],Table3[Top Parent],Table3[Date]) -> #N/A | M80: =Table1[[#This Row],[Date]]-Table1[[#This Row],[Last Date]] -> #N/A | N80: =_xlfn.XLOOKUP(Table1[[#This Row],[Top Parent]],Table3[Top Parent],Table3[Owner Name]) -> #N/A | Q80: =IF(Table1[[#This Row],[Last Owner]]=Table1[[#This Row],[Owner Name]],"No","Si") -> #N/A | R80: =IF(Table1[[#This Row],[Diferencia de dias]]>182,"Si","No") -> #N/A | S80: Julieta Medrano | T80: =IF(Table1[[#This Row],[Owner de la cuenta]]=Table1[[#This Row],[Owner Name]],"Si","No") -> Si | U80: Estado de México | V80: SFAC0006110880 | X80: Misc Service Industries
C81: =VLOOKUP(D81,Diccionario!A:B,2,0) -> LMM 1 | D81: Alejandro Monteón | E81: Meeting | F81: Keymax Comercializadora | H81: 46077 | I81: Seguimiento a cotización de ppt de servidores así como seguimiento al checklist para ingresar a crédito. | J81: =IF(G81="",F81,G81) -> Keymax Comercializadora | K81: =IFERROR(VLOOKUP(Table1[[#This Row],[Top Parent]],'1.- Citas sin this week'!G:G,1,0),"New New") -> Keymax Comercializadora | L81: =_xlfn.XLOOKUP(Table1[[#This Row],[Top Parent]],Table3[Top Parent],Table3[Date]) -> 46051 | M81: =Table1[[#This Row],[Date]]-Table1[[#This Row],[Last Date]] -> 26 | N81: =_xlfn.XLOOKUP(Table1[[#This Row],[Top Parent]],Table3[Top Parent],Table3[Owner Name]) -> Alejandro Monteón | P81: Active | Q81: =IF(Table1[[#This Row],[Last Owner]]=Table1[[#This Row],[Owner Name]],"No","Si") -> No | R81: =IF(Table1[[#This Row],[Diferencia de dias]]>182,"Si","No") -> No | S81: Alejandro Monteón | T81: =IF(Table1[[#This Row],[Owner de la cuenta]]=Table1[[#This Row],[Owner Name]],"Si","No") -> Si | U81: Jalisco | V81: SFAC0006087399 | W81: 7425419.4 | X81: Technology & Business Services
C82: =VLOOKUP(D82,Diccionario!A:B,2,0) -> LMM 5 | D82: Julieta Medrano | E82: Meeting | F82: PRODUCTORA HUEVO SAN LUIS | H82: 46077 | I82: CFO Eduardo Chiapa Actividad de la empresa: Producción de huevo Ventas de la empresa: $49 millones Buró de crédito: Ok Sector privado 100% Años de operación: 8 años Ubicación: San Luis Potosi Buscan Sale and Lease Back de una maquinaria productora de huevo, adjunto cotización. Requieren 4 meses de low high ya que el destino del recurso es comprar pollas para que maduren y en 16 semanas puedan producir huevo | J82: =IF(G82="",F82,G82) -> PRODUCTORA HUEVO SAN LUIS | K82: =IFERROR(VLOOKUP(Table1[[#This Row],[Top Parent]],'1.- Citas sin this week'!G:G,1,0),"New New") -> New New | L82: =_xlfn.XLOOKUP(Table1[[#This Row],[Top Parent]],Table3[Top Parent],Table3[Date]) -> #N/A | M82: =Table1[[#This Row],[Date]]-Table1[[#This Row],[Last Date]] -> #N/A | N82: =_xlfn.XLOOKUP(Table1[[#This Row],[Top Parent]],Table3[Top Parent],Table3[Owner Name]) -> #N/A | P82: Prospect | Q82: =IF(Table1[[#This Row],[Last Owner]]=Table1[[#This Row],[Owner Name]],"No","Si") -> #N/A | R82: =IF(Table1[[#This Row],[Diferencia de dias]]>182,"Si","No") -> #N/A | S82: Julieta Medrano | T82: =IF(Table1[[#This Row],[Owner de la cuenta]]=Table1[[#This Row],[Owner Name]],"Si","No") -> Si | U82: San Luis Potosí | V82: SFAC0006074350 | X82: Food Bev & Ag
C83: =VLOOKUP(D83,Diccionario!A:B,2,0) -> LMM 5 | D83: Monserrat Villanueva | E83: Meeting | F83: Moons Dental | H83: 46076 | I83: Reunión con Leonardo Mirón, COO de Moons y Futura Labs (razon social que fabrica los alineadores), nos aceptó la llamada para ver si podiamos competir al esquema de Lease 4 U con quienes generan leads de doctores para venderles sus scanners dentales c/u cuesta 90K MXN por lo que no existe viabilidad. Confirma ventas de 260MDP y me pide buscarlo para agendar otra llamada pero con el CFO de la empresa y ver temas de arrendamiento de activos propios, hoy todo lo hacen a través de Equity y me comenta que aun traen pérdidas operativas. Se dará seguimiento. | J83: =IF(G83="",F83,G83) -> Moons Dental | K83: =IFERROR(VLOOKUP(Table1[[#This Row],[Top Parent]],'1.- Citas sin this week'!G:G,1,0),"New New") -> New New | L83: =_xlfn.XLOOKUP(Table1[[#This Row],[Top Parent]],Table3[Top Parent],Table3[Date]) -> #N/A | M83: =Table1[[#This Row],[Date]]-Table1[[#This Row],[Last Date]] -> #N/A | N83: =_xlfn.XLOOKUP(Table1[[#This Row],[Top Parent]],Table3[Top Parent],Table3[Owner Name]) -> #N/A | P83: Prospect | Q83: =IF(Table1[[#This Row],[Last Owner]]=Table1[[#This Row],[Owner Name]],"No","Si") -> #N/A | R83: =IF(Table1[[#This Row],[Diferencia de dias]]>182,"Si","No") -> #N/A | S83: Monserrat Villanueva | T83: =IF(Table1[[#This Row],[Owner de la cuenta]]=Table1[[#This Row],[Owner Name]],"Si","No") -> Si | U83: Ciudad de México | V83: SFAC0006087395 | X83: Healthcare
C84: =VLOOKUP(D84,Diccionario!A:B,2,0) -> LMM 4 | D84: Alexandra Ramírez | E84: Meeting | F84: Agricenter zevilla | H84: 46077 | I84: reunion con macriss zesati, en este momento no hay requerimientos | J84: =IF(G84="",F84,G84) -> Agricenter zevilla | K84: =IFERROR(VLOOKUP(Table1[[#This Row],[Top Parent]],'1.- Citas sin this week'!G:G,1,0),"New New") -> Agricenter zevilla | L84: =_xlfn.XLOOKUP(Table1[[#This Row],[Top Parent]],Table3[Top Parent],Table3[Date]) -> 45925 | M84: =Table1[[#This Row],[Date]]-Table1[[#This Row],[Last Date]] -> 152 | N84: =_xlfn.XLOOKUP(Table1[[#This Row],[Top Parent]],Table3[Top Parent],Table3[Owner Name]) -> Alexandra Ramírez | P84: Prospect | Q84: =IF(Table1[[#This Row],[Last Owner]]=Table1[[#This Row],[Owner Name]],"No","Si") -> No | R84: =IF(Table1[[#This Row],[Diferencia de dias]]>182,"Si","No") -> No | S84: Alexandra Ramírez | T84: =IF(Table1[[#This Row],[Owner de la cuenta]]=Table1[[#This Row],[Owner Name]],"Si","No") -> Si | U84: Coahuila | V84: SFAC0006009872 | X84: Food Bev & Ag
C85: =VLOOKUP(D85,Diccionario!A:B,2,0) -> LMM 5 | D85: Ramón Pérez | E85: Meeting | F85: XK NET | H85: 46080 | I85: se tiene contacto con José López empresa dedicada implementación de fibra Óptica con mas de 25 años de experiencias facturación de 130 millones de pesos en 2025 refiere tener buen buro no trabaja con gobierno comenta que que esta interesado en 10 hyundai i10 valor de $2,759,000 pesos a 36 meses | J85: =IF(G85="",F85,G85) -> XK NET | K85: =IFERROR(VLOOKUP(Table1[[#This Row],[Top Parent]],'1.- Citas sin this week'!G:G,1,0),"New New") -> New New | L85: =_xlfn.XLOOKUP(Table1[[#This Row],[Top Parent]],Table3[Top Parent],Table3[Date]) -> #N/A | M85: =Table1[[#This Row],[Date]]-Table1[[#This Row],[Last Date]] -> #N/A | N85: =_xlfn.XLOOKUP(Table1[[#This Row],[Top Parent]],Table3[Top Parent],Table3[Owner Name]) -> #N/A | P85: Prospect | Q85: =IF(Table1[[#This Row],[Last Owner]]=Table1[[#This Row],[Owner Name]],"No","Si") -> #N/A | R85: =IF(Table1[[#This Row],[Diferencia de dias]]>182,"Si","No") -> #N/A | S85: Ramón Pérez | T85: =IF(Table1[[#This Row],[Owner de la cuenta]]=Table1[[#This Row],[Owner Name]],"Si","No") -> Si | U85: Quintana Roo | V85: SFAC0006089508 | X85: Misc Service Industries
C86: =VLOOKUP(D86,Diccionario!A:B,2,0) -> LMM 1 | D86: Roberto Anaya | E86: Meeting | F86: Suajes y Empaques | H86: 46077 | I86: Revisión propuesta One fleet | J86: =IF(G86="",F86,G86) -> Suajes y Empaques | K86: =IFERROR(VLOOKUP(Table1[[#This Row],[Top Parent]],'1.- Citas sin this week'!G:G,1,0),"New New") -> Suajes y Empaques | L86: =_xlfn.XLOOKUP(Table1[[#This Row],[Top Parent]],Table3[Top Parent],Table3[Date]) -> 46073 | M86: =Table1[[#This Row],[Date]]-Table1[[#This Row],[Last Date]] -> 4 | N86: =_xlfn.XLOOKUP(Table1[[#This Row],[Top Parent]],Table3[Top Parent],Table3[Owner Name]) -> Roberto Anaya | P86: Prospect | Q86: =IF(Table1[[#This Row],[Last Owner]]=Table1[[#This Row],[Owner Name]],"No","Si") -> No | R86: =IF(Table1[[#This Row],[Diferencia de dias]]>182,"Si","No") -> No | S86: Roberto Anaya | T86: =IF(Table1[[#This Row],[Owner de la cuenta]]=Table1[[#This Row],[Owner Name]],"Si","No") -> Si | U86: Guanajuato | V86: SFAC0006056557 | X86: Industrial Products & Services
C87: =VLOOKUP(D87,Diccionario!A:B,2,0) -> LMM 5 | D87: Ramón Pérez | E87: Meeting | F87: Productora De Alimentos Mexicanos | H87: 46076 | I87: Reunión con Jose Antonio Silveira, viene inversión fuerte en junio para una planta de bebidas | J87: =IF(G87="",F87,G87) -> Productora De Alimentos Mexicanos | K87: =IFERROR(VLOOKUP(Table1[[#This Row],[Top Parent]],'1.- Citas sin this week'!G:G,1,0),"New New") -> New New | L87: =_xlfn.XLOOKUP(Table1[[#This Row],[Top Parent]],Table3[Top Parent],Table3[Date]) -> #N/A | M87: =Table1[[#This Row],[Date]]-Table1[[#This Row],[Last Date]] -> #N/A | N87: =_xlfn.XLOOKUP(Table1[[#This Row],[Top Parent]],Table3[Top Parent],Table3[Owner Name]) -> #N/A | P87: Prospect | Q87: =IF(Table1[[#This Row],[Last Owner]]=Table1[[#This Row],[Owner Name]],"No","Si") -> #N/A | R87: =IF(Table1[[#This Row],[Diferencia de dias]]>182,"Si","No") -> #N/A | S87: Ramón Pérez | T87: =IF(Table1[[#This Row],[Owner de la cuenta]]=Table1[[#This Row],[Owner Name]],"Si","No") -> Si | U87: Yucatán | V87: SFAC0003592137 | X87: Food Bev & Ag
C88: =VLOOKUP(D88,Diccionario!A:B,2,0) -> México 2 | D88: Rafael Garcia | E88: Meeting | F88: Prefamovil Infraestructura | H88: 46077 | I88: Firma de anexo 7 y platica con Carlos Galica para ver el arrendamiento de las Gruas Sany. | J88: =IF(G88="",F88,G88) -> Prefamovil Infraestructura | K88: =IFERROR(VLOOKUP(Table1[[#This Row],[Top Parent]],'1.- Citas sin this week'!G:G,1,0),"New New") -> Prefamovil Infraestructura | L88: =_xlfn.XLOOKUP(Table1[[#This Row],[Top Parent]],Table3[Top Parent],Table3[Date]) -> 46073 | M88: =Table1[[#This Row],[Date]]-Table1[[#This Row],[Last Date]] -> 4 | N88: =_xlfn.XLOOKUP(Table1[[#This Row],[Top Parent]],Table3[Top Parent],Table3[Owner Name]) -> Rafael Garcia | P88: Active | Q88: =IF(Table1[[#This Row],[Last Owner]]=Table1[[#This Row],[Owner Name]],"No","Si") -> No | R88: =IF(Table1[[#This Row],[Diferencia de dias]]>182,"Si","No") -> No | S88: Rafael Garcia | T88: =IF(Table1[[#This Row],[Owner de la cuenta]]=Table1[[#This Row],[Owner Name]],"Si","No") -> Si | U88: Estado de México | V88: SFAC0006044982 | W88: 5469774.9 | X88: Construction
C89: =VLOOKUP(D89,Diccionario!A:B,2,0) -> México 1 | D89: Armando Estrada | E89: Reunión de Descubrimiento | F89: J. García López | G89: AlcisCorp | H89: 46079 | I89: Reunión con Mario Marín -CFO- | Hoy día trabajan con: i) Arrendadora Banorte, con la que atienden el arrendamiento de +100 vehículos (principalmente) + mobiliario y otros créditos. ii) Prioritas con la que atienden el arrendamiento de; hornos y mobiliario. iii) Active Leasing con la que atienden mobiliario y equipo para el hotel; Hotel Calypso. | El plan de CAPEX para este año es de alrededor de MXN 40m. | Siguientes pasos: 1) Hay una oportunidad inmediata para 3 hornos (USD 750k). 2) enviaran ejemplo de cotización de hornos. 3) realizaremos una propuesta y se coordinara una reunión presencial (tentativamente el jueves 05/03 o viernes 06/03) para discutirla y si es algo que les haga sentido (costo/beneficio), avanzamos con el proceso de calificaicón. | J89: =IF(G89="",F89,G89) -> AlcisCorp | K89: =IFERROR(VLOOKUP(Table1[[#This Row],[Top Parent]],'1.- Citas sin this week'!G:G,1,0),"New New") -> New New | L89: =_xlfn.XLOOKUP(Table1[[#This Row],[Top Parent]],Table3[Top Parent],Table3[Date]) -> #N/A | M89: =Table1[[#This Row],[Date]]-Table1[[#This Row],[Last Date]] -> #N/A | N89: =_xlfn.XLOOKUP(Table1[[#This Row],[Top Parent]],Table3[Top Parent],Table3[Owner Name]) -> #N/A | P89: Prospect | Q89: =IF(Table1[[#This Row],[Last Owner]]=Table1[[#This Row],[Owner Name]],"No","Si") -> #N/A | R89: =IF(Table1[[#This Row],[Diferencia de dias]]>182,"Si","No") -> #N/A | S89: Armando Estrada | T89: =IF(Table1[[#This Row],[Owner de la cuenta]]=Table1[[#This Row],[Owner Name]],"Si","No") -> Si | U89: Ciudad de México | V89: SFAC0006077115 | X89: Misc Service Industries
C90: =VLOOKUP(D90,Diccionario!A:B,2,0) -> LMM 1 | D90: Roberto Anaya | E90: Meeting | F90: Cortes Especializados de Papel | H90: 46077 | I90: Reunión con riesgos para revisar el tema de validación de facturas. | J90: =IF(G90="",F90,G90) -> Cortes Especializados de Papel | K90: =IFERROR(VLOOKUP(Table1[[#This Row],[Top Parent]],'1.- Citas sin this week'!G:G,1,0),"New New") -> Cortes Especializados de Papel | L90: =_xlfn.XLOOKUP(Table1[[#This Row],[Top Parent]],Table3[Top Parent],Table3[Date]) -> 46020 | M90: =Table1[[#This Row],[Date]]-Table1[[#This Row],[Last Date]] -> 57 | N90: =_xlfn.XLOOKUP(Table1[[#This Row],[Top Parent]],Table3[Top Parent],Table3[Owner Name]) -> Roberto Anaya | P90: Prospect | Q90: =IF(Table1[[#This Row],[Last Owner]]=Table1[[#This Row],[Owner Name]],"No","Si") -> No | R90: =IF(Table1[[#This Row],[Diferencia de dias]]>182,"Si","No") -> No | S90: Roberto Anaya | T90: =IF(Table1[[#This Row],[Owner de la cuenta]]=Table1[[#This Row],[Owner Name]],"Si","No") -> Si | U90: Guanajuato | V90: SFAC0006009304 | X90: Forest Products
C91: =VLOOKUP(D91,Diccionario!A:B,2,0) -> México 1 | D91: Fernando Martin | E91: Descubrimiento | F91: Distribuidora De Ropa Viva | H91: 46079 | I91: Reunión con Jack Salame (finanzas). Empresa dedicada de manera vertical al diseño, tejido, acabado, corte, estampado, lavado y empaque de textiles, principalmente playeras y sudaderas. Vende a tiendas de autoservicio y también a tiendas departamentales. Anteriormente ya habían revisado opciones de financiamiento con Engen, pero en aquel momento la tasa no se ajustaba a las necesidades. En 2025 comentó que fue un año complicado para el sector, observó una contracción en ventas del 10% cerrando en 370 mdp Su principal problema actual es el tema de capital de trabajo, comenta que en la industria textil se sufre ya que el pago a proveedores es a 30 días mientras que sus clientes le pagan a 90-100 días. La empresa ya opera líneas de factoraje con BBVA en pesos y dólares; en dólares trae spread +3.5% y pesos quedó en confirmar ya que no lo recordaba. Adicional, trae dos líneas de crédito simple, una con HSBC y otra con BBVA; la de BBVA fue por la adquisición de maquinaria hace dos años y la de HSCB un S&LB que hicieron el año pasado para reestructurarse financieramente. Comenta que tienen alrededor de 80-90 mdp en activos en su planta en tepeji, sin embargo, más de la mitad están en garantía con sus líneas de crédito. De momento mostró interés en Factoraje, aunque mencionó que si no es más económico que lo que tiene actualmente no la usará. Su línea en pesos es de $40 mdp. Next steps: quedó en compartir tasas de sus pasivos, así como maquinaria libre de gravamen para estructurar una línea de capital de trabajo permanente; estas las han usado en el pasado a plazos de 36-48 meses. Se dará seguimiento y se coordinará segunda reunión una vez se tenga la información de factoraje, así como de sus activos | J91: =IF(G91="",F91,G91) -> Distribuidora De Ropa Viva | K91: =IFERROR(VLOOKUP(Table1[[#This Row],[Top Parent]],'1.- Citas sin this week'!G:G,1,0),"New New") -> New New | L91: =_xlfn.XLOOKUP(Table1[[#This Row],[Top Parent]],Table3[Top Parent],Table3[Date]) -> #N/A | M91: =Table1[[#This Row],[Date]]-Table1[[#This Row],[Last Date]] -> #N/A | N91: =_xlfn.XLOOKUP(Table1[[#This Row],[Top Parent]],Table3[Top Parent],Table3[Owner Name]) -> #N/A | P91: Prospect | Q91: =IF(Table1[[#This Row],[Last Owner]]=Table1[[#This Row],[Owner Name]],"No","Si") -> #N/A | R91: =IF(Table1[[#This Row],[Diferencia de dias]]>182,"Si","No") -> #N/A | S91: Fernando Martin | T91: =IF(Table1[[#This Row],[Owner de la cuenta]]=Table1[[#This Row],[Owner Name]],"Si","No") -> Si | U91: Ciudad de México | V91: SFAC0006000088 | X91: Industrial Products & Services
C92: =VLOOKUP(D92,Diccionario!A:B,2,0) -> México 1 | D92: Kenia Martinez | E92: Meeting | F92: Grupo Kuo | H92: 46077 | I92: Video C. Con Flor V. Seguimientos a NDA de ENGEN. Estatus de engrega de NDA de TIP, Conversamos sobre el esquema que estaremos manejando, cual es la razon por la cual existen dos entidades (ENGEN Y TIP) y que tratamiento interno deberia estar dando KUO. | J92: =IF(G92="",F92,G92) -> Grupo Kuo | K92: =IFERROR(VLOOKUP(Table1[[#This Row],[Top Parent]],'1.- Citas sin this week'!G:G,1,0),"New New") -> Grupo Kuo | L92: =_xlfn.XLOOKUP(Table1[[#This Row],[Top Parent]],Table3[Top Parent],Table3[Date]) -> 46059 | M92: =Table1[[#This Row],[Date]]-Table1[[#This Row],[Last Date]] -> 18 | N92: =_xlfn.XLOOKUP(Table1[[#This Row],[Top Parent]],Table3[Top Parent],Table3[Owner Name]) -> Kenia Martinez | P92: Dormant | Q92: =IF(Table1[[#This Row],[Last Owner]]=Table1[[#This Row],[Owner Name]],"No","Si") -> No | R92: =IF(Table1[[#This Row],[Diferencia de dias]]>182,"Si","No") -> No | S92: Kenia Martinez | T92: =IF(Table1[[#This Row],[Owner de la cuenta]]=Table1[[#This Row],[Owner Name]],"Si","No") -> Si | U92: Ciudad de México | V92: 1-EQA5LF | W92: 443963.8 | X92: Food Bev & Ag
C93: =VLOOKUP(D93,Diccionario!A:B,2,0) -> México 1 | D93: Kenia Martinez | E93: Email | F93: Cía Cerillera La Central | H93: 46078 | I93: Email de contacto que derivo en video c. Hola Lau mucho gusto. Soy Kenia Martinez, represento a ENGEN CAPITAL. Te contacto ya que Dorly Rabago sali? de la compa??a y yo tendr? el gusto de estar frente a la relaci?n comercial entre LA CENTRAL Y ENGEN. Me encantar?a reunirme contigo el martes o jueves de la siguiente semana para retomar las ?ltimas conversaciones de arrendamiento y refinanciamientos de pasivos, ?c?mo andas de agenda? Agradezco tus comentarios, saludos. Resultado de video c: Por ahora van a concluir lo que tiene con nosotros, no estan interesados en hacer mas operaciones con ENGEN, sumado a que actualmente no traen inversiones o necesidades nuevas en donde tengamos oportunidades. | J93: =IF(G93="",F93,G93) -> Cía Cerillera La Central | K93: =IFERROR(VLOOKUP(Table1[[#This Row],[Top Parent]],'1.- Citas sin this week'!G:G,1,0),"New New") -> New New | L93: =_xlfn.XLOOKUP(Table1[[#This Row],[Top Parent]],Table3[Top Parent],Table3[Date]) -> #N/A | M93: =Table1[[#This Row],[Date]]-Table1[[#This Row],[Last Date]] -> #N/A | N93: =_xlfn.XLOOKUP(Table1[[#This Row],[Top Parent]],Table3[Top Parent],Table3[Owner Name]) -> #N/A | P93: Prospect | Q93: =IF(Table1[[#This Row],[Last Owner]]=Table1[[#This Row],[Owner Name]],"No","Si") -> #N/A | R93: =IF(Table1[[#This Row],[Diferencia de dias]]>182,"Si","No") -> #N/A | S93: Kenia Martinez | T93: =IF(Table1[[#This Row],[Owner de la cuenta]]=Table1[[#This Row],[Owner Name]],"Si","No") -> Si | U93: Estado de México | V93: 1-5NHK-826 | X93: Chemicals & Plastics
C94: =VLOOKUP(D94,Diccionario!A:B,2,0) -> México 2 | D94: Octavio Chimal | E94: Meeting | F94: Grupo Altex | H94: 46077 | I94: Videollamada con Estefanía Medel | J94: =IF(G94="",F94,G94) -> Grupo Altex | K94: =IFERROR(VLOOKUP(Table1[[#This Row],[Top Parent]],'1.- Citas sin this week'!G:G,1,0),"New New") -> Grupo Altex | L94: =_xlfn.XLOOKUP(Table1[[#This Row],[Top Parent]],Table3[Top Parent],Table3[Date]) -> 45938 | M94: =Table1[[#This Row],[Date]]-Table1[[#This Row],[Last Date]] -> 139 | N94: =_xlfn.XLOOKUP(Table1[[#This Row],[Top Parent]],Table3[Top Parent],Table3[Owner Name]) -> Octavio Chimal | P94: Active | Q94: =IF(Table1[[#This Row],[Last Owner]]=Table1[[#This Row],[Owner Name]],"No","Si") -> No | R94: =IF(Table1[[#This Row],[Diferencia de dias]]>182,"Si","No") -> No | S94: Octavio Chimal | T94: =IF(Table1[[#This Row],[Owner de la cuenta]]=Table1[[#This Row],[Owner Name]],"Si","No") -> Si | U94: Ciudad de México | V94: 1-46E2CE | W94: 19099988 | X94: Food Bev & Ag
C95: =VLOOKUP(D95,Diccionario!A:B,2,0) -> Monterrey | D95: Miguel Antunez | E95: Presentacion Factoraje Engen / Fleet OFS | F95: CY Alimentos | H95: 46077 | I95: Reunion con CEO y AL. Se realizo presentacion de nuestro producto. Principales clientes Abarrey y Casa Ley representan el 8% de sus ventas, utilizan cadenas productivas (Banorte y Bajio), 10 dias reciben el pago a partir de subir la factura con costo del 2.1% sobre el importe a disponer con anticipo del 100% de la factura. El resto de la cobranza la reciben en 15 dias promedio. Se mandara liga para firma. Se realizo presentacion de Fleet y se reviso la propuesta que se le mkando, dar seguimiento. | J95: =IF(G95="",F95,G95) -> CY Alimentos | K95: =IFERROR(VLOOKUP(Table1[[#This Row],[Top Parent]],'1.- Citas sin this week'!G:G,1,0),"New New") -> CY Alimentos | L95: =_xlfn.XLOOKUP(Table1[[#This Row],[Top Parent]],Table3[Top Parent],Table3[Date]) -> 46072 | M95: =Table1[[#This Row],[Date]]-Table1[[#This Row],[Last Date]] -> 5 | N95: =_xlfn.XLOOKUP(Table1[[#This Row],[Top Parent]],Table3[Top Parent],Table3[Owner Name]) -> Miguel Antunez | P95: Prospect | Q95: =IF(Table1[[#This Row],[Last Owner]]=Table1[[#This Row],[Owner Name]],"No","Si") -> No | R95: =IF(Table1[[#This Row],[Diferencia de dias]]>182,"Si","No") -> No | S95: Miguel Antunez | T95: =IF(Table1[[#This Row],[Owner de la cuenta]]=Table1[[#This Row],[Owner Name]],"Si","No") -> Si | U95: Sonora | V95: SFAC0006067050 | X95: Food Bev & Ag
C96: =VLOOKUP(D96,Diccionario!A:B,2,0) -> LMM 5 | D96: Monserrat Villanueva | E96: Meeting | F96: Ahumados Noruegos | H96: 46077 | I96: Cita con Sergio Arché y Nidia para revisar factoraje, empresa con ventas de 600mdp busca que adelantemos facturas de retail y hoteles en la riviera maya. Pide NDA para poder firmarse con CIEC. | J96: =IF(G96="",F96,G96) -> Ahumados Noruegos | K96: =IFERROR(VLOOKUP(Table1[[#This Row],[Top Parent]],'1.- Citas sin this week'!G:G,1,0),"New New") -> Ahumados Noruegos | L96: =_xlfn.XLOOKUP(Table1[[#This Row],[Top Parent]],Table3[Top Parent],Table3[Date]) -> 45728 | M96: =Table1[[#This Row],[Date]]-Table1[[#This Row],[Last Date]] -> 349 | N96: =_xlfn.XLOOKUP(Table1[[#This Row],[Top Parent]],Table3[Top Parent],Table3[Owner Name]) -> Monserrat Villanueva | P96: Prospect | Q96: =IF(Table1[[#This Row],[Last Owner]]=Table1[[#This Row],[Owner Name]],"No","Si") -> No | R96: =IF(Table1[[#This Row],[Diferencia de dias]]>182,"Si","No") -> Si | S96: Monserrat Villanueva | T96: =IF(Table1[[#This Row],[Owner de la cuenta]]=Table1[[#This Row],[Owner Name]],"Si","No") -> Si | U96: Estado de México | V96: SFAC0006008683 | X96: Food Bev & Ag
C97: =VLOOKUP(D97,Diccionario!A:B,2,0) -> México 2 | D97: Francisco Porragas | E97: Meeting | F97: Somos Carton | H97: 46079 | I97: Llamada con Jose Edgar del Bosque. Durante la conversación presenté a Engen y platicmaos un poco sobre el éxito que hemos tenido en empresas empacadoras. revismaos AP y Fleet, a lo que me comento que ahorita trabajan con otra arrendadora pero estan abiertos a escuchar ofertas. Por otro lado, al tocar Factoraje, le intereso el producto y me pidio enviar información por correo. Subo a Nidia al correo para entre ambos dar seguimiento al lead | J97: =IF(G97="",F97,G97) -> Somos Carton | K97: =IFERROR(VLOOKUP(Table1[[#This Row],[Top Parent]],'1.- Citas sin this week'!G:G,1,0),"New New") -> New New | L97: =_xlfn.XLOOKUP(Table1[[#This Row],[Top Parent]],Table3[Top Parent],Table3[Date]) -> #N/A | M97: =Table1[[#This Row],[Date]]-Table1[[#This Row],[Last Date]] -> #N/A | N97: =_xlfn.XLOOKUP(Table1[[#This Row],[Top Parent]],Table3[Top Parent],Table3[Owner Name]) -> #N/A | P97: Prospect | Q97: =IF(Table1[[#This Row],[Last Owner]]=Table1[[#This Row],[Owner Name]],"No","Si") -> #N/A | R97: =IF(Table1[[#This Row],[Diferencia de dias]]>182,"Si","No") -> #N/A | S97: Francisco Porragas | T97: =IF(Table1[[#This Row],[Owner de la cuenta]]=Table1[[#This Row],[Owner Name]],"Si","No") -> Si | U97: Estado de México | V97: SFAC0006110344 | X97: Forest Products
C98: =VLOOKUP(D98,Diccionario!A:B,2,0) -> México 2 | D98: Francisco Porragas | E98: Meeting | F98: Loglab Group | H98: 46078 | I98: Reunión con Carlos Lozano y Estafania Venegas (brooker). El cliente requiere de apoyo financiero para realizar una operación de compraventa de equipo de almacen (Racks, estantes, mezzanine). El cliente gano una licitación a Puma México, quienes pusieron a la venta el equipo debido a que no lo iban a requerir, el equipo tienen máximo 18 meses de uso. La operación que busca el cliente es un crédito para comprar el equipo y posteriormente venderlo a terceros. La oportunidad que nos presenta no es del interés de Engen por lo que se declino. | J98: =IF(G98="",F98,G98) -> Loglab Group | K98: =IFERROR(VLOOKUP(Table1[[#This Row],[Top Parent]],'1.- Citas sin this week'!G:G,1,0),"New New") -> New New | L98: =_xlfn.XLOOKUP(Table1[[#This Row],[Top Parent]],Table3[Top Parent],Table3[Date]) -> #N/A | M98: =Table1[[#This Row],[Date]]-Table1[[#This Row],[Last Date]] -> #N/A | N98: =_xlfn.XLOOKUP(Table1[[#This Row],[Top Parent]],Table3[Top Parent],Table3[Owner Name]) -> #N/A | P98: Prospect | Q98: =IF(Table1[[#This Row],[Last Owner]]=Table1[[#This Row],[Owner Name]],"No","Si") -> #N/A | R98: =IF(Table1[[#This Row],[Diferencia de dias]]>182,"Si","No") -> #N/A | S98: Francisco Porragas | T98: =IF(Table1[[#This Row],[Owner de la cuenta]]=Table1[[#This Row],[Owner Name]],"Si","No") -> Si | U98: Estado de México | V98: SFAC0006110350 | X98: Transportation
C99: =VLOOKUP(D99,Diccionario!A:B,2,0) -> México 2 | D99: Marco Cohen | E99: Meeting | F99: DISTRIBUIDORA DE INSUMOS DIECA | H99: 46079 | I99: Reunió n con Claret Colli, nos la recomendo Eduardo Diez de Osteomedica es una empresa que se dedica a lo mismo que ellos en el sureste y quieren arrendamiento de unas torres | J99: =IF(G99="",F99,G99) -> DISTRIBUIDORA DE INSUMOS DIECA | K99: =IFERROR(VLOOKUP(Table1[[#This Row],[Top Parent]],'1.- Citas sin this week'!G:G,1,0),"New New") -> New New | L99: =_xlfn.XLOOKUP(Table1[[#This Row],[Top Parent]],Table3[Top Parent],Table3[Date]) -> #N/A | M99: =Table1[[#This Row],[Date]]-Table1[[#This Row],[Last Date]] -> #N/A | N99: =_xlfn.XLOOKUP(Table1[[#This Row],[Top Parent]],Table3[Top Parent],Table3[Owner Name]) -> #N/A | Q99: =IF(Table1[[#This Row],[Last Owner]]=Table1[[#This Row],[Owner Name]],"No","Si") -> #N/A | R99: =IF(Table1[[#This Row],[Diferencia de dias]]>182,"Si","No") -> #N/A | S99: Marco Cohen | T99: =IF(Table1[[#This Row],[Owner de la cuenta]]=Table1[[#This Row],[Owner Name]],"Si","No") -> Si | U99: Yucatán | V99: SFAC0006110897 | X99: Healthcare
C100: =VLOOKUP(D100,Diccionario!A:B,2,0) -> México 2 | D100: Octavio Chimal | E100: Meeting | F100: Zf Chasis Components Toluca | G100: Zf Sachs Automotive México | H100: 46077 | I100: Se exploro leasing para inyectoras y CNC par Toluca y Saltillo | J100: =IF(G100="",F100,G100) -> Zf Sachs Automotive México | K100: =IFERROR(VLOOKUP(Table1[[#This Row],[Top Parent]],'1.- Citas sin this week'!G:G,1,0),"New New") -> New New | L100: =_xlfn.XLOOKUP(Table1[[#This Row],[Top Parent]],Table3[Top Parent],Table3[Date]) -> #N/A | M100: =Table1[[#This Row],[Date]]-Table1[[#This Row],[Last Date]] -> #N/A | N100: =_xlfn.XLOOKUP(Table1[[#This Row],[Top Parent]],Table3[Top Parent],Table3[Owner Name]) -> #N/A | P100: Prospect | Q100: =IF(Table1[[#This Row],[Last Owner]]=Table1[[#This Row],[Owner Name]],"No","Si") -> #N/A | R100: =IF(Table1[[#This Row],[Diferencia de dias]]>182,"Si","No") -> #N/A | S100: Octavio Chimal | T100: =IF(Table1[[#This Row],[Owner de la cuenta]]=Table1[[#This Row],[Owner Name]],"Si","No") -> Si | U100: Estado de México | V100: SFAC0003384928 | X100: Automotive
...

Sheet 1.- Citas sin this week
A1: Region | B1: Owner Name | C1: Subject | D1: Account Legal Name | E1: Top Parent Account | F1: Date | G1: Top Parent | H1: Account Status
B2: Julieta Medrano | C2: Meeting | D2: CONSORCIO INDUSTRIAL ELIGON | F2: 46073 | G2: =IF(Table3[[#This Row],[Top Parent Account]]="",Table3[[#This Row],[Account Legal Name]],Table3[[#This Row],[Top Parent Account]]) -> CONSORCIO INDUSTRIAL ELIGON
B3: Samuel Cepeda | C3: Meeting | D3: Naturesweet Invernaderos | F3: 46073 | G3: =IF(Table3[[#This Row],[Top Parent Account]]="",Table3[[#This Row],[Account Legal Name]],Table3[[#This Row],[Top Parent Account]]) -> Naturesweet Invernaderos
B4: Alexandra Ramírez | C4: Meeting | D4: LM Minería y Proyectos | F4: 46073 | G4: =IF(Table3[[#This Row],[Top Parent Account]]="",Table3[[#This Row],[Account Legal Name]],Table3[[#This Row],[Top Parent Account]]) -> LM Minería y Proyectos
B5: Rafael Garcia | C5: Meeting | D5: Prefamovil Infraestructura | F5: 46073 | G5: =IF(Table3[[#This Row],[Top Parent Account]]="",Table3[[#This Row],[Account Legal Name]],Table3[[#This Row],[Top Parent Account]]) -> Prefamovil Infraestructura
B6: Josue Olvera | C6: Meeting | D6: PQ Servicios e Infraestructura | F6: 46073 | G6: =IF(Table3[[#This Row],[Top Parent Account]]="",Table3[[#This Row],[Account Legal Name]],Table3[[#This Row],[Top Parent Account]]) -> PQ Servicios e Infraestructura
B7: Ivan Gonzalez | C7: Call | D7: Ladrillera Mecanizada | F7: 46073 | G7: =IF(Table3[[#This Row],[Top Parent Account]]="",Table3[[#This Row],[Account Legal Name]],Table3[[#This Row],[Top Parent Account]]) -> Ladrillera Mecanizada
B8: Josue Olvera | C8: Meeting | D8: Manufacturas Industriales Dp | F8: 46073 | G8: =IF(Table3[[#This Row],[Top Parent Account]]="",Table3[[#This Row],[Account Legal Name]],Table3[[#This Row],[Top Parent Account]]) -> Manufacturas Industriales Dp
B9: Josue Olvera | C9: Meeting | D9: DICOM Fresnillo | F9: 46073 | G9: =IF(Table3[[#This Row],[Top Parent Account]]="",Table3[[#This Row],[Account Legal Name]],Table3[[#This Row],[Top Parent Account]]) -> DICOM Fresnillo
B10: Jose Nava | C10: Meeting | D10: ANOVA AMERICAS INTERNATIONAL COMPANY | F10: 46073 | G10: =IF(Table3[[#This Row],[Top Parent Account]]="",Table3[[#This Row],[Account Legal Name]],Table3[[#This Row],[Top Parent Account]]) -> ANOVA AMERICAS INTERNATIONAL COMPANY
B11: Fernando Martin | C11: Meeting | D11: Evsa | F11: 46073 | G11: =IF(Table3[[#This Row],[Top Parent Account]]="",Table3[[#This Row],[Account Legal Name]],Table3[[#This Row],[Top Parent Account]]) -> Evsa
B12: Moises Villalon | C12: Meeting | D12: Cosmética | F12: 46073 | G12: =IF(Table3[[#This Row],[Top Parent Account]]="",Table3[[#This Row],[Account Legal Name]],Table3[[#This Row],[Top Parent Account]]) -> Cosmética
B13: Josue Olvera | C13: Meeting | D13: Super Farmacias Santa Maria | F13: 46073 | G13: =IF(Table3[[#This Row],[Top Parent Account]]="",Table3[[#This Row],[Account Legal Name]],Table3[[#This Row],[Top Parent Account]]) -> Super Farmacias Santa Maria
B14: Gabriela Lopez | C14: Meeting | D14: IACNA MEXICO II | E14: IACNA MEXICO | F14: 46073 | G14: =IF(Table3[[#This Row],[Top Parent Account]]="",Table3[[#This Row],[Account Legal Name]],Table3[[#This Row],[Top Parent Account]]) -> IACNA MEXICO
B15: Jorge Avendaño | C15: Meeting | D15: Especialistas En Turbopartes División Aeronáutica | E15: Especialistas En Turbopartes | F15: 46073 | G15: =IF(Table3[[#This Row],[Top Parent Account]]="",Table3[[#This Row],[Account Legal Name]],Table3[[#This Row],[Top Parent Account]]) -> Especialistas En Turbopartes
B16: Roberto Anaya | C16: Meeting | D16: Suajes y Empaques | F16: 46073 | G16: =IF(Table3[[#This Row],[Top Parent Account]]="",Table3[[#This Row],[Account Legal Name]],Table3[[#This Row],[Top Parent Account]]) -> Suajes y Empaques
B17: Fernando Carbajal | C17: Meeting | D17: Edificaciones Carver | F17: 46073 | G17: =IF(Table3[[#This Row],[Top Parent Account]]="",Table3[[#This Row],[Account Legal Name]],Table3[[#This Row],[Top Parent Account]]) -> Edificaciones Carver
B18: Armando Estrada | C18: Meeting | D18: Alianza Eléctrica | F18: 46073 | G18: =IF(Table3[[#This Row],[Top Parent Account]]="",Table3[[#This Row],[Account Legal Name]],Table3[[#This Row],[Top Parent Account]]) -> Alianza Eléctrica
B19: Julieta Medrano | C19: Meeting | D19: Oscar Alonso Reynosa Armendariz | F19: 46073 | G19: =IF(Table3[[#This Row],[Top Parent Account]]="",Table3[[#This Row],[Account Legal Name]],Table3[[#This Row],[Top Parent Account]]) -> Oscar Alonso Reynosa Armendariz
B20: Omar Rodríguez | C20: Meeting | D20: Grupo Canels | F20: 46073 | G20: =IF(Table3[[#This Row],[Top Parent Account]]="",Table3[[#This Row],[Account Legal Name]],Table3[[#This Row],[Top Parent Account]]) -> Grupo Canels
B21: Moises Villalon | C21: Meeting | D21: Gluten y Almidones Industriales | F21: 46073 | G21: =IF(Table3[[#This Row],[Top Parent Account]]="",Table3[[#This Row],[Account Legal Name]],Table3[[#This Row],[Top Parent Account]]) -> Gluten y Almidones Industriales
B22: Marco Cohen | C22: Meeting | D22: Siemens | F22: 46073 | G22: =IF(Table3[[#This Row],[Top Parent Account]]="",Table3[[#This Row],[Account Legal Name]],Table3[[#This Row],[Top Parent Account]]) -> Siemens
B23: Jose Nava | C23: Meeting | D23: Planeación de Logística y movilidad | F23: 46073 | G23: =IF(Table3[[#This Row],[Top Parent Account]]="",Table3[[#This Row],[Account Legal Name]],Table3[[#This Row],[Top Parent Account]]) -> Planeación de Logística y movilidad
B24: Jose Nava | C24: Meeting | D24: Refrigerados Maverick | F24: 46073 | G24: =IF(Table3[[#This Row],[Top Parent Account]]="",Table3[[#This Row],[Account Legal Name]],Table3[[#This Row],[Top Parent Account]]) -> Refrigerados Maverick
B25: Jose Nava | C25: Meeting | D25: Alambique de Oro | F25: 46073 | G25: =IF(Table3[[#This Row],[Top Parent Account]]="",Table3[[#This Row],[Account Legal Name]],Table3[[#This Row],[Top Parent Account]]) -> Alambique de Oro
B26: Jose Nava | C26: Meeting | D26: CAJAS Y CORRUGADOS PARA EMPAQUE | F26: 46073 | G26: =IF(Table3[[#This Row],[Top Parent Account]]="",Table3[[#This Row],[Account Legal Name]],Table3[[#This Row],[Top Parent Account]]) -> CAJAS Y CORRUGADOS PARA EMPAQUE
B27: Mauricio Ortiz | C27: Meeting | D27: Enfoque Quimico | F27: 46073 | G27: =IF(Table3[[#This Row],[Top Parent Account]]="",Table3[[#This Row],[Account Legal Name]],Table3[[#This Row],[Top Parent Account]]) -> Enfoque Quimico
... B31: Jose Nava | C31: Meeting | D31: Innovacion Logika En Transporte | F31: 46073 | G31: =IF(Table3[[#This Row],[Top Parent Account]]="",Table3[[#This Row],[Account Legal Name]],Table3[[#This Row],[Top Parent Account]]) -> Innovacion Logika En Transporte
B32: Armando Estrada | C32: Meeting | D32: Enlace Int. | E32: Central De Corretajes | F32: 46073 | G32: =IF(Table3[[#This Row],[Top Parent Account]]="",Table3[[#This Row],[Account Legal Name]],Table3[[#This Row],[Top Parent Account]]) -> Central De Corretajes
B33: Dulce Villegas | C33: Meeting | D33: Fraenkische Industrial Pipes México | F33: 46073 | G33: =IF(Table3[[#This Row],[Top Parent Account]]="",Table3[[#This Row],[Account Legal Name]],Table3[[#This Row],[Top Parent Account]]) -> Fraenkische Industrial Pipes México
B34: Ramón Pérez | C34: Meeting | D34: Metal Tec Industrial | F34: 46072 | G34: =IF(Table3[[#This Row],[Top Parent Account]]="",Table3[[#This Row],[Account Legal Name]],Table3[[#This Row],[Top Parent Account]]) -> Metal Tec Industrial
B35: Myrna Leija | C35: Meeting | D35: Graneros Espinoza | F35: 46072 | G35: =IF(Table3[[#This Row],[Top Parent Account]]="",Table3[[#This Row],[Account Legal Name]],Table3[[#This Row],[Top Parent Account]]) -> Graneros Espinoza
B36: Jorge Avendaño | C36: Meeting | D36: Proffinox | F36: 46072 | G36: =IF(Table3[[#This Row],[Top Parent Account]]="",Table3[[#This Row],[Account Legal Name]],Table3[[#This Row],[Top Parent Account]]) -> Proffinox
B37: Marco Cohen | C37: Meeting | D37: Vitalmex Internacional | E37: Grupo Vitalmex | F37: 46072 | G37: =IF(Table3[[#This Row],[Top Parent Account]]="",Table3[[#This Row],[Account Legal Name]],Table3[[#This Row],[Top Parent Account]]) -> Grupo Vitalmex
B38: Marco Cohen | C38: Meeting | D38: Smurfit Carton y Papel de México | E38: Grupo Smurfit | F38: 46072 | G38: =IF(Table3[[#This Row],[Top Parent Account]]="",Table3[[#This Row],[Account Legal Name]],Table3[[#This Row],[Top Parent Account]]) -> Grupo Smurfit
B39: Kenia Martinez | C39: Video C | D39: Centro Médico De Toluca | F39: 46072 | G39: =IF(Table3[[#This Row],[Top Parent Account]]="",Table3[[#This Row],[Account Legal Name]],Table3[[#This Row],[Top Parent Account]]) -> Centro Médico De Toluca
B40: Monserrat Villanueva | C40: Meeting | D40: Novaplástica | F40: 46072 | G40: =IF(Table3[[#This Row],[Top Parent Account]]="",Table3[[#This Row],[Account Legal Name]],Table3[[#This Row],[Top Parent Account]]) -> Novaplástica
B41: Dulce Villegas | C41: Meeting | D41: Amco Educación | F41: 46072 | G41: =IF(Table3[[#This Row],[Top Parent Account]]="",Table3[[#This Row],[Account Legal Name]],Table3[[#This Row],[Top Parent Account]]) -> Amco Educación
B42: Teresa Cisneros | C42: Meeting | D42: HANGCHA MEXICO | F42: 46072 | G42: =IF(Table3[[#This Row],[Top Parent Account]]="",Table3[[#This Row],[Account Legal Name]],Table3[[#This Row],[Top Parent Account]]) -> HANGCHA MEXICO
B43: Alfonso Ortiz | C43: Other | D43: PULSO GRAFICO | F43: 46072 | G43: =IF(Table3[[#This Row],[Top Parent Account]]="",Table3[[#This Row],[Account Legal Name]],Table3[[#This Row],[Top Parent Account]]) -> PULSO GRAFICO
B44: Juan Villaseñor | C44: Meeting | D44: Soluciones Integrales | F44: 46072 | G44: =IF(Table3[[#This Row],[Top Parent Account]]="",Table3[[#This Row],[Account Legal Name]],Table3[[#This Row],[Top Parent Account]]) -> Soluciones Integrales
B45: Alexandra Ramírez | C45: Meeting | D45: Compañia Transportista de America | F45: 46072 | G45: =IF(Table3[[#This Row],[Top Parent Account]]="",Table3[[#This Row],[Account Legal Name]],Table3[[#This Row],[Top Parent Account]]) -> Compañia Transportista de America
B46: Alexandra Ramírez | C46: Meeting | D46: Coda Logistica Y Transportes | F46: 46072 | G46: =IF(Table3[[#This Row],[Top Parent Account]]="",Table3[[#This Row],[Account Legal Name]],Table3[[#This Row],[Top Parent Account]]) -> Coda Logistica Y Transportes
B47: Julieta Medrano | C47: Meeting | D47: AIR3 de Mexico | F47: 46072 | G47: =IF(Table3[[#This Row],[Top Parent Account]]="",Table3[[#This Row],[Account Legal Name]],Table3[[#This Row],[Top Parent Account]]) -> AIR3 de Mexico
B48: Marianna Peña | C48: Meeting | D48: BOLSAS PLÁSTICAS DE QUERÉTARO S DE RL DE CV | F48: 46072 | G48: =IF(Table3[[#This Row],[Top Parent Account]]="",Table3[[#This Row],[Account Legal Name]],Table3[[#This Row],[Top Parent Account]]) -> BOLSAS PLÁSTICAS DE QUERÉTARO S DE RL DE CV
B49: Alejandro Monteón | C49: Meeting | D49: Hidroponica Sustentable | F49: 46072 | G49: =IF(Table3[[#This Row],[Top Parent Account]]="",Table3[[#This Row],[Account Legal Name]],Table3[[#This Row],[Top Parent Account]]) -> Hidroponica Sustentable
B50: Fernando Martin | C50: Meeting | D50: Phoenix Packaging México | F50: 46072 | G50: =IF(Table3[[#This Row],[Top Parent Account]]="",Table3[[#This Row],[Account Legal Name]],Table3[[#This Row],[Top Parent Account]]) -> Phoenix Packaging México
... B71: Veronica Sesma | C71: Meeting | D71: Grupo Corporativo Papelera | F71: 46072 | G71: =IF(Table3[[#This Row],[Top Parent Account]]="",Table3[[#This Row],[Account Legal Name]],Table3[[#This Row],[Top Parent Account]]) -> Grupo Corporativo Papelera
B72: Dulce Villegas | C72: Meeting | D72: CAPIX LEASING | E72: Sesajal | F72: 46072 | G72: =IF(Table3[[#This Row],[Top Parent Account]]="",Table3[[#This Row],[Account Legal Name]],Table3[[#This Row],[Top Parent Account]]) -> Sesajal
B73: Ramón Pérez | C73: Meeting | D73: Forrajes y Granos Agropecuarios De yucatán | F73: 46072 | G73: =IF(Table3[[#This Row],[Top Parent Account]]="",Table3[[#This Row],[Account Legal Name]],Table3[[#This Row],[Top Parent Account]]) -> Forrajes y Granos Agropecuarios De yucatán
B74: Francisco Porragas | C74: Meeting | D74: Minera Media Luna | F74: 46072 | G74: =IF(Table3[[#This Row],[Top Parent Account]]="",Table3[[#This Row],[Account Legal Name]],Table3[[#This Row],[Top Parent Account]]) -> Minera Media Luna
B75: Kenia Martinez | C75: Reunión presencial | D75: Essencefleur de México | F75: 46072 | G75: =IF(Table3[[#This Row],[Top Parent Account]]="",Table3[[#This Row],[Account Legal Name]],Table3[[#This Row],[Top Parent Account]]) -> Essencefleur de México
B76: Ramón Pérez | C76: Meeting | D76: Operadora Exe | F76: 46071 | G76: =IF(Table3[[#This Row],[Top Parent Account]]="",Table3[[#This Row],[Account Legal Name]],Table3[[#This Row],[Top Parent Account]]) -> Operadora Exe
B77: Ramón Pérez | C77: Meeting | D77: Inco Peninsular | F77: 46071 | G77: =IF(Table3[[#This Row],[Top Parent Account]]="",Table3[[#This Row],[Account Legal Name]],Table3[[#This Row],[Top Parent Account]]) -> Inco Peninsular
B78: Ramón Pérez | C78: Meeting | D78: Celulares y Accesorios del Sureste S.A. | F78: 46071 | G78: =IF(Table3[[#This Row],[Top Parent Account]]="",Table3[[#This Row],[Account Legal Name]],Table3[[#This Row],[Top Parent Account]]) -> Celulares y Accesorios del Sureste S.A.
B79: Alfonso Ortiz | C79: Meeting | D79: Reciclados Plásticos Alvarado | F79: 46071 | G79: =IF(Table3[[#This Row],[Top Parent Account]]="",Table3[[#This Row],[Account Legal Name]],Table3[[#This Row],[Top Parent Account]]) -> Reciclados Plásticos Alvarado
B80: Samuel Cepeda | C80: Meeting | D80: Empacadora Dilusa De Aguascalientes | F80: 46071 | G80: =IF(Table3[[#This Row],[Top Parent Account]]="",Table3[[#This Row],[Account Legal Name]],Table3[[#This Row],[Top Parent Account]]) -> Empacadora Dilusa De Aguascalientes
B81: Marianna Peña | C81: Meeting | D81: Tecnostamp Triulzi México | F81: 46071 | G81: =IF(Table3[[#This Row],[Top Parent Account]]="",Table3[[#This Row],[Account Legal Name]],Table3[[#This Row],[Top Parent Account]]) -> Tecnostamp Triulzi México
B82: Jorge Avendaño | C82: Meeting | D82: Manufacturas y Aleaciones de Cobre | F82: 46071 | G82: =IF(Table3[[#This Row],[Top Parent Account]]="",Table3[[#This Row],[Account Legal Name]],Table3[[#This Row],[Top Parent Account]]) -> Manufacturas y Aleaciones de Cobre
B83: Alexandra Luna | C83: Meeting | D83: Rancho Caloca | F83: 46071 | G83: =IF(Table3[[#This Row],[Top Parent Account]]="",Table3[[#This Row],[Account Legal Name]],Table3[[#This Row],[Top Parent Account]]) -> Rancho Caloca
B84: Moises Villalon | C84: Meeting | D84: REFACCIONES MERETI | F84: 46071 | G84: =IF(Table3[[#This Row],[Top Parent Account]]="",Table3[[#This Row],[Account Legal Name]],Table3[[#This Row],[Top Parent Account]]) -> REFACCIONES MERETI
... B87: Rafael Garcia | C87: Meeting | D87: Kensa Logistics México | F87: 46071 | G87: =IF(Table3[[#This Row],[Top Parent Account]]="",Table3[[#This Row],[Account Legal Name]],Table3[[#This Row],[Top Parent Account]]) -> Kensa Logistics México
B88: Alexandra Luna | C88: Meeting | D88: Maquinaria y Elevacion de Juarez | E88: Maquinaria de Elevacion | F88: 46071 | G88: =IF(Table3[[#This Row],[Top Parent Account]]="",Table3[[#This Row],[Account Legal Name]],Table3[[#This Row],[Top Parent Account]]) -> Maquinaria de Elevacion
B89: Myrna Leija | C89: Meeting | D89: CFMOTO MEXICO | F89: 46071 | G89: =IF(Table3[[#This Row],[Top Parent Account]]="",Table3[[#This Row],[Account Legal Name]],Table3[[#This Row],[Top Parent Account]]) -> CFMOTO MEXICO
B90: Miguel Antunez | C90: Presentacion Engen Capital | D90: Zobele México | F90: 46071 | G90: =IF(Table3[[#This Row],[Top Parent Account]]="",Table3[[#This Row],[Account Legal Name]],Table3[[#This Row],[Top Parent Account]]) -> Zobele México
B91: Christian Gamboa | C91: Meeting | D91: TRINITA GRUPO HOSPITALARIO | F91: 46071 | G91: =IF(Table3[[#This Row],[Top Parent Account]]="",Table3[[#This Row],[Account Legal Name]],Table3[[#This Row],[Top Parent Account]]) -> TRINITA GRUPO HOSPITALARIO
B92: Alfonso Ortiz | C92: Call | D92: Metales y Equipos Mecanicos Regios | F92: 46071 | G92: =IF(Table3[[#This Row],[Top Parent Account]]="",Table3[[#This Row],[Account Legal Name]],Table3[[#This Row],[Top Parent Account]]) -> Metales y Equipos Mecanicos Regios
B93: Alfonso Ortiz | C93: Other | D93: Plastirey | F93: 46071 | G93: =IF(Table3[[#This Row],[Top Parent Account]]="",Table3[[#This Row],[Account Legal Name]],Table3[[#This Row],[Top Parent Account]]) -> Plastirey
B94: Manuel Ibal | C94: Meeting | D94: Auto Express Toscano | F94: 46071 | G94: =IF(Table3[[#This Row],[Top Parent Account]]="",Table3[[#This Row],[Account Legal Name]],Table3[[#This Row],[Top Parent Account]]) -> Auto Express Toscano
B95: Samuel Cepeda | C95: Meeting | D95: Agroindustrias Quesada | F95: 46071 | G95: =IF(Table3[[#This Row],[Top Parent Account]]="",Table3[[#This Row],[Account Legal Name]],Table3[[#This Row],[Top Parent Account]]) -> Agroindustrias Quesada
B96: Jorge Avendaño | C96: Meeting | D96: DC CONCRETOS | F96: 46071 | G96: =IF(Table3[[#This Row],[Top Parent Account]]="",Table3[[#This Row],[Account Legal Name]],Table3[[#This Row],[Top Parent Account]]) -> DC CONCRETOS
B97: Alejandro Monteón | C97: Meeting | D97: Compresores Maqpower | F97: 46071 | G97: =IF(Table3[[#This Row],[Top Parent Account]]="",Table3[[#This Row],[Account Legal Name]],Table3[[#This Row],[Top Parent Account]]) -> Compresores Maqpower
B98: Cynthia Diaz | C98: Call | D98: Lucta Mexicana | F98: 46071 | G98: =IF(Table3[[#This Row],[Top Parent Account]]="",Table3[[#This Row],[Account Legal Name]],Table3[[#This Row],[Top Parent Account]]) -> Lucta Mexicana
B99: Alexandra Ramírez | C99: Meeting | D99: Maquinaria Magnum | F99: 46071 | G99: =IF(Table3[[#This Row],[Top Parent Account]]="",Table3[[#This Row],[Account Legal Name]],Table3[[#This Row],[Top Parent Account]]) -> Maquinaria Magnum
B100: Cynthia Diaz | C100: Meeting | D100: FGR Ingeniería y Montajes del Centro | F100: 46071 | G100: =IF(Table3[[#This Row],[Top Parent Account]]="",Table3[[#This Row],[Account Legal Name]],Table3[[#This Row],[Top Parent Account]]) -> FGR Ingeniería y Montajes del Centro
... B103: Manuel Ibal | C103: Meeting | D103: Tracto Express Sánchez | F103: 46071 | G103: =IF(Table3[[#This Row],[Top Parent Account]]="",Table3[[#This Row],[Account Legal Name]],Table3[[#This Row],[Top Parent Account]]) -> Tracto Express Sánchez
B104: Francisco Porragas | C104: Call | D104: Centro De Ingenieria Avanzada En Turbomaquinas | E104: General Electric México | F104: 46071 | G104: =IF(Table3[[#This Row],[Top Parent Account]]="",Table3[[#This Row],[Account Legal Name]],Table3[[#This Row],[Top Parent Account]]) -> General Electric México
B105: Christian Gamboa | C105: Meeting | D105: Distribuidora Alcatraz | E105: Industrias Cuamex | F105: 46071 | G105: =IF(Table3[[#This Row],[Top Parent Account]]="",Table3[[#This Row],[Account Legal Name]],Table3[[#This Row],[Top Parent Account]]) -> Industrias Cuamex
B106: Mauricio Ortiz | C106: Meeting | D106: Somaki de México | F106: 46071 | G106: =IF(Table3[[#This Row],[Top Parent Account]]="",Table3[[#This Row],[Account Legal Name]],Table3[[#This Row],[Top Parent Account]]) -> Somaki de México
B107: Alejandro Monteón | C107: Meeting | D107: SH Lunch | F107: 46071 | G107: =IF(Table3[[#This Row],[Top Parent Account]]="",Table3[[#This Row],[Account Legal Name]],Table3[[#This Row],[Top Parent Account]]) -> SH Lunch
B108: Jorge Avendaño | C108: Meeting | D108: Metrocolor de Mexico | F108: 46071 | G108: =IF(Table3[[#This Row],[Top Parent Account]]="",Table3[[#This Row],[Account Legal Name]],Table3[[#This Row],[Top Parent Account]]) -> Metrocolor de Mexico
B109: Sergio Mange | C109: Meeting | D109: impulsora de bienes alameda | F109: 46071 | G109: =IF(Table3[[#This Row],[Top Parent Account]]="",Table3[[#This Row],[Account Legal Name]],Table3[[#This Row],[Top Parent Account]]) -> impulsora de bienes alameda
B110: Christian Gamboa | C110: Meeting | D110: Megaluminio Servicios | F110: 46071 | G110: =IF(Table3[[#This Row],[Top Parent Account]]="",Table3[[#This Row],[Account Legal Name]],Table3[[#This Row],[Top Parent Account]]) -> Megaluminio Servicios
B111: Alfonso Ortiz | C111: Other | D111: Arrendadora Datamovil | F111: 46071 | G111: =IF(Table3[[#This Row],[Top Parent Account]]="",Table3[[#This Row],[Account Legal Name]],Table3[[#This Row],[Top Parent Account]]) -> Arrendadora Datamovil
B112: Josue Olvera | C112: Meeting | D112: AZUD | F112: 46071 | G112: =IF(Table3[[#This Row],[Top Parent Account]]="",Table3[[#This Row],[Account Legal Name]],Table3[[#This Row],[Top Parent Account]]) -> AZUD
B113: Roberto Anaya | C113: Meeting | D113: EECOE | F113: 46071 | G113: =IF(Table3[[#This Row],[Top Parent Account]]="",Table3[[#This Row],[Account Legal Name]],Table3[[#This Row],[Top Parent Account]]) -> EECOE
B114: Vadir Peña | C114: Meeting | D114: Transportes Treviño | F114: 46071 | G114: =IF(Table3[[#This Row],[Top Parent Account]]="",Table3[[#This Row],[Account Legal Name]],Table3[[#This Row],[Top Parent Account]]) -> Transportes Treviño
B115: Fernanda Rangel | C115: Meeting | D115: Tamales Salinas | F115: 46071 | G115: =IF(Table3[[#This Row],[Top Parent Account]]="",Table3[[#This Row],[Account Legal Name]],Table3[[#This Row],[Top Parent Account]]) -> Tamales Salinas
B116: Marco Cohen | C116: Meeting | D116: GRUPO INTEGRAL DE MEDICINA PRIMARIA | F116: 46071 | G116: =IF(Table3[[#This Row],[Top Parent Account]]="",Table3[[#This Row],[Account Legal Name]],Table3[[#This Row],[Top Parent Account]]) -> GRUPO INTEGRAL DE MEDICINA PRIMARIA
B117: Cynthia Diaz | C117: Call | D117: Grupo Lamesa | F117: 46071 | G117: =IF(Table3[[#This Row],[Top Parent Account]]="",Table3[[#This Row],[Account Legal Name]],Table3[[#This Row],[Top Parent Account]]) -> Grupo Lamesa
... B126: Samuel Cepeda | C126: Meeting | D126: Mundienvases de Plastico | F126: 46071 | G126: =IF(Table3[[#This Row],[Top Parent Account]]="",Table3[[#This Row],[Account Legal Name]],Table3[[#This Row],[Top Parent Account]]) -> Mundienvases de Plastico
B127: Cynthia Diaz | C127: Call | D127: Bruluagsa | E127: Grupo Bruluart | F127: 46070 | G127: =IF(Table3[[#This Row],[Top Parent Account]]="",Table3[[#This Row],[Account Legal Name]],Table3[[#This Row],[Top Parent Account]]) -> Grupo Bruluart
B128: Ramón Pérez | C128: Meeting | D128: EMPACADORA GRUMA DEL SURESTE | F128: 46070 | G128: =IF(Table3[[#This Row],[Top Parent Account]]="",Table3[[#This Row],[Account Legal Name]],Table3[[#This Row],[Top Parent Account]]) -> EMPACADORA GRUMA DEL SURESTE
B129: Ramón Pérez | C129: Meeting | D129: Distribuidora Mayorista de Tornillos de Yucatán | F129: 46070 | G129: =IF(Table3[[#This Row],[Top Parent Account]]="",Table3[[#This Row],[Account Legal Name]],Table3[[#This Row],[Top Parent Account]]) -> Distribuidora Mayorista de Tornillos de Yucatán
B130: Roberto Anaya | C130: Meeting | D130: MAQUINARIA BOIX MEXICO | F130: 46070 | G130: =IF(Table3[[#This Row],[Top Parent Account]]="",Table3[[#This Row],[Account Legal Name]],Table3[[#This Row],[Top Parent Account]]) -> MAQUINARIA BOIX MEXICO
B131: Dulce Villegas | C131: Meeting | D131: Laboratorios Pisa | F131: 46070 | G131: =IF(Table3[[#This Row],[Top Parent Account]]="",Table3[[#This Row],[Account Legal Name]],Table3[[#This Row],[Top Parent Account]]) -> Laboratorios Pisa
B132: Jorge Avendaño | C132: Other | D132: Transportes Martillo | F132: 46070 | G132: =IF(Table3[[#This Row],[Top Parent Account]]="",Table3[[#This Row],[Account Legal Name]],Table3[[#This Row],[Top Parent Account]]) -> Transportes Martillo
B133: David Shaw | C133: Meeting | D133: Neta Systems | F133: 46070 | G133: =IF(Table3[[#This Row],[Top Parent Account]]="",Table3[[#This Row],[Account Legal Name]],Table3[[#This Row],[Top Parent Account]]) -> Neta Systems
B134: Brenda Vargas | C134: Meeting | D134: Copamex | F134: 46070 | G134: =IF(Table3[[#This Row],[Top Parent Account]]="",Table3[[#This Row],[Account Legal Name]],Table3[[#This Row],[Top Parent Account]]) -> Copamex
B135: Cynthia Diaz | C135: Call | D135: Condimentos Naturales Tres Villas | F135: 46070 | G135: =IF(Table3[[#This Row],[Top Parent Account]]="",Table3[[#This Row],[Account Legal Name]],Table3[[#This Row],[Top Parent Account]]) -> Condimentos Naturales Tres Villas
...

Sheet Opps creadas
A1: Opportunity Currency | B1: EXT_REF_ID | C1: Region | D1: Target Market | E1: Account Legal Name | F1: Inside Sales Owner | G1: Opportunity Owner | H1: Opportunity Name | I1: Amount (converted).amount | J1: Amount (converted).currency | K1: Required Book Yield to Win | L1: Reason Lost - Level 1 | M1: Reason Lost - Level 3 | N1: Competitor | O1: Competitor Product | P1: Competitor Rate Type | Q1: Competitor Term (Months) | R1: Amount Converted MXN | S1: Lost Comments | T1: Line of Business | U1: Stage | V1: Collateral | W1: Insurance Type | X1: Deal Category | Y1: Financing Need | Z1: Product | AA1: Lost Date Q | AB1: Opportunity Identified Date | AC1: Target Market2 | AD1: Indirect Opportunity? | AE1: Opportunity from Broker? | AF1: Billing State/Province | AG1: SIC Industry
A2: MXN | B2: SFOP0006027252 | C2: Factoring | D2: Lower middle market | E2: Reivax Internacional | F2: Julio Castillo | G2: Antonio Soto | H2: Factoraje Reivax | I2: 10000000 | J2: MXN | L2: - | M2: - | N2: - | O2: - | P2: - | R2: 10000000 | S2: - | T2: Factoring | U2: Opportunity Identified | V2: - | W2: - | X2: New Customer | Y2: Cash Substitution | Z2: Recourse | AB2: 46078 | AC2: Lower middle market | AD2: No | AE2: No | AF2: Jalisco | AG2: Healthcare
A3: MXN | B3: SFOP0006027449 | C3: Guadalajara 1 | D3: Lower middle market | E3: Cervecería de Colima | F3: Alan Alatorre | G3: Dulce Villegas | H3: S&LB Capital de trabajo | Línea Envasado y Embotellado | I3: 15000000 | J3: MXN | L3: - | M3: - | N3: - | O3: - | P3: - | R3: 15000000 | S3: - | T3: Equipment | U3: Opportunity Identified | V3: Other | W3: - | X3: New Origination | Y3: Sale & Leaseback | Z3: True Lease | AB3: 46080 | AC3: Lower middle market | AD3: No | AE3: No | AF3: Colima | AG3: Food Bev & Ag
A4: MXN | B4: SFOP0006027457 | C4: Guadalajara 1 | D4: Middle market | E4: Anteus Constructora | F4: Alan Alatorre | G4: Dulce Villegas | H4: S&LB | Equipo Amarillo - Capital de trabajo 2026 | I4: 20000000 | J4: MXN | L4: - | M4: - | N4: - | O4: - | P4: - | R4: 20000000 | S4: - | T4: Equipment | U4: Opportunity Identified | V4: Construction Equipment | W4: - | X4: New Origination | Y4: Sale & Leaseback | Z4: True Lease | AB4: 46081 | AC4: Middle market | AD4: No | AE4: No | AF4: Jalisco | AG4: Construction
A5: MXN | B5: SFOP0006027442 | C5: Guadalajara 1 | D5: Lower middle market | E5: MADOBOX | F5: Alan Alatorre | G5: Fernando Carbajal | H5: Flexo Madobox | I5: 20000000 | J5: MXN | L5: - | M5: - | N5: - | O5: - | P5: - | R5: 20000000 | S5: - | T5: Equipment | U5: Opportunity Identified | V5: Manufacturing Equipment | W5: Engen Capital Financed | X5: New Origination | Y5: CapEx Lines | Z5: True Lease | AB5: 46080 | AC5: Lower middle market | AD5: No | AE5: No | AF5: Michoacán | AG5: Forest Products
A6: USD | B6: SFOP0006027418 | C6: Guadalajara 1 | D6: Lower middle market | E6: Empaques y diseños de polietileno | F6: Omar Rodríguez | G6: Omar Rodríguez | H6: Capex EDP 2026 | I6: 8626600 | J6: MXN | L6: - | M6: - | N6: - | O6: - | P6: - | R6: 8626600 | S6: - | T6: Equipment | U6: Opportunity Identified | V6: Manufacturing Equipment | W6: Engen Capital Financed | X6: New Origination | Y6: CapEx Lines | Z6: Quasi Lease | AB6: 46079 | AC6: Lower middle market | AD6: No | AE6: No | AF6: Jalisco | AG6: Forest Products
A7: MXN | B7: SFOP0006027348 | C7: LMM 1 | D7: Lower middle market | E7: SH Lunch | F7: Miranda Cabral | G7: Alejandro Monteón | H7: OFS Flota vehicular | I7: 4000000 | J7: MXN | L7: - | M7: - | N7: No competitor | O7: - | P7: - | R7: 4000000 | S7: - | T7: Fleet | U7: Opportunity Identified | V7: Cars + Insurance | W7: Engen Capital Financed | X7: New Origination | Y7: CapEx Lines | Z7: True Lease | AB7: 46080 | AC7: Lower middle market | AD7: No | AE7: No | AF7: Zacatecas | AG7: Franchise
A8: MXN | B8: SFOP0006027388 | C8: LMM 1 | D8: Lower middle market | E8: SH Lunch | F8: Miranda Cabral | G8: Alejandro Monteón | H8: Factoraje CH Lunch | I8: 10000000 | J8: MXN | L8: - | M8: - | N8: - | O8: - | P8: - | R8: 10000000 | S8: - | T8: Factoring | U8: Opportunity Identified | V8: - | W8: - | X8: New Product | Y8: - | Z8: Recourse | AB8: 46078 | AC8: Lower middle market | AD8: No | AE8: No | AF8: Zacatecas | AG8: Franchise
A9: MXN | B9: SFOP0006027433 | C9: LMM 1 | D9: Lower middle market | E9: Mova Printing Solutions | F9: Miranda Cabral | G9: Alejandro Monteón | H9: Sistema de impresión digital | I9: 12154275 | J9: MXN | L9: - | M9: - | N9: No competitor | O9: - | P9: - | R9: 12154275 | S9: - | T9: Equipment | U9: Opportunity Identified | V9: Printing Equipment | W9: Engen Capital Financed | X9: Progress Payment | Y9: CapEx Lines | Z9: True Lease | AB9: 46079 | AC9: Lower middle market | AD9: No | AE9: No | AF9: Jalisco | AG9: Forest Products
A10: MXN | B10: SFOP0006027411 | C10: LMM 1 | D10: Lower middle market | E10: Energio Servicios de Energía Sostenible | F10: Juan Villaseñor | G10: Juan Villaseñor | H10: Fleet 4 vehiculos | I10: 3000000 | J10: MXN | L10: - | M10: - | N10: - | O10: - | P10: - | R10: 3000000 | S10: - | T10: Fleet | U10: Opportunity Identified | V10: Cars Full Service | W10: - | X10: New Origination | Y10: CapEx Lines | Z10: True Lease | AB10: 46080 | AC10: Lower middle market | AD10: No | AE10: No | AF10: Sinaloa | AG10: Misc Service Industries
A11: MXN | B11: SFOP0006027429 | C11: LMM 1 | D11: Small Business | E11: RANCHO LA MEMORIA | F11: Juan Villaseñor | G11: Juan Villaseñor | H11: Urvan 3 | I11: 4000000 | J11: MXN | L11: - | M11: - | N11: - | O11: - | P11: - | R11: 4000000 | S11: - | T11: Fleet | U11: Opportunity Identified | V11: Cars | W11: - | X11: - | Y11: - | Z11: - | AB11: 46080 | AC11: Small Business | AD11: No | AE11: No | AF11: Sinaloa | AG11: Food Bev & Ag
A12: MXN | B12: SFOP0006027410 | C12: LMM 1 | D12: Lower middle market | E12: Nutriesence | F12: Juan Villaseñor | G12: Juan Villaseñor | H12: Factoraje Nutriesence | I12: 18000000 | J12: MXN | L12: - | M12: - | N12: Expocredit | O12: - | P12: - | R12: 18000000 | S12: - | T12: Factoring | U12: Opportunity Identified | V12: - | W12: - | X12: - | Y12: - | Z12: - | AB12: 46079 | AC12: Lower middle market | AD12: No | AE12: No | AF12: Jalisco | AG12: Food Bev & Ag
A13: MXN | B13: SFOP0006027403 | C13: LMM 1 | D13: Lower middle market | E13: EECOE | F13: Miranda Cabral | G13: Roberto Anaya | H13: Montacargas y planta eléctrica | I13: 1021370 | J13: MXN | L13: - | M13: - | N13: No competitor | O13: - | P13: - | R13: 1021370 | S13: - | T13: Equipment | U13: Opportunity Identified | V13: Multiple | W13: - | X13: - | Y13: CapEx Lines | Z13: True Lease | AB13: 46079 | AC13: Lower middle market | AD13: No | AE13: No | AF13: Jalisco | AG13: Construction
... A24: MXN | B24: SFOP0006027450 | C24: LMM 5 | D24: Lower middle market | E24: Softelligence | F24: César Flores | G24: Jorge Avendaño | H24: Lease Back equipos de geolocalizacion | I24: 4000000 | J24: MXN | L24: - | M24: - | N24: - | O24: - | P24: - | R24: 4000000 | S24: - | T24: Technology | U24: Opportunity Identified | V24: Security and Surveillance Equipment | W24: Engen Capital Financed | X24: New Origination | Y24: Sale & Leaseback | Z24: True Lease | AB24: 46080 | AC24: Lower middle market | AD24: No | AE24: No | AF24: Querétaro | AG24: Telecom
A25: MXN | B25: SFOP0006027400 | C25: LMM 5 | D25: Small Business | E25: PRODUCTORA HUEVO SAN LUIS | F25: César Flores | G25: Julieta Medrano | H25: S&LB sistema de jaulas para huevo | I25: 1032183.7 | J25: MXN | L25: - | M25: - | N25: Banco del Bajio | O25: - | P25: - | Q25: 36 | R25: 1032183.7 | S25: - | T25: Equipment | U25: Opportunity Identified | V25: Agricultural Equipment | W25: Engen Capital Financed | X25: New Origination | Y25: CapEx Lines | Z25: True Lease | AB25: 46080 | AC25: Small Business | AD25: No | AE25: No | AF25: San Luis Potosí | AG25: Food Bev & Ag
A26: MXN | B26: SFOP0006027397 | C26: LMM 5 | D26: Small Business | E26: SERVICIOS INTEGRALES E INDUSTRIALES EN ACERO ESTRUCTURAL | F26: César Flores | G26: Julieta Medrano | H26: Freightliner M2 35K | I26: 2142241.4 | J26: MXN | L26: - | M26: - | N26: - | O26: - | P26: - | R26: 2142241.4 | S26: - | T26: Equipment | U26: Proposal | V26: Transportation | W26: Engen Capital Financed | X26: New Origination | Y26: CapEx Lines | Z26: True Lease | AB26: 46078 | AC26: Small Business | AD26: No | AE26: Yes | AF26: Colima | AG26: Metals, Mining & Metals Fabrication
A27: MXN | B27: SFOP0006027435 | C27: LMM 5 | D27: Lower middle market | E27: ELASTOMEROS TAZA | F27: César Flores | G27: Mauricio Ortiz | H27: Refinanciamiento 2026 Consolidación de Pasivos | I27: 20000000 | J27: MXN | L27: - | M27: - | N27: N/A | O27: - | P27: - | R27: 20000000 | S27: - | T27: Real Estate | U27: Opportunity Identified | V27: Bundled (Real estate + M&E) | W27: Engen Capital Financed | X27: New Origination | Y27: External Refinancing | Z27: Term Loan | AB27: 46080 | AC27: Lower middle market | AD27: No | AE27: No | AF27: Estado de México | AG27: Chemicals & Plastics
A28: MXN | B28: SFOP0006027387 | C28: LMM 5 | D28: Lower middle market | E28: FLORES IXTAPAN | F28: César Flores | G28: Monserrat Villanueva | H28: Flotilla - Flores Ixtapan | I28: 4000000 | J28: MXN | L28: - | M28: - | N28: - | O28: - | P28: - | R28: 4000000 | S28: - | T28: Fleet | U28: Opportunity Identified | V28: Cars | W28: - | X28: - | Y28: CapEx Lines | Z28: True Lease | AB28: 46076 | AC28: Lower middle market | AD28: No | AE28: No | AF28: Estado de México | AG28: Food Bev & Ag
A29: MXN | B29: SFOP0006027443 | C29: LMM 5 | D29: Lower middle market | E29: Impocarnes | F29: Monserrat Villanueva | G29: Monserrat Villanueva | H29: EQUIPAMIENTO PLANTA ECATEPEC | I29: 20000000 | J29: MXN | L29: - | M29: - | N29: - | O29: - | P29: - | R29: 20000000 | S29: - | T29: Equipment | U29: Opportunity Identified | V29: Food Processing Equipment | W29: - | X29: - | Y29: - | Z29: True Lease | AB29: 46080 | AC29: Lower middle market | AD29: No | AE29: No | AF29: Ciudad de México | AG29: Food Bev & Ag
A30: MXN | B30: SFOP0006027432 | C30: LMM 5 | D30: Lower middle market | E30: Oswaldo Ancona Ricalde | F30: César Flores | G30: Ramón Pérez | H30: Fleet | I30: 4000000 | J30: MXN | L30: - | M30: - | N30: - | O30: - | P30: - | R30: 4000000 | S30: - | T30: Fleet | U30: Opportunity Identified | V30: Cars + Insurance | W30: Engen Capital Financed | X30: New Origination | Y30: CapEx Lines | Z30: True Lease | AB30: 46080 | AC30: Lower middle market | AD30: No | AE30: No | AF30: Yucatán | AG30: Consumer Products
A31: MXN | B31: SFOP0006027243 | C31: LMM 5 | D31: Middle market | E31: Celulares y Accesorios del Sureste S.A. | F31: César Flores | G31: Ramón Pérez | H31: Factoraje proveedores | I31: 35000000 | J31: MXN | L31: - | M31: - | N31: Xepelin | O31: - | P31: - | R31: 35000000 | S31: - | T31: Factoring | U31: Opportunity Identified | V31: - | W31: - | X31: New Product | Y31: Competitor Substitution | Z31: Reverse | AB31: 46076 | AC31: Middle market | AD31: No | AE31: No | AF31: Yucatán | AG31: Retail
A32: MXN | B32: SFOP0006027374 | C32: Mexico 2 | D32: Lower middle market | E32: Comercializadora Naremo | F32: Veronica Castañeda | G32: Rafael Garcia | H32: Caldera F&B | I32: 10000000 | J32: MXN | L32: - | M32: - | N32: - | O32: - | P32: - | R32: 10000000 | S32: - | T32: Equipment | U32: Opportunity Identified | V32: Food Processing Equipment | W32: - | X32: New Origination | Y32: CapEx Lines | Z32: True Lease | AB32: 46080 | AC32: Lower middle market | AD32: No | AE32: No | AF32: Puebla | AG32: Food Bev & Ag
A33: MXN | B33: SFOP0006027354 | C33: Mexico 2 | D33: Lower middle market | E33: GRUPO INTEGRAL DE MEDICINA PRIMARIA | F33: Karen Torres | G33: Marco Cohen | H33: Spine package | I33: 12000000 | J33: MXN | L33: - | M33: - | N33: no competition (cash) | O33: - | P33: - | R33: 12000000 | S33: - | T33: Equipment | U33: Opportunity Identified | V33: Healthcare | W33: Engen Capital Financed | X33: New Origination | Y33: CapEx Lines | Z33: True Lease | AB33: 46080 | AC33: Lower middle market | AD33: No | AE33: No | AF33: Chihuahua | AG33: Healthcare
A34: MXN | B34: SFOP0006027353 | C34: Mexico 2 | D34: Lower middle market | E34: Operadora Juventud | F34: Karen Torres | G34: Marco Cohen | H34: Tivatto 700 premium | I34: 14000000 | J34: MXN | L34: - | M34: - | N34: BanRegio | O34: - | P34: - | R34: 14000000 | S34: - | T34: Equipment | U34: Opportunity Identified | V34: Healthcare | W34: Engen Capital Financed | X34: New Origination | Y34: CapEx Lines | Z34: True Lease | AB34: 46080 | AC34: Lower middle market | AD34: No | AE34: No | AF34: Chihuahua | AG34: Healthcare
A35: MXN | B35: SFOP0006027459 | C35: Mexico 2 | D35: Lower middle market | E35: Agropecuaria Bretona | F35: Ivan Gonzalez | G35: Ivan Gonzalez | H35: Paneles Solares 2026 | I35: 15000000 | J35: MXN | L35: - | M35: - | N35: - | O35: - | P35: - | R35: 15000000 | S35: - | T35: Energy | U35: Opportunity Identified | V35: Paneles Solares mayor a 500kw | W35: - | X35: New Origination | Y35: CapEx Lines | Z35: True Lease | AB35: 46080 | AC35: Lower middle market | AD35: No | AE35: No | AF35: Sonora | AG35: Food Bev & Ag
A36: MXN | B36: SFOP0006027440 | C36: Mexico 2 | D36: Middle market | E36: Intermet | F36: Karen Torres | G36: Marco Cohen | H36: S&LB contratos terminados | I36: 17000000 | J36: MXN | L36: - | M36: - | N36: No competitor | O36: - | P36: - | R36: 17000000 | S36: - | T36: Equipment | U36: Opportunity Identified | V36: Healthcare | W36: Engen Capital Financed | X36: New Origination | Y36: Sale & Leaseback | Z36: True Lease | AB36: 46080 | AC36: Middle market | AD36: No | AE36: No | AF36: Ciudad de México | AG36: Healthcare
A37: MXN | B37: SFOP0006027444 | C37: Mexico 2 | D37: Lower middle market | E37: Ticoy Foods | F37: Alan Alatorre | G37: Samuel Cepeda | H37: Capex 2026 | I37: 20000000 | J37: MXN | L37: - | M37: - | N37: - | O37: - | P37: - | R37: 20000000 | S37: - | T37: Equipment | U37: Opportunity Identified | V37: Food Processing Equipment | W37: - | X37: - | Y37: - | Z37: True Lease | AB37: 46080 | AC37: Lower middle market | AD37: No | AE37: No | AF37: Aguascalientes | AG37: Food Bev & Ag
... A45: MXN | B45: SFOP0006027117 | C45: Monterrey 1 | D45: Lower middle market | E45: Inyector | F45: Alfonso Ortiz | G45: Alfonso Ortiz | H45: MOLDES | I45: 20000000 | J45: MXN | L45: - | M45: - | N45: - | O45: - | P45: - | R45: 20000000 | S45: - | T45: Equipment | U45: Proposal | V45: Manufacturing Equipment | W45: - | X45: New Origination | Y45: CapEx Lines | Z45: True Lease | AB45: 46076 | AC45: Lower middle market | AD45: No | AE45: No | AF45: Nuevo León | AG45: Chemicals & Plastics
A46: MXN | B46: SFOP0006027288 | C46: Monterrey 1 | D46: Middle market | E46: Industrias Metálicas de Monclova | F46: Brenda Vargas | G46: Brenda Vargas | H46: Construcción Nave Mdo Libre | I46: 30000000 | J46: MXN | L46: - | M46: - | N46: Afirme | O46: Term Loan | P46: - | Q46: 84 | R46: 30000000 | S46: - | T46: Equipment | U46: Opportunity Identified | V46: Machine Tools (Metal) | W46: Engen Capital Financed | X46: New Origination | Y46: - | Z46: True Lease | AB46: 46080 | AC46: Middle market | AD46: No | AE46: No | AF46: Coahuila | AG46: Metals, Mining & Metals Fabrication
A47: MXN | B47: SFOP0006027462 | C47: Monterrey 1 | D47: Middle market | E47: AQUA SALUS | F47: Edgar Rodriguez | G47: Edgar Rodriguez | H47: Flotilla Empresa | I47: 50000000 | J47: MXN | L47: - | M47: - | N47: - | O47: - | P47: - | R47: 50000000 | S47: - | T47: Fleet | U47: Opportunity Identified | V47: Cars + Insurance | W47: - | X47: - | Y47: CapEx Lines | Z47: True Lease | AB47: 46081 | AC47: Middle market | AD47: No | AE47: No | AF47: Chihuahua | AG47: Industrial Products & Services
A48: MXN | B48: SFOP0006027406 | C48: Monterrey 1 | D48: Middle market | E48: Red Ambiental | F48: Gabriela Lopez | G48: Gabriela Lopez | H48: CAPEX 2026 Red Ambiental | I48: 100000000 | J48: MXN | L48: - | M48: - | N48: - | O48: - | P48: - | R48: 100000000 | S48: - | T48: Equipment | U48: Opportunity Identified | V48: Transportation | W48: - | X48: - | Y48: CapEx Lines | Z48: Quasi Lease | AB48: 46077 | AC48: Middle market | AD48: No | AE48: No | AF48: Nuevo León | AG48: Industrial Products & Services
A49: USD | B49: SFOP0006027441 | C49: Monterrey 1 | D49: Lower middle market | E49: Grupo Minero Golden Rock de Mexico | F49: Ana Acosta | G49: Sergio Mange | H49: Linea de trituración | I49: 22429160 | J49: MXN | L49: - | M49: - | N49: - | O49: - | P49: - | R49: 22429160 | S49: - | T49: Equipment | U49: Opportunity Identified | V49: Mining Equipment | W49: - | X49: New Origination | Y49: CapEx Lines | Z49: True Lease | AB49: 46080 | AC49: Lower middle market | AD49: No | AE49: No | AF49: Michoacán | AG49: Construction
A50: USD | B50: SFOP0006027439 | C50: Monterrey 1 | D50: Lower middle market | E50: Servicios y Anclajes del Norte | F50: Ana Acosta | G50: Sergio Mange | H50: Equipo para tuneles 2026 | I50: 34506400 | J50: MXN | L50: - | M50: - | N50: - | O50: - | P50: - | R50: 34506400 | S50: - | T50: Equipment | U50: Opportunity Identified | V50: Construction Equipment | W50: - | X50: New Origination | Y50: CapEx Lines | Z50: True Lease | AB50: 46080 | AC50: Lower middle market | AD50: No | AE50: No | AF50: Chihuahua | AG50: Metals, Mining & Metals Fabrication
A51: MXN | B51: SFOP0006027430 | C51: Sureste | D51: Middle market | E51: Productora De Alimentos Mexicanos | F51: César Flores | G51: Ramón Pérez | H51: Línea de Te bebible Nestea y REFI | I51: 30000000 | J51: MXN | L51: - | M51: - | N51: - | O51: - | P51: - | R51: 30000000 | S51: - | T51: Equipment | U51: Opportunity Identified | V51: Food Processing Equipment | W51: Engen Capital Financed | X51: New Origination | Y51: CapEx Lines | Z51: True Lease | AB51: 46080 | AC51: Middle market | AD51: No | AE51: No | AF51: Yucatán | AG51: Food Bev & Ag
A52: MXN | B52: SFOP0006026931 | C52: SWATT LMM 1 | D52: Lower middle market | E52: MICAR TRUCKINGS | F52: Genaro Villareal | G52: Fernanda Rangel | H52: Compra Pasivos | I52: 2790000 | J52: MXN | L52: - | M52: - | N52: Sin competidor | O52: - | P52: - | R52: 2790000 | S52: - | T52: Equipment | U52: In Credit | V52: Trailers | W52: Engen Capital Financed | X52: New Origination | Y52: External Refinancing | Z52: Term Loan | AB52: 46079 | AC52: Lower middle market | AD52: No | AE52: No | AF52: Nuevo León | AG52: Transportation
A53: MXN | B53: SFOP0006027309 | C53: SWATT LMM 2 | D53: Middle market | E53: International Metals de México | F53: Ivan Mosqueda | G53: Cynthia Diaz | H53: Equipos 2026 | I53: 20065865 | J53: MXN | L53: - | M53: - | N53: BBVA Bancomer | O53: - | P53: - | R53: 20065865 | S53: - | T53: Equipment | U53: Opportunity Identified | V53: Manufacturing Equipment | W53: Engen Capital Financed | X53: New Origination | Y53: CapEx Lines | Z53: True Lease | AB53: 46076 | AC53: Middle market | AD53: No | AE53: No | AF53: Estado de México | AG53: Industrial Products & Services

Sheet Diccionario
A1: FullName | B1: Region
A2: Pablo Perez | B2: Fleet
A3: Joaquin Padilla | B3: Fleet
A4: Gisell Trujillo | B4: Fleet
A5: Miroslava Parra | B5: Fleet
A6: Patricia Silva | B6: Fleet
A7: Alejandro Monteón | B7: LMM 1
A8: Roberto Anaya | B8: LMM 1
A9: Karen Davila | B9: LMM 1
A10: Juan Villaseñor | B10: LMM 1
A11: Gerardo Vazquez | B11: LMM 1
A12: Carlos Ramos | B12: LMM 1
... A38: Ilan Mizrahi | B38: LMM 5
B39: LMM 5
A40: Yenisei Garcia | B40: Capital Markets
A41: Herbert Bouchez | B41: Capital Markets
A42: Herbert Bouchez | B42: Capital Markets
A43: Alvaro de Garay | B43: Capital Markets
A44: Dulce Villegas | B44: Guadalajara
A45: Samuel Cepeda | B45: Guadalajara
A46: Omar Rodríguez | B46: Guadalajara
A47: Daniel Castillo | B47: Guadalajara
A48: Natalia Bernat | B48: Guadalajara
A49: Fernando Carbajal | B49: Guadalajara
A50: Miguel Ortiz | B50: Guadalajara
B51: Guadalajara
A52: Kenia Martinez | B52: México 1
A53: Juan Rosas | B53: México 2
A54: Fernando Martin | B54: México 1
A55: Edith Sánchez | B55: México 1
A56: - | B56: México 1
A57: Armando Estrada | B57: México 1
A58: Patricia Jurado | B58: México 1
A59: Rafael Garcia | B59: México 2
A60: Octavio Chimal | B60: México 2
A61: Hernan Aguilar | B61: México 2
A62: David Shaw | B62: México 2
A63: Marco Cohen | B63: México 2
... A67: Dorly Rabago | B67: México 1
A68: Ivan Parra | B68: México 3 | C68: Factoraje
A69: Mario Garcia | B69: México 3
A70: Abraham Mejia | B70: México 3
A71: Brenda Vargas | B71: Monterrey
A72: Miguel Antunez | B72: Monterrey
A73: Gerardo Pedroza | B73: Monterrey
A74: Gabriela Lopez | B74: Monterrey
A75: Juan Edgar Zepeda | B75: Monterrey
A76: Sergio Mange | B76: Monterrey
A77: Ricardo Meza | B77: Monterrey
A78: Alfonso Ortiz | B78: Monterrey
A79: Ivan Gonzalez | B79: Monterrey
A80: Marianna Peña | B80: Guadalajara
... A91: Rodrigo Velazquez | B91: Vendor
B92: Vendor & Energy
A93: Nefi Aranda | B93: LMM 4
A94: Josue Olvera | B94: Estructurados Core
A95: Capital Markets | B95: Alvaro de Garay
A96: Edgar Rodriguez | B96: Monterrey
A97: Ricardo Ramirez | B97: LMM 3
A98: Vadir Peña | B98: LMM 3
